Workbook

Sheet E-impôts
A1: NCC | B1: Nom | C1: Portefeuille | D1: Adhesion | E1: N° Adhésion | F1: Adresse | G1: Regime | H1: Forme juridique | I1: Dirigeant | J1: =I268 -> 0 | K1: N°RCCM | L1: Centre d'impôts | M1: section | N1: parcelle | O1: codeacti | P1: montcapit
A2: 1850348X | B2: 5 PAINS ET 2 POISSONS | C2: =VLOOKUP(A2,Feuil2!$A$1:$AA$298,4,0) -> CABINET CFA | D2: 44224 | E2: =VLOOKUP('E-impôts'!A2,Feuil2!$A$1:$AA$298,8,0) -> DCK-CGA2021-Q165 | F2: =VLOOKUP('E-impôts'!A2,Feuil2!$A$1:$AA$298,24,0) -> COCODY CENTRE FACE INADES | G2: =VLOOKUP('E-impôts'!A2,Feuil2!$A$1:$AA$298,11,0) -> TEE | H2: =VLOOKUP('E-impôts'!A2,Feuil2!$A$1:$AA$298,10,0) -> SARL | I2: =VLOOKUP('E-impôts'!A2,Feuil2!$A$1:$AA$298,5,0) -> NULL | J2: =VLOOKUP('E-impôts'!A2,Feuil2!$A$1:$AA$298,19,0) -> 708047428 | K2: =VLOOKUP('E-impôts'!A2,Feuil2!$A$1:$AA$298,9,0) -> NULL | L2: =VLOOKUP('E-impôts'!A2,Feuil2!$A$1:$AA$298,15,0) -> Cocody | M2: =VLOOKUP('E-impôts'!A2,Feuil2!$A$1:$AA$298,13,0) -> NULL | N2: =VLOOKUP('E-impôts'!A2,Feuil2!$A$1:$AA$298,14,0) -> NULL | O2: =VLOOKUP('E-impôts'!A2,Feuil2!$A$1:$AA$298,16,0) -> NULL | P2: =VLOOKUP(A2,Feuil2!$A$1:$AA$298,17,0) -> NULL
A3: 2304047J | B3: 2TK & ASSOCIES | C3: =VLOOKUP(A3,Feuil2!$A$1:$AA$298,4,0) -> #N/A | D3: 45322 | E3: =VLOOKUP('E-impôts'!A3,Feuil2!$A$1:$AA$298,8,0) -> DCK-CGA2024-A062 | F3: =VLOOKUP('E-impôts'!A3,Feuil2!$A$1:$AA$298,24,0) -> COCODY AKOUEDO, LAURIER 15 | G3: =VLOOKUP('E-impôts'!A3,Feuil2!$A$1:$AA$298,11,0) -> TEE | H3: =VLOOKUP('E-impôts'!A3,Feuil2!$A$1:$AA$298,10,0) -> SARL | I3: =VLOOKUP('E-impôts'!A3,Feuil2!$A$1:$AA$298,5,0) -> M. KOFFI N'ZI BILE MARIUS | J3: =VLOOKUP('E-impôts'!A3,Feuil2!$A$1:$AA$298,19,0) -> 0708889604 /0707038895 | K3: =VLOOKUP('E-impôts'!A3,Feuil2!$A$1:$AA$298,9,0) -> CI-ABJ-03-2023-B12-05066 | L3: =VLOOKUP('E-impôts'!A3,Feuil2!$A$1:$AA$298,15,0) -> Riviera II | M3: =VLOOKUP('E-impôts'!A3,Feuil2!$A$1:$AA$298,13,0) -> N/D | N3: =VLOOKUP('E-impôts'!A3,Feuil2!$A$1:$AA$298,14,0) -> N/D | O3: =VLOOKUP('E-impôts'!A3,Feuil2!$A$1:$AA$298,16,0) -> SCE0306 | P3: =VLOOKUP(A3,Feuil2!$A$1:$AA$298,17,0) -> 1000000
A4: 2037325R | B4: 2N IMMOBILIER | C4: =VLOOKUP(A4,Feuil2!$A$1:$AA$298,4,0) -> CABINET CFA | D4: 44224 | E4: =VLOOKUP('E-impôts'!A4,Feuil2!$A$1:$AA$298,8,0) -> DCK-CGA2019-A006 | F4: =VLOOKUP('E-impôts'!A4,Feuil2!$A$1:$AA$298,24,0) -> DEUX PLATEAUX SICOGI | G4: =VLOOKUP('E-impôts'!A4,Feuil2!$A$1:$AA$298,11,0) -> TEE | H4: =VLOOKUP('E-impôts'!A4,Feuil2!$A$1:$AA$298,10,0) -> SARL | I4: =VLOOKUP('E-impôts'!A4,Feuil2!$A$1:$AA$298,5,0) -> NULL | J4: =VLOOKUP('E-impôts'!A4,Feuil2!$A$1:$AA$298,19,0) -> 708514241 | K4: =VLOOKUP('E-impôts'!A4,Feuil2!$A$1:$AA$298,9,0) -> NULL | L4: =VLOOKUP('E-impôts'!A4,Feuil2!$A$1:$AA$298,15,0) -> II Plateaux I | M4: =VLOOKUP('E-impôts'!A4,Feuil2!$A$1:$AA$298,13,0) -> NULL | N4: =VLOOKUP('E-impôts'!A4,Feuil2!$A$1:$AA$298,14,0) -> NULL | O4: =VLOOKUP('E-impôts'!A4,Feuil2!$A$1:$AA$298,16,0) -> NULL | P4: =VLOOKUP(A4,Feuil2!$A$1:$AA$298,17,0) -> NULL
A5: 2244766Y | B5: ZOUE SEA ESTELLE | C5: =VLOOKUP(A5,Feuil2!$A$1:$AA$298,4,0) -> #N/A | D5: 45321 | E5: =VLOOKUP('E-impôts'!A5,Feuil2!$A$1:$AA$298,8,0) -> DCK-CGA2024-A088 | F5: =VLOOKUP('E-impôts'!A5,Feuil2!$A$1:$AA$298,24,0) -> COCODY RIVIERA AKOUEDO EXT | G5: =VLOOKUP('E-impôts'!A5,Feuil2!$A$1:$AA$298,11,0) -> TEE | H5: =VLOOKUP('E-impôts'!A5,Feuil2!$A$1:$AA$298,10,0) -> ENTREPRISE INDIVIDUELLE | I5: =VLOOKUP('E-impôts'!A5,Feuil2!$A$1:$AA$298,5,0) -> ZOUE SEA ESTELLE | J5: =VLOOKUP('E-impôts'!A5,Feuil2!$A$1:$AA$298,19,0) -> 505954425 | K5: =VLOOKUP('E-impôts'!A5,Feuil2!$A$1:$AA$298,9,0) -> CI-ABJ-032022-A10-04009 | L5: =VLOOKUP('E-impôts'!A5,Feuil2!$A$1:$AA$298,15,0) -> Cocody | M5: =VLOOKUP('E-impôts'!A5,Feuil2!$A$1:$AA$298,13,0) -> 0 | N5: =VLOOKUP('E-impôts'!A5,Feuil2!$A$1:$AA$298,14,0) -> 0 | O5: I550000 | P5: =VLOOKUP(A5,Feuil2!$A$1:$AA$298,17,0) -> 25000
A6: 1507261D | B6: ZANGRE HAROUNA | C6: =VLOOKUP('E-impôts'!A6,Feuil2!$A$1:$AA$298,4,0) -> DCK | D6: 43479 | E6: =VLOOKUP('E-impôts'!A6,Feuil2!$A$1:$AA$298,8,0) -> DCK-CGA2019-A024 | F6: =VLOOKUP('E-impôts'!A6,Feuil2!$A$1:$AA$298,24,0) -> COCODY SAINT JEAN | G6: =VLOOKUP('E-impôts'!A6,Feuil2!$A$1:$AA$298,11,0) -> TEE | H6: =VLOOKUP('E-impôts'!A6,Feuil2!$A$1:$AA$298,10,0) -> ENTREPRISE INDIVIDUELLE | I6: ZANGRE HAROUNA | J6: =VLOOKUP('E-impôts'!A6,Feuil2!$A$1:$AA$298,19,0) -> 505843545 | K6: =VLOOKUP('E-impôts'!A6,Feuil2!$A$1:$AA$298,9,0) -> NULL | L6: =VLOOKUP('E-impôts'!A6,Feuil2!$A$1:$AA$298,15,0) -> Cocody | M6: =VLOOKUP('E-impôts'!A6,Feuil2!$A$1:$AA$298,13,0) -> NULL | N6: =VLOOKUP('E-impôts'!A6,Feuil2!$A$1:$AA$298,14,0) -> NULL | O6: G470306 | P6: =VLOOKUP(A6,Feuil2!$A$1:$AA$298,17,0) -> NULL
A7: 0514603E | B7: ZALLE MAHAMOUD | C7: =VLOOKUP('E-impôts'!A7,Feuil2!$A$1:$AA$298,4,0) -> DCK | D7: 43479 | E7: =VLOOKUP('E-impôts'!A7,Feuil2!$A$1:$AA$298,8,0) -> DCK-CGA2019-A025 | F7: =VLOOKUP('E-impôts'!A7,Feuil2!$A$1:$AA$298,24,0) -> COCODY ANGRE-DJIBI | G7: =VLOOKUP('E-impôts'!A7,Feuil2!$A$1:$AA$298,11,0) -> TEE | H7: =VLOOKUP('E-impôts'!A7,Feuil2!$A$1:$AA$298,10,0) -> ENTREPRISE INDIVIDUELLE | I7: =VLOOKUP('E-impôts'!A7,Feuil2!$A$1:$AA$298,5,0) -> ZALLE MAHAMOUD | J7: =VLOOKUP('E-impôts'!A7,Feuil2!$A$1:$AA$298,19,0) -> 505938989 | K7: =VLOOKUP('E-impôts'!A7,Feuil2!$A$1:$AA$298,9,0) -> CI-ABJ-2011-A-6598 | L7: =VLOOKUP('E-impôts'!A7,Feuil2!$A$1:$AA$298,15,0) -> II Plateaux Djibi | M7: =VLOOKUP('E-impôts'!A7,Feuil2!$A$1:$AA$298,13,0) -> N/D | N7: =VLOOKUP('E-impôts'!A7,Feuil2!$A$1:$AA$298,14,0) -> N/D | O7: G470205 | P7: =VLOOKUP(A7,Feuil2!$A$1:$AA$298,17,0) -> 0
A8: 1709117F | B8: YONH LAINE THEOPHILE | C8: =VLOOKUP('E-impôts'!A8,Feuil2!$A$1:$AA$298,4,0) -> CABINET CFA | D8: 44224 | E8: =VLOOKUP('E-impôts'!A8,Feuil2!$A$1:$AA$298,8,0) -> DCK-CGA2021-Q144 | F8: =VLOOKUP('E-impôts'!A8,Feuil2!$A$1:$AA$298,24,0) -> RIVIERA BONOUMIN | G8: =VLOOKUP('E-impôts'!A8,Feuil2!$A$1:$AA$298,11,0) -> TEE | H8: =VLOOKUP('E-impôts'!A8,Feuil2!$A$1:$AA$298,10,0) -> ENTREPRISE INDIVIDUELLE | I8: =VLOOKUP('E-impôts'!A8,Feuil2!$A$1:$AA$298,5,0) -> NULL | J8: =VLOOKUP('E-impôts'!A8,Feuil2!$A$1:$AA$298,19,0) -> 757740578 | K8: =VLOOKUP('E-impôts'!A8,Feuil2!$A$1:$AA$298,9,0) -> NULL | L8: =VLOOKUP('E-impôts'!A8,Feuil2!$A$1:$AA$298,15,0) -> II Plateaux I | M8: =VLOOKUP('E-impôts'!A8,Feuil2!$A$1:$AA$298,13,0) -> NULL | N8: =VLOOKUP('E-impôts'!A8,Feuil2!$A$1:$AA$298,14,0) -> NULL | O8: =VLOOKUP('E-impôts'!A8,Feuil2!$A$1:$AA$298,16,0) -> NULL | P8: =VLOOKUP(A8,Feuil2!$A$1:$AA$298,17,0) -> NULL
A9: 0709432N | B9: YIRA SIAKA | C9: =VLOOKUP('E-impôts'!A9,Feuil2!$A$1:$AA$298,4,0) -> DCK | D9: 43479 | E9: =VLOOKUP('E-impôts'!A9,Feuil2!$A$1:$AA$298,8,0) -> DCK-CGA2019-A005 | F9: =VLOOKUP('E-impôts'!A9,Feuil2!$A$1:$AA$298,24,0) -> COCODY RIVIERA BONOUMIN | G9: =VLOOKUP('E-impôts'!A9,Feuil2!$A$1:$AA$298,11,0) -> TEE | H9: =VLOOKUP('E-impôts'!A9,Feuil2!$A$1:$AA$298,10,0) -> ENTREPRISE INDIVIDUELLE | I9: =VLOOKUP('E-impôts'!A9,Feuil2!$A$1:$AA$298,5,0) -> YIRA SIAKA | J9: =VLOOKUP('E-impôts'!A9,Feuil2!$A$1:$AA$298,19,0) -> 757740598 | K9: =VLOOKUP('E-impôts'!A9,Feuil2!$A$1:$AA$298,9,0) -> 09 BP 2525 ABIDJAN 09 | L9: =VLOOKUP('E-impôts'!A9,Feuil2!$A$1:$AA$298,15,0) -> II Plateaux III | M9: =VLOOKUP('E-impôts'!A9,Feuil2!$A$1:$AA$298,13,0) -> N/D | N9: =VLOOKUP('E-impôts'!A9,Feuil2!$A$1:$AA$298,14,0) -> N/D | O9: H490202 | P9: =VLOOKUP(A9,Feuil2!$A$1:$AA$298,17,0) -> 6000000
A10: 9410895U | B10: YERE LOU EPSE YACE Nenenan Blandine | C10: =VLOOKUP('E-impôts'!A10,Feuil2!$A$1:$AA$298,4,0) -> DCK | D10: 43479 | E10: =VLOOKUP('E-impôts'!A10,Feuil2!$A$1:$AA$298,8,0) -> DCK-CGA2019-A040 | F10: =VLOOKUP('E-impôts'!A10,Feuil2!$A$1:$AA$298,24,0) -> COCODY II PLATEAUX VALLON | G10: =VLOOKUP('E-impôts'!A10,Feuil2!$A$1:$AA$298,11,0) -> TEE | H10: =VLOOKUP('E-impôts'!A10,Feuil2!$A$1:$AA$298,10,0) -> ENTREPRISE INDIVIDUELLE | I10: YERE LOU EPSE YACE Nenenan Blandine | J10: =VLOOKUP('E-impôts'!A10,Feuil2!$A$1:$AA$298,19,0) -> 707070392 | K10: =VLOOKUP('E-impôts'!A10,Feuil2!$A$1:$AA$298,9,0) -> NULL | L10: =VLOOKUP('E-impôts'!A10,Feuil2!$A$1:$AA$298,15,0) -> II Plateaux II | M10: =VLOOKUP('E-impôts'!A10,Feuil2!$A$1:$AA$298,13,0) -> NULL | N10: =VLOOKUP('E-impôts'!A10,Feuil2!$A$1:$AA$298,14,0) -> NULL | O10: G4702 | P10: =VLOOKUP(A10,Feuil2!$A$1:$AA$298,17,0) -> NULL
A11: 0800398U | B11: YEBOUE EPSE BOUAH ADJOUA IRENE | C11: =VLOOKUP('E-impôts'!A11,Feuil2!$A$1:$AA$298,4,0) -> #N/A | D11: 43479 | E11: =VLOOKUP('E-impôts'!A11,Feuil2!$A$1:$AA$298,8,0) -> #N/A | F11: =VLOOKUP('E-impôts'!A11,Feuil2!$A$1:$AA$298,24,0) -> #N/A | G11: =VLOOKUP('E-impôts'!A11,Feuil2!$A$1:$AA$298,11,0) -> #N/A | H11: =VLOOKUP('E-impôts'!A11,Feuil2!$A$1:$AA$298,10,0) -> #N/A | I11: =VLOOKUP('E-impôts'!A11,Feuil2!$A$1:$AA$298,5,0) -> #N/A | J11: =VLOOKUP('E-impôts'!A11,Feuil2!$A$1:$AA$298,19,0) -> #N/A | K11: =VLOOKUP('E-impôts'!A11,Feuil2!$A$1:$AA$298,9,0) -> #N/A | L11: =VLOOKUP('E-impôts'!A11,Feuil2!$A$1:$AA$298,15,0) -> #N/A | M11: =VLOOKUP('E-impôts'!A11,Feuil2!$A$1:$AA$298,13,0) -> #N/A | N11: =VLOOKUP('E-impôts'!A11,Feuil2!$A$1:$AA$298,14,0) -> #N/A | O11: =VLOOKUP('E-impôts'!A11,Feuil2!$A$1:$AA$298,16,0) -> #N/A | P11: =VLOOKUP(A11,Feuil2!$A$1:$AA$298,17,0) -> #N/A
A12: 1865233X | B12: YAPO YAPO GHISLAIN CYRILLE | C12: =VLOOKUP('E-impôts'!A12,Feuil2!$A$1:$AA$298,4,0) -> DCK | D12: 44574 | E12: =VLOOKUP('E-impôts'!A12,Feuil2!$A$1:$AA$298,8,0) -> DCK-CGA-2022-J004 | F12: =VLOOKUP('E-impôts'!A12,Feuil2!$A$1:$AA$298,24,0) -> COCODY RIVIERA II | G12: =VLOOKUP('E-impôts'!A12,Feuil2!$A$1:$AA$298,11,0) -> TEE | H12: =VLOOKUP('E-impôts'!A12,Feuil2!$A$1:$AA$298,10,0) -> ENTREPRISE INDIVIDUELLE | I12: =VLOOKUP('E-impôts'!A12,Feuil2!$A$1:$AA$298,5,0) -> NULL | J12: =VLOOKUP('E-impôts'!A12,Feuil2!$A$1:$AA$298,19,0) -> 778120796 | K12: =VLOOKUP('E-impôts'!A12,Feuil2!$A$1:$AA$298,9,0) -> NULL | L12: =VLOOKUP('E-impôts'!A12,Feuil2!$A$1:$AA$298,15,0) -> Riviera I | M12: =VLOOKUP('E-impôts'!A12,Feuil2!$A$1:$AA$298,13,0) -> NULL | N12: =VLOOKUP('E-impôts'!A12,Feuil2!$A$1:$AA$298,14,0) -> NULL | O12: =VLOOKUP('E-impôts'!A12,Feuil2!$A$1:$AA$298,16,0) -> NULL | P12: =VLOOKUP(A12,Feuil2!$A$1:$AA$298,17,0) -> NULL
A13: 1345558K | B13: YAO N'GUESSAN ANGE-FABRICE | C13: =VLOOKUP('E-impôts'!A13,Feuil2!$A$1:$AA$298,4,0) -> CABINET CFA | D13: 44224 | E13: =VLOOKUP('E-impôts'!A13,Feuil2!$A$1:$AA$298,8,0) -> DCK-CGA2021-Q139 | F13: =VLOOKUP('E-impôts'!A13,Feuil2!$A$1:$AA$298,24,0) -> 0 | G13: =VLOOKUP('E-impôts'!A13,Feuil2!$A$1:$AA$298,11,0) -> TEE | H13: =VLOOKUP('E-impôts'!A13,Feuil2!$A$1:$AA$298,10,0) -> ENTREPRISE INDIVIDUELLE | I13: =VLOOKUP('E-impôts'!A13,Feuil2!$A$1:$AA$298,5,0) -> NULL | J13: =VLOOKUP('E-impôts'!A13,Feuil2!$A$1:$AA$298,19,0) -> 0 | K13: =VLOOKUP('E-impôts'!A13,Feuil2!$A$1:$AA$298,9,0) -> NULL | L13: =VLOOKUP('E-impôts'!A13,Feuil2!$A$1:$AA$298,15,0) -> II Plateaux I | M13: =VLOOKUP('E-impôts'!A13,Feuil2!$A$1:$AA$298,13,0) -> NULL | N13: =VLOOKUP('E-impôts'!A13,Feuil2!$A$1:$AA$298,14,0) -> NULL | O13: =VLOOKUP('E-impôts'!A13,Feuil2!$A$1:$AA$298,16,0) -> NULL | P13: =VLOOKUP(A13,Feuil2!$A$1:$AA$298,17,0) -> NULL
A14: 1212885P | B14: YAO N'Guessan Adele Epse Djedje | C14: =VLOOKUP('E-impôts'!A14,Feuil2!$A$1:$AA$298,4,0) -> DCK | D14: 43479 | E14: =VLOOKUP('E-impôts'!A14,Feuil2!$A$1:$AA$298,8,0) -> DCK-CGA2019-A027 | F14: =VLOOKUP('E-impôts'!A14,Feuil2!$A$1:$AA$298,24,0) -> RIVIERA BONOUMIN | G14: =VLOOKUP('E-impôts'!A14,Feuil2!$A$1:$AA$298,11,0) -> TEE | H14: =VLOOKUP('E-impôts'!A14,Feuil2!$A$1:$AA$298,10,0) -> ENTREPRISE INDIVIDUELLE | I14: =VLOOKUP('E-impôts'!A14,Feuil2!$A$1:$AA$298,5,0) -> YOA N'GUESSAN ADELE EPSE DJEDJE | J14: =VLOOKUP('E-impôts'!A14,Feuil2!$A$1:$AA$298,19,0) -> 505060740 | K14: =VLOOKUP('E-impôts'!A14,Feuil2!$A$1:$AA$298,9,0) -> CI-ABJ-2012-A-1024 | L14: =VLOOKUP('E-impôts'!A14,Feuil2!$A$1:$AA$298,15,0) -> II Plateaux III | M14: =VLOOKUP('E-impôts'!A14,Feuil2!$A$1:$AA$298,13,0) -> ABC | N14: =VLOOKUP('E-impôts'!A14,Feuil2!$A$1:$AA$298,14,0) -> 39 | O14: G470201 | P14: =VLOOKUP(A14,Feuil2!$A$1:$AA$298,17,0) -> 0
A15: 1900445C | B15: YAO N'DRI FRANCK AIME | C15: =VLOOKUP('E-impôts'!A15,Feuil2!$A$1:$AA$298,4,0) -> DCK | D15: 43847 | E15: =VLOOKUP('E-impôts'!A15,Feuil2!$A$1:$AA$298,8,0) -> DCK-CGA2020-A051 | F15: =VLOOKUP('E-impôts'!A15,Feuil2!$A$1:$AA$298,24,0) -> COCODY BONOUMIN | G15: =VLOOKUP('E-impôts'!A15,Feuil2!$A$1:$AA$298,11,0) -> TEE | H15: =VLOOKUP('E-impôts'!A15,Feuil2!$A$1:$AA$298,10,0) -> ENTREPRISE INDIVIDUELLE | I15: =VLOOKUP('E-impôts'!A15,Feuil2!$A$1:$AA$298,5,0) -> YAO N'DRI FRANCK AIME | J15: =VLOOKUP('E-impôts'!A15,Feuil2!$A$1:$AA$298,19,0) -> 708112943 | K15: =VLOOKUP('E-impôts'!A15,Feuil2!$A$1:$AA$298,9,0) -> 0 | L15: =VLOOKUP('E-impôts'!A15,Feuil2!$A$1:$AA$298,15,0) -> II Plateaux III | M15: =VLOOKUP('E-impôts'!A15,Feuil2!$A$1:$AA$298,13,0) -> ABH | N15: =VLOOKUP('E-impôts'!A15,Feuil2!$A$1:$AA$298,14,0) -> 10 | O15: Q860100 | P15: =VLOOKUP(A15,Feuil2!$A$1:$AA$298,17,0) -> 0
A16: 2242835K | B16: YANKAN-MO | C16: =VLOOKUP('E-impôts'!A16,Feuil2!$A$1:$AA$298,4,0) -> GOHI | D16: 44951 | E16: =VLOOKUP('E-impôts'!A16,Feuil2!$A$1:$AA$298,8,0) -> DCK-CGA2023-J018 | F16: =VLOOKUP('E-impôts'!A16,Feuil2!$A$1:$AA$298,24,0) -> COCODY ANGRE 7E TRANCHE OSCARS | G16: =VLOOKUP('E-impôts'!A16,Feuil2!$A$1:$AA$298,11,0) -> TEE | H16: =VLOOKUP('E-impôts'!A16,Feuil2!$A$1:$AA$298,10,0) -> SARL | I16: =VLOOKUP('E-impôts'!A16,Feuil2!$A$1:$AA$298,5,0) -> NULL | J16: =VLOOKUP('E-impôts'!A16,Feuil2!$A$1:$AA$298,19,0) -> 757118226 | K16: =VLOOKUP('E-impôts'!A16,Feuil2!$A$1:$AA$298,9,0) -> NULL | L16: =VLOOKUP('E-impôts'!A16,Feuil2!$A$1:$AA$298,15,0) -> II Plateaux I | M16: =VLOOKUP('E-impôts'!A16,Feuil2!$A$1:$AA$298,13,0) -> NULL | N16: =VLOOKUP('E-impôts'!A16,Feuil2!$A$1:$AA$298,14,0) -> NULL | O16: =VLOOKUP('E-impôts'!A16,Feuil2!$A$1:$AA$298,16,0) -> NULL | P16: =VLOOKUP(A16,Feuil2!$A$1:$AA$298,17,0) -> NULL
A17: 1800364N | B17: YAKIME DESIGN | C17: =VLOOKUP('E-impôts'!A17,Feuil2!$A$1:$AA$298,4,0) -> #N/A | D17: 43845 | E17: =VLOOKUP('E-impôts'!A17,Feuil2!$A$1:$AA$298,8,0) -> #N/A | F17: =VLOOKUP('E-impôts'!A17,Feuil2!$A$1:$AA$298,24,0) -> #N/A | G17: =VLOOKUP('E-impôts'!A17,Feuil2!$A$1:$AA$298,11,0) -> #N/A | H17: =VLOOKUP('E-impôts'!A17,Feuil2!$A$1:$AA$298,10,0) -> #N/A | I17: TOURE EPSE M'BAYE MARIAM | J17: =VLOOKUP('E-impôts'!A17,Feuil2!$A$1:$AA$298,19,0) -> #N/A | K17: =VLOOKUP('E-impôts'!A17,Feuil2!$A$1:$AA$298,9,0) -> #N/A | L17: =VLOOKUP('E-impôts'!A17,Feuil2!$A$1:$AA$298,15,0) -> #N/A | M17: =VLOOKUP('E-impôts'!A17,Feuil2!$A$1:$AA$298,13,0) -> #N/A | N17: =VLOOKUP('E-impôts'!A17,Feuil2!$A$1:$AA$298,14,0) -> #N/A | O17: N810001 | P17: =VLOOKUP(A17,Feuil2!$A$1:$AA$298,17,0) -> #N/A
A18: 1827528R | B18: YAGUERA & COMPAGNIE | C18: =VLOOKUP('E-impôts'!A18,Feuil2!$A$1:$AA$298,4,0) -> DCK | D18: 43479 | E18: =VLOOKUP('E-impôts'!A18,Feuil2!$A$1:$AA$298,8,0) -> DCK-CGA2019-A007 | F18: =VLOOKUP('E-impôts'!A18,Feuil2!$A$1:$AA$298,24,0) -> COCODY ANGRE 7E TRANCHE | G18: =VLOOKUP('E-impôts'!A18,Feuil2!$A$1:$AA$298,11,0) -> TEE | H18: =VLOOKUP('E-impôts'!A18,Feuil2!$A$1:$AA$298,10,0) -> SARL | I18: YACE EPSE ANGUERA NINA CATHERINE | J18: =VLOOKUP('E-impôts'!A18,Feuil2!$A$1:$AA$298,19,0) -> 789844008 | K18: =VLOOKUP('E-impôts'!A18,Feuil2!$A$1:$AA$298,9,0) -> NULL | L18: =VLOOKUP('E-impôts'!A18,Feuil2!$A$1:$AA$298,15,0) -> II Plateaux I | M18: =VLOOKUP('E-impôts'!A18,Feuil2!$A$1:$AA$298,13,0) -> NULL | N18: =VLOOKUP('E-impôts'!A18,Feuil2!$A$1:$AA$298,14,0) -> NULL | O18: L680100 | P18: =VLOOKUP(A18,Feuil2!$A$1:$AA$298,17,0) -> NULL
A19: 0714977C | B19: YACE EMMANUELLE | C19: =VLOOKUP('E-impôts'!A19,Feuil2!$A$1:$AA$298,4,0) -> DCK | D19: 43479 | E19: =VLOOKUP('E-impôts'!A19,Feuil2!$A$1:$AA$298,8,0) -> DCK-CGA2019-A014 | F19: =VLOOKUP('E-impôts'!A19,Feuil2!$A$1:$AA$298,24,0) -> COCODY ANGRE 7E TRANCHE | G19: =VLOOKUP('E-impôts'!A19,Feuil2!$A$1:$AA$298,11,0) -> TEE | H19: =VLOOKUP('E-impôts'!A19,Feuil2!$A$1:$AA$298,10,0) -> ENTREPRISE INDIVIDUELLE | I19: =VLOOKUP('E-impôts'!A19,Feuil2!$A$1:$AA$298,5,0) -> YACE EMMANUELLE | J19: =VLOOKUP('E-impôts'!A19,Feuil2!$A$1:$AA$298,19,0) -> 707070392 | K19: =VLOOKUP('E-impôts'!A19,Feuil2!$A$1:$AA$298,9,0) -> CI-ABJ-2014-A-1249 | L19: =VLOOKUP('E-impôts'!A19,Feuil2!$A$1:$AA$298,15,0) -> II Plateaux III | M19: =VLOOKUP('E-impôts'!A19,Feuil2!$A$1:$AA$298,13,0) -> OZ | N19: =VLOOKUP('E-impôts'!A19,Feuil2!$A$1:$AA$298,14,0) -> 207 | O19: L680100 | P19: =VLOOKUP(A19,Feuil2!$A$1:$AA$298,17,0) -> 0
A20: 2240985C | B20: X-YOLO | C20: =VLOOKUP('E-impôts'!A20,Feuil2!$A$1:$AA$298,4,0) -> #N/A | D20: 45316 | E20: =VLOOKUP('E-impôts'!A20,Feuil2!$A$1:$AA$298,8,0) -> DCK-CGA2024-A033 | F20: =VLOOKUP('E-impôts'!A20,Feuil2!$A$1:$AA$298,24,0) -> BINGERVILLE | G20: =VLOOKUP('E-impôts'!A20,Feuil2!$A$1:$AA$298,11,0) -> TEE | H20: =VLOOKUP('E-impôts'!A20,Feuil2!$A$1:$AA$298,10,0) -> SARL | I20: =VLOOKUP('E-impôts'!A20,Feuil2!$A$1:$AA$298,5,0) -> WANG JINGZHONG | J20: =VLOOKUP('E-impôts'!A20,Feuil2!$A$1:$AA$298,19,0) -> 768151168 | K20: =VLOOKUP('E-impôts'!A20,Feuil2!$A$1:$AA$298,9,0) -> CI-ABJ-03-2022-B13-03433 | L20: =VLOOKUP('E-impôts'!A20,Feuil2!$A$1:$AA$298,15,0) -> Bingerville | M20: =VLOOKUP('E-impôts'!A20,Feuil2!$A$1:$AA$298,13,0) -> 0 | N20: =VLOOKUP('E-impôts'!A20,Feuil2!$A$1:$AA$298,14,0) -> 0 | O20: =VLOOKUP('E-impôts'!A20,Feuil2!$A$1:$AA$298,16,0) -> 0 | P20: =VLOOKUP(A20,Feuil2!$A$1:$AA$298,17,0) -> 1000000
A21: 1709973R | B21: WILSEM CONSULTING | C21: =VLOOKUP('E-impôts'!A21,Feuil2!$A$1:$AA$298,4,0) -> #N/A | D21: 45322 | E21: =VLOOKUP('E-impôts'!A21,Feuil2!$A$1:$AA$298,8,0) -> DCK-CGA2024-A059 | F21: =VLOOKUP('E-impôts'!A21,Feuil2!$A$1:$AA$298,24,0) -> ABIDJAN COCODY ATTOBAN | G21: =VLOOKUP('E-impôts'!A21,Feuil2!$A$1:$AA$298,11,0) -> TEE | H21: =VLOOKUP('E-impôts'!A21,Feuil2!$A$1:$AA$298,10,0) -> SARL | I21: =VLOOKUP('E-impôts'!A21,Feuil2!$A$1:$AA$298,5,0) -> TONYI AMEGADJIN | J21: =VLOOKUP('E-impôts'!A21,Feuil2!$A$1:$AA$298,19,0) -> 05 45 83 24 70 / 07 48 71 99 0 | K21: =VLOOKUP('E-impôts'!A21,Feuil2!$A$1:$AA$298,9,0) -> CI-ABJ-2016-B-00665 | L21: =VLOOKUP('E-impôts'!A21,Feuil2!$A$1:$AA$298,15,0) -> II Plateaux III | M21: =VLOOKUP('E-impôts'!A21,Feuil2!$A$1:$AA$298,13,0) -> PW | N21: =VLOOKUP('E-impôts'!A21,Feuil2!$A$1:$AA$298,14,0) -> 1054 | O21: =VLOOKUP('E-impôts'!A21,Feuil2!$A$1:$AA$298,16,0) -> SCE0801 | P21: =VLOOKUP(A21,Feuil2!$A$1:$AA$298,17,0) -> 1.000.000
A22: 1849567E | B22: WEST AFRICA FOOD AS-AGRILAND | C22: =VLOOKUP('E-impôts'!A22,Feuil2!$A$1:$AA$298,4,0) -> CABINET CFA | D22: 44592 | E22: =VLOOKUP('E-impôts'!A22,Feuil2!$A$1:$AA$298,8,0) -> DCK-CGA2022-J036 | F22: =VLOOKUP('E-impôts'!A22,Feuil2!$A$1:$AA$298,24,0) -> COCODY II PLATEAUX 7E TRANCHE | G22: =VLOOKUP('E-impôts'!A22,Feuil2!$A$1:$AA$298,11,0) -> TEE | H22: =VLOOKUP('E-impôts'!A22,Feuil2!$A$1:$AA$298,10,0) -> SARL | I22: =VLOOKUP('E-impôts'!A22,Feuil2!$A$1:$AA$298,5,0) -> NULL | J22: =VLOOKUP('E-impôts'!A22,Feuil2!$A$1:$AA$298,19,0) -> 505423838 | K22: =VLOOKUP('E-impôts'!A22,Feuil2!$A$1:$AA$298,9,0) -> NULL | L22: =VLOOKUP('E-impôts'!A22,Feuil2!$A$1:$AA$298,15,0) -> II Plateaux I | M22: =VLOOKUP('E-impôts'!A22,Feuil2!$A$1:$AA$298,13,0) -> NULL | N22: =VLOOKUP('E-impôts'!A22,Feuil2!$A$1:$AA$298,14,0) -> NULL | O22: =VLOOKUP('E-impôts'!A22,Feuil2!$A$1:$AA$298,16,0) -> NULL | P22: =VLOOKUP(A22,Feuil2!$A$1:$AA$298,17,0) -> NULL
A23: 2300875R | B23: WELDING VISION COTE D'IVOIRE | C23: =VLOOKUP('E-impôts'!A23,Feuil2!$A$1:$AA$298,4,0) -> #N/A | D23: 45316 | E23: =VLOOKUP('E-impôts'!A23,Feuil2!$A$1:$AA$298,8,0) -> DCK-CGA2024-A031 | F23: =VLOOKUP('E-impôts'!A23,Feuil2!$A$1:$AA$298,24,0) -> COCODY ANGRE SOLEIL 3 | G23: =VLOOKUP('E-impôts'!A23,Feuil2!$A$1:$AA$298,11,0) -> TEE | H23: =VLOOKUP('E-impôts'!A23,Feuil2!$A$1:$AA$298,10,0) -> SARL | I23: =VLOOKUP('E-impôts'!A23,Feuil2!$A$1:$AA$298,5,0) -> EKUE ADADE | J23: =VLOOKUP('E-impôts'!A23,Feuil2!$A$1:$AA$298,19,0) -> 757263143 | K23: =VLOOKUP('E-impôts'!A23,Feuil2!$A$1:$AA$298,9,0) -> CI-ABJ-03-2023-B13-02205 | L23: =VLOOKUP('E-impôts'!A23,Feuil2!$A$1:$AA$298,15,0) -> II Plateaux Djibi | M23: =VLOOKUP('E-impôts'!A23,Feuil2!$A$1:$AA$298,13,0) -> 0 | N23: =VLOOKUP('E-impôts'!A23,Feuil2!$A$1:$AA$298,14,0) -> 0 | O23: =VLOOKUP('E-impôts'!A23,Feuil2!$A$1:$AA$298,16,0) -> 0 | P23: =VLOOKUP(A23,Feuil2!$A$1:$AA$298,17,0) -> 1000000
A24: 2242769N | B24: VK SERVICES PLUS | C24: =VLOOKUP('E-impôts'!A24,Feuil2!$A$1:$AA$298,4,0) -> CABINET CFA | D24: 44774 | E24: =VLOOKUP('E-impôts'!A24,Feuil2!$A$1:$AA$298,8,0) -> DCK-CGA2022-J077 | F24: =VLOOKUP('E-impôts'!A24,Feuil2!$A$1:$AA$298,24,0) -> COCODY ANGRE DJIBI | G24: =VLOOKUP('E-impôts'!A24,Feuil2!$A$1:$AA$298,11,0) -> TEE | H24: =VLOOKUP('E-impôts'!A24,Feuil2!$A$1:$AA$298,10,0) -> SARL | I24: =VLOOKUP('E-impôts'!A24,Feuil2!$A$1:$AA$298,5,0) -> NULL | J24: =VLOOKUP('E-impôts'!A24,Feuil2!$A$1:$AA$298,19,0) -> 757417993 | K24: =VLOOKUP('E-impôts'!A24,Feuil2!$A$1:$AA$298,9,0) -> NULL | L24: =VLOOKUP('E-impôts'!A24,Feuil2!$A$1:$AA$298,15,0) -> II Plateaux Djibi | M24: =VLOOKUP('E-impôts'!A24,Feuil2!$A$1:$AA$298,13,0) -> NULL | N24: =VLOOKUP('E-impôts'!A24,Feuil2!$A$1:$AA$298,14,0) -> NULL | O24: =VLOOKUP('E-impôts'!A24,Feuil2!$A$1:$AA$298,16,0) -> NULL | P24: =VLOOKUP(A24,Feuil2!$A$1:$AA$298,17,0) -> NULL
A25: 2243769Z | B25: VIDAS GROUP HOLDING | C25: =VLOOKUP('E-impôts'!A25,Feuil2!$A$1:$AA$298,4,0) -> DCK | D25: 44956 | E25: =VLOOKUP('E-impôts'!A25,Feuil2!$A$1:$AA$298,8,0) -> DCK-CGA-2022-J031 | F25: =VLOOKUP('E-impôts'!A25,Feuil2!$A$1:$AA$298,24,0) -> COCODY BONOUMIN | G25: =VLOOKUP('E-impôts'!A25,Feuil2!$A$1:$AA$298,11,0) -> TEE | H25: =VLOOKUP('E-impôts'!A25,Feuil2!$A$1:$AA$298,10,0) -> SARL | I25: =VLOOKUP('E-impôts'!A25,Feuil2!$A$1:$AA$298,5,0) -> DJOGBENOU | J25: =VLOOKUP('E-impôts'!A25,Feuil2!$A$1:$AA$298,19,0) -> 708414136 | K25: =VLOOKUP('E-impôts'!A25,Feuil2!$A$1:$AA$298,9,0) -> CI-ABJ-03-B17-00080 | L25: =VLOOKUP('E-impôts'!A25,Feuil2!$A$1:$AA$298,15,0) -> II Plateaux III | M25: =VLOOKUP('E-impôts'!A25,Feuil2!$A$1:$AA$298,13,0) -> AO | N25: =VLOOKUP('E-impôts'!A25,Feuil2!$A$1:$AA$298,14,0) -> 13 | O25: P850400 | P25: =VLOOKUP(A25,Feuil2!$A$1:$AA$298,17,0) -> 10000000
A26: 1906134N | B26: UNIDIS INTER | C26: =VLOOKUP('E-impôts'!A26,Feuil2!$A$1:$AA$298,4,0) -> #N/A | D26: 43858 | E26: =VLOOKUP('E-impôts'!A26,Feuil2!$A$1:$AA$298,8,0) -> DCK-CGA2021-Q147 | F26: =VLOOKUP('E-impôts'!A26,Feuil2!$A$1:$AA$298,24,0) -> 01 BP 10683 ABJ 01 | G26: =VLOOKUP('E-impôts'!A26,Feuil2!$A$1:$AA$298,11,0) -> RME | H26: =VLOOKUP('E-impôts'!A26,Feuil2!$A$1:$AA$298,10,0) -> SARL | I26: =VLOOKUP('E-impôts'!A26,Feuil2!$A$1:$AA$298,5,0) -> YOUZAN AYA ROSINE-LEA Epse N'GUESSAN | J26: =VLOOKUP('E-impôts'!A26,Feuil2!$A$1:$AA$298,19,0) -> 749933263 | K26: =VLOOKUP('E-impôts'!A26,Feuil2!$A$1:$AA$298,9,0) -> CI-ABJ-2019-B-02186 | L26: =VLOOKUP('E-impôts'!A26,Feuil2!$A$1:$AA$298,15,0) -> II Pateaux I | M26: =VLOOKUP('E-impôts'!A26,Feuil2!$A$1:$AA$298,13,0) -> ND | N26: =VLOOKUP('E-impôts'!A26,Feuil2!$A$1:$AA$298,14,0) -> ND | O26: =VLOOKUP('E-impôts'!A26,Feuil2!$A$1:$AA$298,16,0) -> IND1504 | P26: =VLOOKUP(A26,Feuil2!$A$1:$AA$298,17,0) -> 1000000
A27: 2303775P | B27: TRAZIE LOU NABOUE NADEGE | C27: =VLOOKUP('E-impôts'!A27,Feuil2!$A$1:$AA$298,4,0) -> MARIAME | D27: 45315 | E27: =VLOOKUP('E-impôts'!A27,Feuil2!$A$1:$AA$298,8,0) -> DCK-CGA2024-A023 | F27: =VLOOKUP('E-impôts'!A27,Feuil2!$A$1:$AA$298,24,0) -> FAYA | G27: =VLOOKUP('E-impôts'!A27,Feuil2!$A$1:$AA$298,11,0) -> TEE | H27: =VLOOKUP('E-impôts'!A27,Feuil2!$A$1:$AA$298,10,0) -> ENTREPRISE INDIVIDUELLE | I27: =VLOOKUP('E-impôts'!A27,Feuil2!$A$1:$AA$298,5,0) -> TRAZIE LOU NABOUE NADEGE | J27: =VLOOKUP('E-impôts'!A27,Feuil2!$A$1:$AA$298,19,0) -> 709899557 | K27: =VLOOKUP('E-impôts'!A27,Feuil2!$A$1:$AA$298,9,0) -> CI-ABJ-03-2023-A10-02618 | L27: =VLOOKUP('E-impôts'!A27,Feuil2!$A$1:$AA$298,15,0) -> II Plateaux III | M27: =VLOOKUP('E-impôts'!A27,Feuil2!$A$1:$AA$298,13,0) -> VZ | N27: =VLOOKUP('E-impôts'!A27,Feuil2!$A$1:$AA$298,14,0) -> 201 | O27: =VLOOKUP('E-impôts'!A27,Feuil2!$A$1:$AA$298,16,0) -> SCE19001 | P27: =VLOOKUP(A27,Feuil2!$A$1:$AA$298,17,0) -> 1000000
A28: 0313308U | B28: TRAZIE Houlie Lucie | C28: =VLOOKUP('E-impôts'!A28,Feuil2!$A$1:$AA$298,4,0) -> CABINET CFA | D28: 44589 | E28: =VLOOKUP('E-impôts'!A28,Feuil2!$A$1:$AA$298,8,0) -> DCK-CGA2022-J056 | F28: =VLOOKUP('E-impôts'!A28,Feuil2!$A$1:$AA$298,24,0) -> COCODY II PLATEAUX AGHIEN | G28: =VLOOKUP('E-impôts'!A28,Feuil2!$A$1:$AA$298,11,0) -> TEE | H28: =VLOOKUP('E-impôts'!A28,Feuil2!$A$1:$AA$298,10,0) -> ENTREPRISE INDIVIDUELLE | I28: =VLOOKUP('E-impôts'!A28,Feuil2!$A$1:$AA$298,5,0) -> NULL | J28: =VLOOKUP('E-impôts'!A28,Feuil2!$A$1:$AA$298,19,0) -> 2722426745 | K28: =VLOOKUP('E-impôts'!A28,Feuil2!$A$1:$AA$298,9,0) -> NULL | L28: =VLOOKUP('E-impôts'!A28,Feuil2!$A$1:$AA$298,15,0) -> II Plateaux III | M28: =VLOOKUP('E-impôts'!A28,Feuil2!$A$1:$AA$298,13,0) -> NULL | N28: =VLOOKUP('E-impôts'!A28,Feuil2!$A$1:$AA$298,14,0) -> NULL | O28: =VLOOKUP('E-impôts'!A28,Feuil2!$A$1:$AA$298,16,0) -> NULL | P28: =VLOOKUP(A28,Feuil2!$A$1:$AA$298,17,0) -> NULL
A29: 2016878X | B29: TRAN TRONG HOANG | C29: =VLOOKUP('E-impôts'!A29,Feuil2!$A$1:$AA$298,4,0) -> Abdoulaye | D29: 45315 | E29: =VLOOKUP('E-impôts'!A29,Feuil2!$A$1:$AA$298,8,0) -> DCK-CGA2024-A022 | F29: =VLOOKUP('E-impôts'!A29,Feuil2!$A$1:$AA$298,24,0) -> BINGERVILLE COUP DE FREIN | G29: =VLOOKUP('E-impôts'!A29,Feuil2!$A$1:$AA$298,11,0) -> TEE | H29: =VLOOKUP('E-impôts'!A29,Feuil2!$A$1:$AA$298,10,0) -> ENTREPRISE INDIVIDUELLE | I29: =VLOOKUP('E-impôts'!A29,Feuil2!$A$1:$AA$298,5,0) -> TRAN TRONG HOANG | J29: =VLOOKUP('E-impôts'!A29,Feuil2!$A$1:$AA$298,19,0) -> 708537463 | K29: =VLOOKUP('E-impôts'!A29,Feuil2!$A$1:$AA$298,9,0) -> CI-ABJ-2018-A-05921 | L29: =VLOOKUP('E-impôts'!A29,Feuil2!$A$1:$AA$298,15,0) -> Bingerville | M29: =VLOOKUP('E-impôts'!A29,Feuil2!$A$1:$AA$298,13,0) -> 0 | N29: =VLOOKUP('E-impôts'!A29,Feuil2!$A$1:$AA$298,14,0) -> 0 | O29: =VLOOKUP('E-impôts'!A29,Feuil2!$A$1:$AA$298,16,0) -> SCE0204 | P29: =VLOOKUP(A29,Feuil2!$A$1:$AA$298,17,0) -> 1000000
A30: 2244784P | B30: TRADE OF ROYAL MAX | C30: =VLOOKUP('E-impôts'!A30,Feuil2!$A$1:$AA$298,4,0) -> #N/A | D30: 45318 | E30: =VLOOKUP('E-impôts'!A30,Feuil2!$A$1:$AA$298,8,0) -> DCK-CGA2024-A025 | F30: =VLOOKUP('E-impôts'!A30,Feuil2!$A$1:$AA$298,24,0) -> 2 PLATEAUX VALLON | G30: =VLOOKUP('E-impôts'!A30,Feuil2!$A$1:$AA$298,11,0) -> TEE | H30: =VLOOKUP('E-impôts'!A30,Feuil2!$A$1:$AA$298,10,0) -> SARL | I30: =VLOOKUP('E-impôts'!A30,Feuil2!$A$1:$AA$298,5,0) -> LI XIAOMING | J30: =VLOOKUP('E-impôts'!A30,Feuil2!$A$1:$AA$298,19,0) -> 711129045 | K30: =VLOOKUP('E-impôts'!A30,Feuil2!$A$1:$AA$298,9,0) -> CI-ABJ-03-2022-B13-10636 | L30: =VLOOKUP('E-impôts'!A30,Feuil2!$A$1:$AA$298,15,0) -> II Plateaux III | M30: =VLOOKUP('E-impôts'!A30,Feuil2!$A$1:$AA$298,13,0) -> N/D | N30: =VLOOKUP('E-impôts'!A30,Feuil2!$A$1:$AA$298,14,0) -> N/D | O30: =VLOOKUP('E-impôts'!A30,Feuil2!$A$1:$AA$298,16,0) -> N/D | P30: =VLOOKUP(A30,Feuil2!$A$1:$AA$298,17,0) -> 1Â 000 000
A31: 1707216G | B31: TOUNDE QUICAILLERIE | C31: =VLOOKUP('E-impôts'!A31,Feuil2!$A$1:$AA$298,4,0) -> ZADI | D31: 44574 | E31: =VLOOKUP('E-impôts'!A31,Feuil2!$A$1:$AA$298,8,0) -> DCK-CGA2020-A074 | F31: =VLOOKUP('E-impôts'!A31,Feuil2!$A$1:$AA$298,24,0) -> BINGERVILLE | G31: =VLOOKUP('E-impôts'!A31,Feuil2!$A$1:$AA$298,11,0) -> TEE | H31: =VLOOKUP('E-impôts'!A31,Feuil2!$A$1:$AA$298,10,0) -> ENTREPRISE INDIVIDUELLE | I31: =VLOOKUP('E-impôts'!A31,Feuil2!$A$1:$AA$298,5,0) -> NULL | J31: =VLOOKUP('E-impôts'!A31,Feuil2!$A$1:$AA$298,19,0) -> 506899413 | K31: =VLOOKUP('E-impôts'!A31,Feuil2!$A$1:$AA$298,9,0) -> NULL | L31: =VLOOKUP('E-impôts'!A31,Feuil2!$A$1:$AA$298,15,0) -> Bingerville | M31: =VLOOKUP('E-impôts'!A31,Feuil2!$A$1:$AA$298,13,0) -> NULL | N31: =VLOOKUP('E-impôts'!A31,Feuil2!$A$1:$AA$298,14,0) -> NULL | O31: =VLOOKUP('E-impôts'!A31,Feuil2!$A$1:$AA$298,16,0) -> NULL | P31: =VLOOKUP(A31,Feuil2!$A$1:$AA$298,17,0) -> NULL
A32: 2245408S | B32: TENAN GROUP | C32: =VLOOKUP('E-impôts'!A32,Feuil2!$A$1:$AA$298,4,0) -> #N/A | D32: 45316 | E32: =VLOOKUP('E-impôts'!A32,Feuil2!$A$1:$AA$298,8,0) -> DCK-CGA2024-A030 | F32: =VLOOKUP('E-impôts'!A32,Feuil2!$A$1:$AA$298,24,0) -> COCODY 7Ã¨me tranche | G32: =VLOOKUP('E-impôts'!A32,Feuil2!$A$1:$AA$298,11,0) -> TEE | H32: =VLOOKUP('E-impôts'!A32,Feuil2!$A$1:$AA$298,10,0) -> SARL | I32: =VLOOKUP('E-impôts'!A32,Feuil2!$A$1:$AA$298,5,0) -> KONE TENAN ISSA | J32: =VLOOKUP('E-impôts'!A32,Feuil2!$A$1:$AA$298,19,0) -> 707999183 | K32: =VLOOKUP('E-impôts'!A32,Feuil2!$A$1:$AA$298,9,0) -> CI-ABJ-03-2022-B13-11335 | L32: =VLOOKUP('E-impôts'!A32,Feuil2!$A$1:$AA$298,15,0) -> Riviera II | M32: =VLOOKUP('E-impôts'!A32,Feuil2!$A$1:$AA$298,13,0) -> 0 | N32: =VLOOKUP('E-impôts'!A32,Feuil2!$A$1:$AA$298,14,0) -> 0 | O32: =VLOOKUP('E-impôts'!A32,Feuil2!$A$1:$AA$298,16,0) -> 0 | P32: =VLOOKUP(A32,Feuil2!$A$1:$AA$298,17,0) -> 1000000
A33: 0720702T | B33: TANOH EPSE AKOUASSA AFFOUE | C33: =VLOOKUP('E-impôts'!A33,Feuil2!$A$1:$AA$298,4,0) -> #N/A | D33: 43859 | E33: =VLOOKUP('E-impôts'!A33,Feuil2!$A$1:$AA$298,8,0) -> #N/A | F33: =VLOOKUP('E-impôts'!A33,Feuil2!$A$1:$AA$298,24,0) -> #N/A | G33: =VLOOKUP('E-impôts'!A33,Feuil2!$A$1:$AA$298,11,0) -> #N/A | H33: =VLOOKUP('E-impôts'!A33,Feuil2!$A$1:$AA$298,10,0) -> #N/A | I33: =VLOOKUP('E-impôts'!A33,Feuil2!$A$1:$AA$298,5,0) -> #N/A | J33: =VLOOKUP('E-impôts'!A33,Feuil2!$A$1:$AA$298,19,0) -> #N/A | K33: =VLOOKUP('E-impôts'!A33,Feuil2!$A$1:$AA$298,9,0) -> #N/A | L33: =VLOOKUP('E-impôts'!A33,Feuil2!$A$1:$AA$298,15,0) -> #N/A | M33: =VLOOKUP('E-impôts'!A33,Feuil2!$A$1:$AA$298,13,0) -> #N/A | N33: =VLOOKUP('E-impôts'!A33,Feuil2!$A$1:$AA$298,14,0) -> #N/A | O33: =VLOOKUP('E-impôts'!A33,Feuil2!$A$1:$AA$298,16,0) -> #N/A | P33: =VLOOKUP(A33,Feuil2!$A$1:$AA$298,17,0) -> #N/A
A34: 1810218D | B34: TALENT SCHOOL OF BUSINESS | C34: =VLOOKUP('E-impôts'!A34,Feuil2!$A$1:$AA$298,4,0) -> #N/A | D34: 45315 | E34: =VLOOKUP('E-impôts'!A34,Feuil2!$A$1:$AA$298,8,0) -> DCK-CGA2024-A019 | F34: =VLOOKUP('E-impôts'!A34,Feuil2!$A$1:$AA$298,24,0) -> II PLATEAUX VALLONS | G34: =VLOOKUP('E-impôts'!A34,Feuil2!$A$1:$AA$298,11,0) -> TEE | H34: =VLOOKUP('E-impôts'!A34,Feuil2!$A$1:$AA$298,10,0) -> SAS | I34: =VLOOKUP('E-impôts'!A34,Feuil2!$A$1:$AA$298,5,0) -> ZARROUK MEHDI | J34: =VLOOKUP('E-impôts'!A34,Feuil2!$A$1:$AA$298,19,0) -> 778292924 | K34: =VLOOKUP('E-impôts'!A34,Feuil2!$A$1:$AA$298,9,0) -> CI-ABJ03-2023-M-15026 | L34: =VLOOKUP('E-impôts'!A34,Feuil2!$A$1:$AA$298,15,0) -> II Pateaux II | M34: =VLOOKUP('E-impôts'!A34,Feuil2!$A$1:$AA$298,13,0) -> LS | N34: =VLOOKUP('E-impôts'!A34,Feuil2!$A$1:$AA$298,14,0) -> 297 | O34: =VLOOKUP('E-impôts'!A34,Feuil2!$A$1:$AA$298,16,0) -> SCE1501 | P34: =VLOOKUP(A34,Feuil2!$A$1:$AA$298,17,0) -> 10000000
A35: 2300836U | B35: SYNERGY PHARMA | C35: =VLOOKUP('E-impôts'!A35,Feuil2!$A$1:$AA$298,4,0) -> #N/A | D35: 45321 | E35: =VLOOKUP('E-impôts'!A35,Feuil2!$A$1:$AA$298,8,0) -> DCK-CGA2024-A081 | F35: =VLOOKUP('E-impôts'!A35,Feuil2!$A$1:$AA$298,24,0) -> COCODY RIVIERA FAYA | G35: =VLOOKUP('E-impôts'!A35,Feuil2!$A$1:$AA$298,11,0) -> TEE | H35: =VLOOKUP('E-impôts'!A35,Feuil2!$A$1:$AA$298,10,0) -> SARL | I35: =VLOOKUP('E-impôts'!A35,Feuil2!$A$1:$AA$298,5,0) -> DEBRIMOU DANIELLE RENEE | J35: =VLOOKUP('E-impôts'!A35,Feuil2!$A$1:$AA$298,19,0) -> 142900455 | K35: =VLOOKUP('E-impôts'!A35,Feuil2!$A$1:$AA$298,9,0) -> CI-ABJ-03-2023-B12-01206 | L35: =VLOOKUP('E-impôts'!A35,Feuil2!$A$1:$AA$298,15,0) -> Riviera II | M35: =VLOOKUP('E-impôts'!A35,Feuil2!$A$1:$AA$298,13,0) -> HR | N35: =VLOOKUP('E-impôts'!A35,Feuil2!$A$1:$AA$298,14,0) -> 44 | O35: I550000 | P35: =VLOOKUP(A35,Feuil2!$A$1:$AA$298,17,0) -> 5000000
A36: 2019321T | B36: SYMBIOZ IMMOBILIER | C36: =VLOOKUP('E-impôts'!A36,Feuil2!$A$1:$AA$298,4,0) -> CABINET CFA | D36: 44224 | E36: =VLOOKUP('E-impôts'!A36,Feuil2!$A$1:$AA$298,8,0) -> DCK-CGA2021-Q168 | F36: =VLOOKUP('E-impôts'!A36,Feuil2!$A$1:$AA$298,24,0) -> COCODY, RIVIERA PALMERAIE | G36: =VLOOKUP('E-impôts'!A36,Feuil2!$A$1:$AA$298,11,0) -> TEE | H36: =VLOOKUP('E-impôts'!A36,Feuil2!$A$1:$AA$298,10,0) -> SARL | I36: =VLOOKUP('E-impôts'!A36,Feuil2!$A$1:$AA$298,5,0) -> NULL | J36: =VLOOKUP('E-impôts'!A36,Feuil2!$A$1:$AA$298,19,0) -> 767552335 | K36: =VLOOKUP('E-impôts'!A36,Feuil2!$A$1:$AA$298,9,0) -> NULL | L36: =VLOOKUP('E-impôts'!A36,Feuil2!$A$1:$AA$298,15,0) -> Riviera I | M36: =VLOOKUP('E-impôts'!A36,Feuil2!$A$1:$AA$298,13,0) -> NULL | N36: =VLOOKUP('E-impôts'!A36,Feuil2!$A$1:$AA$298,14,0) -> NULL | O36: =VLOOKUP('E-impôts'!A36,Feuil2!$A$1:$AA$298,16,0) -> NULL | P36: =VLOOKUP(A36,Feuil2!$A$1:$AA$298,17,0) -> NULL
B37: STENO GROUP | C37: =VLOOKUP('E-impôts'!A37,Feuil2!$A$1:$AA$298,4,0) -> #N/A | D37: 44589 | E37: =VLOOKUP('E-impôts'!A37,Feuil2!$A$1:$AA$298,8,0) -> #N/A | F37: =VLOOKUP('E-impôts'!A37,Feuil2!$A$1:$AA$298,24,0) -> #N/A | G37: =VLOOKUP('E-impôts'!A37,Feuil2!$A$1:$AA$298,11,0) -> #N/A | H37: =VLOOKUP('E-impôts'!A37,Feuil2!$A$1:$AA$298,10,0) -> #N/A | I37: =VLOOKUP('E-impôts'!A37,Feuil2!$A$1:$AA$298,5,0) -> #N/A | J37: =VLOOKUP('E-impôts'!A37,Feuil2!$A$1:$AA$298,19,0) -> #N/A | K37: =VLOOKUP('E-impôts'!A37,Feuil2!$A$1:$AA$298,9,0) -> #N/A | L37: =VLOOKUP('E-impôts'!A37,Feuil2!$A$1:$AA$298,15,0) -> #N/A | M37: =VLOOKUP('E-impôts'!A37,Feuil2!$A$1:$AA$298,13,0) -> #N/A | N37: =VLOOKUP('E-impôts'!A37,Feuil2!$A$1:$AA$298,14,0) -> #N/A | O37: =VLOOKUP('E-impôts'!A37,Feuil2!$A$1:$AA$298,16,0) -> #N/A | P37: =VLOOKUP(A37,Feuil2!$A$1:$AA$298,17,0) -> #N/A
A38: 1430635S | B38: STE DE PRODUCTION ET DE DISTRI | C38: =VLOOKUP('E-impôts'!A38,Feuil2!$A$1:$AA$298,4,0) -> #N/A | D38: 45322 | E38: =VLOOKUP('E-impôts'!A38,Feuil2!$A$1:$AA$298,8,0) -> DCK-CGA2024-A002 | F38: =VLOOKUP('E-impôts'!A38,Feuil2!$A$1:$AA$298,24,0) -> ABIDJAN COCODY ANGRE STAR 6 | G38: =VLOOKUP('E-impôts'!A38,Feuil2!$A$1:$AA$298,11,0) -> TEE | H38: =VLOOKUP('E-impôts'!A38,Feuil2!$A$1:$AA$298,10,0) -> SARL | I38: =VLOOKUP('E-impôts'!A38,Feuil2!$A$1:$AA$298,5,0) -> OSNOU YOBOUET EDJEM AWA JACQUELINE EPSE DJIRE | J38: =VLOOKUP('E-impôts'!A38,Feuil2!$A$1:$AA$298,19,0) -> 07 59 37 49 20 | K38: =VLOOKUP('E-impôts'!A38,Feuil2!$A$1:$AA$298,9,0) -> CI-ABI-2014-B-8078 | L38: =VLOOKUP('E-impôts'!A38,Feuil2!$A$1:$AA$298,15,0) -> II Pateaux I | M38: =VLOOKUP('E-impôts'!A38,Feuil2!$A$1:$AA$298,13,0) -> DO | N38: =VLOOKUP('E-impôts'!A38,Feuil2!$A$1:$AA$298,14,0) -> 99 | O38: =VLOOKUP('E-impôts'!A38,Feuil2!$A$1:$AA$298,16,0) -> CCE1701 | P38: =VLOOKUP(A38,Feuil2!$A$1:$AA$298,17,0) -> 1000000
A39: 1336628G | B39: SORO FOUNGNIGUE | C39: =VLOOKUP('E-impôts'!A39,Feuil2!$A$1:$AA$298,4,0) -> CABINET CFA | D39: 43871 | E39: =VLOOKUP('E-impôts'!A39,Feuil2!$A$1:$AA$298,8,0) -> DCK-CGA2020-A100 | F39: =VLOOKUP('E-impôts'!A39,Feuil2!$A$1:$AA$298,24,0) -> COCODY CAFFEIER II | G39: =VLOOKUP('E-impôts'!A39,Feuil2!$A$1:$AA$298,11,0) -> TEE | H39: =VLOOKUP('E-impôts'!A39,Feuil2!$A$1:$AA$298,10,0) -> ENTREPRISE INDIVIDUELLE | I39: =VLOOKUP('E-impôts'!A39,Feuil2!$A$1:$AA$298,5,0) -> NULL | J39: =VLOOKUP('E-impôts'!A39,Feuil2!$A$1:$AA$298,19,0) -> 707347436 | K39: =VLOOKUP('E-impôts'!A39,Feuil2!$A$1:$AA$298,9,0) -> NULL | L39: =VLOOKUP('E-impôts'!A39,Feuil2!$A$1:$AA$298,15,0) -> II Plateaux I | M39: =VLOOKUP('E-impôts'!A39,Feuil2!$A$1:$AA$298,13,0) -> NULL | N39: =VLOOKUP('E-impôts'!A39,Feuil2!$A$1:$AA$298,14,0) -> NULL | O39: =VLOOKUP('E-impôts'!A39,Feuil2!$A$1:$AA$298,16,0) -> NULL | P39: =VLOOKUP(A39,Feuil2!$A$1:$AA$298,17,0) -> NULL
A40: 2241904N | B40: SOFT INGENIERIE | C40: =VLOOKUP('E-impôts'!A40,Feuil2!$A$1:$AA$298,4,0) -> #N/A | D40: 45322 | E40: =VLOOKUP('E-impôts'!A40,Feuil2!$A$1:$AA$298,8,0) -> DCK-CGA2024-A052 | F40: =VLOOKUP('E-impôts'!A40,Feuil2!$A$1:$AA$298,24,0) -> COCODY RIVIERA ABATTA NOUVEAU GOUDRON VERS BLD SIR CITE PRESTIGE 2 | G40: =VLOOKUP('E-impôts'!A40,Feuil2!$A$1:$AA$298,11,0) -> TEE | H40: =VLOOKUP('E-impôts'!A40,Feuil2!$A$1:$AA$298,10,0) -> SARL | I40: =VLOOKUP('E-impôts'!A40,Feuil2!$A$1:$AA$298,5,0) -> COULIBALY ISMAEL | J40: =VLOOKUP('E-impôts'!A40,Feuil2!$A$1:$AA$298,19,0) -> 707336407 | K40: =VLOOKUP('E-impôts'!A40,Feuil2!$A$1:$AA$298,9,0) -> CI-ABJ-03-2022-B13-04073 | L40: =VLOOKUP('E-impôts'!A40,Feuil2!$A$1:$AA$298,15,0) -> Riviera II | M40: =VLOOKUP('E-impôts'!A40,Feuil2!$A$1:$AA$298,13,0) -> 0 | N40: =VLOOKUP('E-impôts'!A40,Feuil2!$A$1:$AA$298,14,0) -> 0 | O40: =VLOOKUP('E-impôts'!A40,Feuil2!$A$1:$AA$298,16,0) -> SCE0801 | P40: =VLOOKUP(A40,Feuil2!$A$1:$AA$298,17,0) -> 1000000
A41: 1916804Q | B41: SOCIETE IVOIRIENNE DE VENTES D | C41: =VLOOKUP('E-impôts'!A41,Feuil2!$A$1:$AA$298,4,0) -> CABINET CFA | D41: 44224 | E41: =VLOOKUP('E-impôts'!A41,Feuil2!$A$1:$AA$298,8,0) -> DCK-CGA2021-Q-162 | F41: =VLOOKUP('E-impôts'!A41,Feuil2!$A$1:$AA$298,24,0) -> ANGRE ANCIEN MARCHÃ‰ | G41: =VLOOKUP('E-impôts'!A41,Feuil2!$A$1:$AA$298,11,0) -> TEE | H41: =VLOOKUP('E-impôts'!A41,Feuil2!$A$1:$AA$298,10,0) -> SARL | I41: =VLOOKUP('E-impôts'!A41,Feuil2!$A$1:$AA$298,5,0) -> NULL | J41: =VLOOKUP('E-impôts'!A41,Feuil2!$A$1:$AA$298,19,0) -> 747755863 | K41: =VLOOKUP('E-impôts'!A41,Feuil2!$A$1:$AA$298,9,0) -> NULL | L41: =VLOOKUP('E-impôts'!A41,Feuil2!$A$1:$AA$298,15,0) -> II Plateaux I | M41: =VLOOKUP('E-impôts'!A41,Feuil2!$A$1:$AA$298,13,0) -> NULL | N41: =VLOOKUP('E-impôts'!A41,Feuil2!$A$1:$AA$298,14,0) -> NULL | O41: =VLOOKUP('E-impôts'!A41,Feuil2!$A$1:$AA$298,16,0) -> NULL | P41: =VLOOKUP(A41,Feuil2!$A$1:$AA$298,17,0) -> NULL
A42: 1101308N | B42: SOCIETE D'ETUDES TRAVAUX MAINT | C42: =VLOOKUP('E-impôts'!A42,Feuil2!$A$1:$AA$298,4,0) -> #N/A | D42: 44224 | E42: =VLOOKUP('E-impôts'!A42,Feuil2!$A$1:$AA$298,8,0) -> #N/A | F42: =VLOOKUP('E-impôts'!A42,Feuil2!$A$1:$AA$298,24,0) -> #N/A | G42: =VLOOKUP('E-impôts'!A42,Feuil2!$A$1:$AA$298,11,0) -> #N/A | H42: =VLOOKUP('E-impôts'!A42,Feuil2!$A$1:$AA$298,10,0) -> #N/A | I42: =VLOOKUP('E-impôts'!A42,Feuil2!$A$1:$AA$298,5,0) -> #N/A | J42: =VLOOKUP('E-impôts'!A42,Feuil2!$A$1:$AA$298,19,0) -> #N/A | K42: =VLOOKUP('E-impôts'!A42,Feuil2!$A$1:$AA$298,9,0) -> #N/A | L42: =VLOOKUP('E-impôts'!A42,Feuil2!$A$1:$AA$298,15,0) -> #N/A | M42: =VLOOKUP('E-impôts'!A42,Feuil2!$A$1:$AA$298,13,0) -> #N/A | N42: =VLOOKUP('E-impôts'!A42,Feuil2!$A$1:$AA$298,14,0) -> #N/A | O42: =VLOOKUP('E-impôts'!A42,Feuil2!$A$1:$AA$298,16,0) -> #N/A | P42: =VLOOKUP(A42,Feuil2!$A$1:$AA$298,17,0) -> #N/A
A43: 2165858D | B43: SOCIETE DE TRANSPORT MAMADOU ET FRERES | C43: =VLOOKUP('E-impôts'!A43,Feuil2!$A$1:$AA$298,4,0) -> GOHI | D43: 44472 | E43: =VLOOKUP('E-impôts'!A43,Feuil2!$A$1:$AA$298,8,0) -> DCK-CGA2021-Q184 | F43: =VLOOKUP('E-impôts'!A43,Feuil2!$A$1:$AA$298,24,0) -> COCODY II PLATEAUX | G43: =VLOOKUP('E-impôts'!A43,Feuil2!$A$1:$AA$298,11,0) -> TEE | H43: =VLOOKUP('E-impôts'!A43,Feuil2!$A$1:$AA$298,10,0) -> SARL | I43: =VLOOKUP('E-impôts'!A43,Feuil2!$A$1:$AA$298,5,0) -> NULL | J43: =VLOOKUP('E-impôts'!A43,Feuil2!$A$1:$AA$298,19,0) -> 757921316 | K43: =VLOOKUP('E-impôts'!A43,Feuil2!$A$1:$AA$298,9,0) -> NULL | L43: =VLOOKUP('E-impôts'!A43,Feuil2!$A$1:$AA$298,15,0) -> II Plateaux II | M43: =VLOOKUP('E-impôts'!A43,Feuil2!$A$1:$AA$298,13,0) -> NULL | N43: =VLOOKUP('E-impôts'!A43,Feuil2!$A$1:$AA$298,14,0) -> NULL | O43: =VLOOKUP('E-impôts'!A43,Feuil2!$A$1:$AA$298,16,0) -> NULL | P43: =VLOOKUP(A43,Feuil2!$A$1:$AA$298,17,0) -> NULL
A44: 2193133B | B44: SOCIETE DE PRODUCTION DE VENTE ET DE MULTISERVICES SARL | C44: =VLOOKUP('E-impôts'!A44,Feuil2!$A$1:$AA$298,4,0) -> #N/A | D44: 44628 | E44: =VLOOKUP('E-impôts'!A44,Feuil2!$A$1:$AA$298,8,0) -> #N/A | F44: =VLOOKUP('E-impôts'!A44,Feuil2!$A$1:$AA$298,24,0) -> #N/A | G44: =VLOOKUP('E-impôts'!A44,Feuil2!$A$1:$AA$298,11,0) -> #N/A | H44: =VLOOKUP('E-impôts'!A44,Feuil2!$A$1:$AA$298,10,0) -> #N/A | I44: =VLOOKUP('E-impôts'!A44,Feuil2!$A$1:$AA$298,5,0) -> #N/A | J44: =VLOOKUP('E-impôts'!A44,Feuil2!$A$1:$AA$298,19,0) -> #N/A | K44: =VLOOKUP('E-impôts'!A44,Feuil2!$A$1:$AA$298,9,0) -> #N/A | L44: =VLOOKUP('E-impôts'!A44,Feuil2!$A$1:$AA$298,15,0) -> #N/A | M44: =VLOOKUP('E-impôts'!A44,Feuil2!$A$1:$AA$298,13,0) -> #N/A | N44: =VLOOKUP('E-impôts'!A44,Feuil2!$A$1:$AA$298,14,0) -> #N/A | O44: =VLOOKUP('E-impôts'!A44,Feuil2!$A$1:$AA$298,16,0) -> #N/A | P44: =VLOOKUP(A44,Feuil2!$A$1:$AA$298,17,0) -> #N/A
A45: 2301374V | B45: SOCIETE DE MENUISERIE ALIMINIUM ET DIVERS | C45: =VLOOKUP('E-impôts'!A45,Feuil2!$A$1:$AA$298,4,0) -> DCK | D45: 45309 | E45: =VLOOKUP('E-impôts'!A45,Feuil2!$A$1:$AA$298,8,0) -> DCK-CGA2024-A008 | F45: =VLOOKUP('E-impôts'!A45,Feuil2!$A$1:$AA$298,24,0) -> ABIDJAN-COCODY-RIVIERA-ABATTA-CARREFOUR MOSQUE | G45: =VLOOKUP('E-impôts'!A45,Feuil2!$A$1:$AA$298,11,0) -> TEE | H45: =VLOOKUP('E-impôts'!A45,Feuil2!$A$1:$AA$298,10,0) -> SARL | I45: KOME KOKOU AGBEDJIDOR | J45: =VLOOKUP('E-impôts'!A45,Feuil2!$A$1:$AA$298,19,0) -> 788194883 | K45: =VLOOKUP('E-impôts'!A45,Feuil2!$A$1:$AA$298,9,0) -> CI-ABJ-03-2023-B13-03049 | L45: =VLOOKUP('E-impôts'!A45,Feuil2!$A$1:$AA$298,15,0) -> 0 | M45: =VLOOKUP('E-impôts'!A45,Feuil2!$A$1:$AA$298,13,0) -> IX | N45: =VLOOKUP('E-impôts'!A45,Feuil2!$A$1:$AA$298,14,0) -> 173 | O45: A0104 | P45: =VLOOKUP(A45,Feuil2!$A$1:$AA$298,17,0) -> 2000000
A46: 2244612N | B46: SOCIETE DE MAINTENANCE ET D'INGENIERIE | C46: =VLOOKUP('E-impôts'!A46,Feuil2!$A$1:$AA$298,4,0) -> KOFFI ALBERT | D46: 44935 | E46: =VLOOKUP('E-impôts'!A46,Feuil2!$A$1:$AA$298,8,0) -> DCK-CGA2023-J002 | F46: =VLOOKUP('E-impôts'!A46,Feuil2!$A$1:$AA$298,24,0) -> BINGERVILLE | G46: =VLOOKUP('E-impôts'!A46,Feuil2!$A$1:$AA$298,11,0) -> TEE | H46: =VLOOKUP('E-impôts'!A46,Feuil2!$A$1:$AA$298,10,0) -> SARL | I46: =VLOOKUP('E-impôts'!A46,Feuil2!$A$1:$AA$298,5,0) -> NULL | J46: =VLOOKUP('E-impôts'!A46,Feuil2!$A$1:$AA$298,19,0) -> 584483480 | K46: =VLOOKUP('E-impôts'!A46,Feuil2!$A$1:$AA$298,9,0) -> NULL | L46: =VLOOKUP('E-impôts'!A46,Feuil2!$A$1:$AA$298,15,0) -> Bingerville | M46: =VLOOKUP('E-impôts'!A46,Feuil2!$A$1:$AA$298,13,0) -> NULL | N46: =VLOOKUP('E-impôts'!A46,Feuil2!$A$1:$AA$298,14,0) -> NULL | O46: =VLOOKUP('E-impôts'!A46,Feuil2!$A$1:$AA$298,16,0) -> NULL | P46: =VLOOKUP(A46,Feuil2!$A$1:$AA$298,17,0) -> NULL
A47: 1820448E | B47: SN HAXEDYN | C47: =VLOOKUP('E-impôts'!A47,Feuil2!$A$1:$AA$298,4,0) -> #N/A | D47: 43479 | E47: =VLOOKUP('E-impôts'!A47,Feuil2!$A$1:$AA$298,8,0) -> #N/A | F47: =VLOOKUP('E-impôts'!A47,Feuil2!$A$1:$AA$298,24,0) -> #N/A | G47: =VLOOKUP('E-impôts'!A47,Feuil2!$A$1:$AA$298,11,0) -> #N/A | H47: =VLOOKUP('E-impôts'!A47,Feuil2!$A$1:$AA$298,10,0) -> #N/A | I47: =VLOOKUP('E-impôts'!A47,Feuil2!$A$1:$AA$298,5,0) -> #N/A | J47: =VLOOKUP('E-impôts'!A47,Feuil2!$A$1:$AA$298,19,0) -> #N/A | K47: =VLOOKUP('E-impôts'!A47,Feuil2!$A$1:$AA$298,9,0) -> #N/A | L47: =VLOOKUP('E-impôts'!A47,Feuil2!$A$1:$AA$298,15,0) -> #N/A | M47: =VLOOKUP('E-impôts'!A47,Feuil2!$A$1:$AA$298,13,0) -> #N/A | N47: =VLOOKUP('E-impôts'!A47,Feuil2!$A$1:$AA$298,14,0) -> #N/A | O47: =VLOOKUP('E-impôts'!A47,Feuil2!$A$1:$AA$298,16,0) -> #N/A | P47: =VLOOKUP(A47,Feuil2!$A$1:$AA$298,17,0) -> #N/A
A48: 2176405T | B48: SISSAKO ISSOUFOU | C48: =VLOOKUP('E-impôts'!A48,Feuil2!$A$1:$AA$298,4,0) -> #N/A | D48: 44574 | E48: =VLOOKUP('E-impôts'!A48,Feuil2!$A$1:$AA$298,8,0) -> #N/A | F48: =VLOOKUP('E-impôts'!A48,Feuil2!$A$1:$AA$298,24,0) -> #N/A | G48: =VLOOKUP('E-impôts'!A48,Feuil2!$A$1:$AA$298,11,0) -> #N/A | H48: =VLOOKUP('E-impôts'!A48,Feuil2!$A$1:$AA$298,10,0) -> #N/A | I48: =VLOOKUP('E-impôts'!A48,Feuil2!$A$1:$AA$298,5,0) -> #N/A | J48: =VLOOKUP('E-impôts'!A48,Feuil2!$A$1:$AA$298,19,0) -> #N/A | K48: =VLOOKUP('E-impôts'!A48,Feuil2!$A$1:$AA$298,9,0) -> #N/A | L48: =VLOOKUP('E-impôts'!A48,Feuil2!$A$1:$AA$298,15,0) -> #N/A | M48: =VLOOKUP('E-impôts'!A48,Feuil2!$A$1:$AA$298,13,0) -> #N/A | N48: =VLOOKUP('E-impôts'!A48,Feuil2!$A$1:$AA$298,14,0) -> #N/A | O48: =VLOOKUP('E-impôts'!A48,Feuil2!$A$1:$AA$298,16,0) -> #N/A | P48: =VLOOKUP(A48,Feuil2!$A$1:$AA$298,17,0) -> #N/A
A49: 2241940M | B49: SINEQUANONE SERVICE | C49: =VLOOKUP('E-impôts'!A49,Feuil2!$A$1:$AA$298,4,0) -> #N/A | D49: 44774 | E49: =VLOOKUP('E-impôts'!A49,Feuil2!$A$1:$AA$298,8,0) -> #N/A | F49: =VLOOKUP('E-impôts'!A49,Feuil2!$A$1:$AA$298,24,0) -> #N/A | G49: =VLOOKUP('E-impôts'!A49,Feuil2!$A$1:$AA$298,11,0) -> #N/A | H49: =VLOOKUP('E-impôts'!A49,Feuil2!$A$1:$AA$298,10,0) -> #N/A | I49: =VLOOKUP('E-impôts'!A49,Feuil2!$A$1:$AA$298,5,0) -> #N/A | J49: =VLOOKUP('E-impôts'!A49,Feuil2!$A$1:$AA$298,19,0) -> #N/A | K49: =VLOOKUP('E-impôts'!A49,Feuil2!$A$1:$AA$298,9,0) -> #N/A | L49: =VLOOKUP('E-impôts'!A49,Feuil2!$A$1:$AA$298,15,0) -> #N/A | M49: =VLOOKUP('E-impôts'!A49,Feuil2!$A$1:$AA$298,13,0) -> #N/A | N49: =VLOOKUP('E-impôts'!A49,Feuil2!$A$1:$AA$298,14,0) -> #N/A | O49: =VLOOKUP('E-impôts'!A49,Feuil2!$A$1:$AA$298,16,0) -> #N/A | P49: =VLOOKUP(A49,Feuil2!$A$1:$AA$298,17,0) -> #N/A
A50: 1107962T | B50: SIDI MOHAMED OULD MOUSTAPHA | C50: =VLOOKUP('E-impôts'!A50,Feuil2!$A$1:$AA$298,4,0) -> #N/A | D50: 44585 | E50: =VLOOKUP('E-impôts'!A50,Feuil2!$A$1:$AA$298,8,0) -> #N/A | F50: =VLOOKUP('E-impôts'!A50,Feuil2!$A$1:$AA$298,24,0) -> #N/A | G50: =VLOOKUP('E-impôts'!A50,Feuil2!$A$1:$AA$298,11,0) -> #N/A | H50: =VLOOKUP('E-impôts'!A50,Feuil2!$A$1:$AA$298,10,0) -> #N/A | I50: =VLOOKUP('E-impôts'!A50,Feuil2!$A$1:$AA$298,5,0) -> #N/A | J50: =VLOOKUP('E-impôts'!A50,Feuil2!$A$1:$AA$298,19,0) -> #N/A | K50: =VLOOKUP('E-impôts'!A50,Feuil2!$A$1:$AA$298,9,0) -> #N/A | L50: =VLOOKUP('E-impôts'!A50,Feuil2!$A$1:$AA$298,15,0) -> #N/A | M50: =VLOOKUP('E-impôts'!A50,Feuil2!$A$1:$AA$298,13,0) -> #N/A | N50: =VLOOKUP('E-impôts'!A50,Feuil2!$A$1:$AA$298,14,0) -> #N/A | O50: =VLOOKUP('E-impôts'!A50,Feuil2!$A$1:$AA$298,16,0) -> #N/A | P50: =VLOOKUP(A50,Feuil2!$A$1:$AA$298,17,0) -> #N/A
A51: 1230931S | B51: SEYDOU SANOGO | C51: =VLOOKUP('E-impôts'!A51,Feuil2!$A$1:$AA$298,4,0) -> #N/A | D51: 45320 | E51: =VLOOKUP('E-impôts'!A51,Feuil2!$A$1:$AA$298,8,0) -> DCK-CGA2024-A026 | F51: =VLOOKUP('E-impôts'!A51,Feuil2!$A$1:$AA$298,24,0) -> COCODY RIVIERA PALMERAIE/ CENTRE COMMUNAUTAIRE URBAIN | G51: =VLOOKUP('E-impôts'!A51,Feuil2!$A$1:$AA$298,11,0) -> TEE | H51: =VLOOKUP('E-impôts'!A51,Feuil2!$A$1:$AA$298,10,0) -> ENTREPRISE INDIVIDUELLE | I51: =VLOOKUP('E-impôts'!A51,Feuil2!$A$1:$AA$298,5,0) -> SEYDOU SANOGO | J51: =VLOOKUP('E-impôts'!A51,Feuil2!$A$1:$AA$298,19,0) -> 01 01 10 16 65 | K51: =VLOOKUP('E-impôts'!A51,Feuil2!$A$1:$AA$298,9,0) -> CI-ABJ-2015-A-19315 | L51: =VLOOKUP('E-impôts'!A51,Feuil2!$A$1:$AA$298,15,0) -> II Plateaux III | M51: =VLOOKUP('E-impôts'!A51,Feuil2!$A$1:$AA$298,13,0) -> TX | N51: =VLOOKUP('E-impôts'!A51,Feuil2!$A$1:$AA$298,14,0) -> 16 | O51: =VLOOKUP('E-impôts'!A51,Feuil2!$A$1:$AA$298,16,0) -> N/D | P51: =VLOOKUP(A51,Feuil2!$A$1:$AA$298,17,0) -> N/D
A52: 2130592L | B52: SENY ISSELKOU BECHIRY | C52: =VLOOKUP('E-impôts'!A52,Feuil2!$A$1:$AA$298,4,0) -> ZADI | D52: 44585 | E52: =VLOOKUP('E-impôts'!A52,Feuil2!$A$1:$AA$298,8,0) -> DCK-CGA2022-J005 | F52: =VLOOKUP('E-impôts'!A52,Feuil2!$A$1:$AA$298,24,0) -> COCODY RIVIERA | G52: =VLOOKUP('E-impôts'!A52,Feuil2!$A$1:$AA$298,11,0) -> TEE | H52: =VLOOKUP('E-impôts'!A52,Feuil2!$A$1:$AA$298,10,0) -> ENTREPRISE INDIVIDUELLE | I52: =VLOOKUP('E-impôts'!A52,Feuil2!$A$1:$AA$298,5,0) -> NULL | J52: =VLOOKUP('E-impôts'!A52,Feuil2!$A$1:$AA$298,19,0) -> 1424820022 | K52: =VLOOKUP('E-impôts'!A52,Feuil2!$A$1:$AA$298,9,0) -> NULL | L52: =VLOOKUP('E-impôts'!A52,Feuil2!$A$1:$AA$298,15,0) -> Bingerville | M52: =VLOOKUP('E-impôts'!A52,Feuil2!$A$1:$AA$298,13,0) -> NULL | N52: =VLOOKUP('E-impôts'!A52,Feuil2!$A$1:$AA$298,14,0) -> NULL | O52: =VLOOKUP('E-impôts'!A52,Feuil2!$A$1:$AA$298,16,0) -> NULL | P52: =VLOOKUP(A52,Feuil2!$A$1:$AA$298,17,0) -> NULL
A53: 2245374G | B53: SAYNI & SON | C53: =VLOOKUP('E-impôts'!A53,Feuil2!$A$1:$AA$298,4,0) -> GOHI | D53: 44957 | E53: =VLOOKUP('E-impôts'!A53,Feuil2!$A$1:$AA$298,8,0) -> DCK-CGA2023-J035 | F53: =VLOOKUP('E-impôts'!A53,Feuil2!$A$1:$AA$298,24,0) -> COCODY RIVIERA BONOUMIN | G53: =VLOOKUP('E-impôts'!A53,Feuil2!$A$1:$AA$298,11,0) -> TEE | H53: =VLOOKUP('E-impôts'!A53,Feuil2!$A$1:$AA$298,10,0) -> SARL | I53: =VLOOKUP('E-impôts'!A53,Feuil2!$A$1:$AA$298,5,0) -> NULL | J53: =VLOOKUP('E-impôts'!A53,Feuil2!$A$1:$AA$298,19,0) -> 708824664 | K53: =VLOOKUP('E-impôts'!A53,Feuil2!$A$1:$AA$298,9,0) -> NULL | L53: =VLOOKUP('E-impôts'!A53,Feuil2!$A$1:$AA$298,15,0) -> Riviera II | M53: =VLOOKUP('E-impôts'!A53,Feuil2!$A$1:$AA$298,13,0) -> NULL | N53: =VLOOKUP('E-impôts'!A53,Feuil2!$A$1:$AA$298,14,0) -> NULL | O53: =VLOOKUP('E-impôts'!A53,Feuil2!$A$1:$AA$298,16,0) -> NULL | P53: =VLOOKUP(A53,Feuil2!$A$1:$AA$298,17,0) -> NULL
A54: 0515481M | B54: SAWADOGO KARIM | C54: =VLOOKUP('E-impôts'!A54,Feuil2!$A$1:$AA$298,4,0) -> ZADI | D54: 44585 | E54: =VLOOKUP('E-impôts'!A54,Feuil2!$A$1:$AA$298,8,0) -> DCK-CGA2020-A071 | F54: =VLOOKUP('E-impôts'!A54,Feuil2!$A$1:$AA$298,24,0) -> BINGERVILLE | G54: =VLOOKUP('E-impôts'!A54,Feuil2!$A$1:$AA$298,11,0) -> TEE | H54: =VLOOKUP('E-impôts'!A54,Feuil2!$A$1:$AA$298,10,0) -> ENTREPRISE INDIVIDUELLE | I54: =VLOOKUP('E-impôts'!A54,Feuil2!$A$1:$AA$298,5,0) -> NULL | J54: =VLOOKUP('E-impôts'!A54,Feuil2!$A$1:$AA$298,19,0) -> 0 | K54: =VLOOKUP('E-impôts'!A54,Feuil2!$A$1:$AA$298,9,0) -> NULL | L54: =VLOOKUP('E-impôts'!A54,Feuil2!$A$1:$AA$298,15,0) -> Bingerville | M54: =VLOOKUP('E-impôts'!A54,Feuil2!$A$1:$AA$298,13,0) -> NULL | N54: =VLOOKUP('E-impôts'!A54,Feuil2!$A$1:$AA$298,14,0) -> NULL | O54: =VLOOKUP('E-impôts'!A54,Feuil2!$A$1:$AA$298,16,0) -> NULL | P54: =VLOOKUP(A54,Feuil2!$A$1:$AA$298,17,0) -> NULL
A55: 2196217J | B55: SANTE & SECURITE AU TRAVAIL | C55: =VLOOKUP('E-impôts'!A55,Feuil2!$A$1:$AA$298,4,0) -> DCK | D55: 44564 | E55: =VLOOKUP('E-impôts'!A55,Feuil2!$A$1:$AA$298,8,0) -> DCK-CGA-2022-J002 | F55: =VLOOKUP('E-impôts'!A55,Feuil2!$A$1:$AA$298,24,0) -> COCODY RIVIERA GOLF ANONO | G55: =VLOOKUP('E-impôts'!A55,Feuil2!$A$1:$AA$298,11,0) -> TEE | H55: =VLOOKUP('E-impôts'!A55,Feuil2!$A$1:$AA$298,10,0) -> SARL | I55: KONE EUGENIE EPSE KOSSA | J55: =VLOOKUP('E-impôts'!A55,Feuil2!$A$1:$AA$298,19,0) -> 566284952 | K55: =VLOOKUP('E-impôts'!A55,Feuil2!$A$1:$AA$298,9,0) -> NULL | L55: =VLOOKUP('E-impôts'!A55,Feuil2!$A$1:$AA$298,15,0) -> Riviera I | M55: =VLOOKUP('E-impôts'!A55,Feuil2!$A$1:$AA$298,13,0) -> NULL | N55: =VLOOKUP('E-impôts'!A55,Feuil2!$A$1:$AA$298,14,0) -> NULL | O55: Q860100 | P55: =VLOOKUP(A55,Feuil2!$A$1:$AA$298,17,0) -> NULL
A56: 2302164F | B56: SANGARE MOHAMED | C56: =VLOOKUP('E-impôts'!A56,Feuil2!$A$1:$AA$298,4,0) -> #N/A | D56: 45321 | E56: =VLOOKUP('E-impôts'!A56,Feuil2!$A$1:$AA$298,8,0) -> #N/A | F56: =VLOOKUP('E-impôts'!A56,Feuil2!$A$1:$AA$298,24,0) -> #N/A | G56: =VLOOKUP('E-impôts'!A56,Feuil2!$A$1:$AA$298,11,0) -> #N/A | H56: =VLOOKUP('E-impôts'!A56,Feuil2!$A$1:$AA$298,10,0) -> #N/A | I56: =VLOOKUP('E-impôts'!A56,Feuil2!$A$1:$AA$298,5,0) -> #N/A | J56: =VLOOKUP('E-impôts'!A56,Feuil2!$A$1:$AA$298,19,0) -> #N/A | K56: =VLOOKUP('E-impôts'!A56,Feuil2!$A$1:$AA$298,9,0) -> #N/A | L56: =VLOOKUP('E-impôts'!A56,Feuil2!$A$1:$AA$298,15,0) -> #N/A | M56: =VLOOKUP('E-impôts'!A56,Feuil2!$A$1:$AA$298,13,0) -> #N/A | N56: =VLOOKUP('E-impôts'!A56,Feuil2!$A$1:$AA$298,14,0) -> #N/A | O56: =VLOOKUP('E-impôts'!A56,Feuil2!$A$1:$AA$298,16,0) -> #N/A | P56: =VLOOKUP(A56,Feuil2!$A$1:$AA$298,17,0) -> #N/A
A57: 0042414S | B57: SAGNON ASSITAN EPSE Sanganoko Mamadou | C57: =VLOOKUP('E-impôts'!A57,Feuil2!$A$1:$AA$298,4,0) -> #N/A | D57: 45315 | E57: =VLOOKUP('E-impôts'!A57,Feuil2!$A$1:$AA$298,8,0) -> DCK-CGA2024-A020 | F57: =VLOOKUP('E-impôts'!A57,Feuil2!$A$1:$AA$298,24,0) -> ABATTA CARREFOUR BECEAO | G57: =VLOOKUP('E-impôts'!A57,Feuil2!$A$1:$AA$298,11,0) -> TEE | H57: =VLOOKUP('E-impôts'!A57,Feuil2!$A$1:$AA$298,10,0) -> ENTREPRISE INDIVIDUELLE | I57: =VLOOKUP('E-impôts'!A57,Feuil2!$A$1:$AA$298,5,0) -> SAGNON EPSE SANOKO | J57: =VLOOKUP('E-impôts'!A57,Feuil2!$A$1:$AA$298,19,0) -> 505714618 | K57: =VLOOKUP('E-impôts'!A57,Feuil2!$A$1:$AA$298,9,0) -> CI-ABJ-2019-A-18838 | L57: =VLOOKUP('E-impôts'!A57,Feuil2!$A$1:$AA$298,15,0) -> II Plateaux III | M57: =VLOOKUP('E-impôts'!A57,Feuil2!$A$1:$AA$298,13,0) -> IZ | N57: =VLOOKUP('E-impôts'!A57,Feuil2!$A$1:$AA$298,14,0) -> 12 | O57: =VLOOKUP('E-impôts'!A57,Feuil2!$A$1:$AA$298,16,0) -> ART0705 | P57: =VLOOKUP(A57,Feuil2!$A$1:$AA$298,17,0) -> 1000000
A58: 2243629K | B58: RAYANE DECO + | C58: =VLOOKUP('E-impôts'!A58,Feuil2!$A$1:$AA$298,4,0) -> #N/A | D58: 45316 | E58: =VLOOKUP('E-impôts'!A58,Feuil2!$A$1:$AA$298,8,0) -> DCK-CGA2024-A048 | F58: =VLOOKUP('E-impôts'!A58,Feuil2!$A$1:$AA$298,24,0) -> COCODY RIVIERA 2 | G58: =VLOOKUP('E-impôts'!A58,Feuil2!$A$1:$AA$298,11,0) -> TEE | H58: =VLOOKUP('E-impôts'!A58,Feuil2!$A$1:$AA$298,10,0) -> SARL | I58: =VLOOKUP('E-impôts'!A58,Feuil2!$A$1:$AA$298,5,0) -> KONE BRAHIMA | J58: =VLOOKUP('E-impôts'!A58,Feuil2!$A$1:$AA$298,19,0) -> 757723842 | K58: =VLOOKUP('E-impôts'!A58,Feuil2!$A$1:$AA$298,9,0) -> CI-ABJ-03-2022-B 13-08-07 | L58: =VLOOKUP('E-impôts'!A58,Feuil2!$A$1:$AA$298,15,0) -> II Plateaux III | M58: =VLOOKUP('E-impôts'!A58,Feuil2!$A$1:$AA$298,13,0) -> 0 | N58: =VLOOKUP('E-impôts'!A58,Feuil2!$A$1:$AA$298,14,0) -> 0 | O58: =VLOOKUP('E-impôts'!A58,Feuil2!$A$1:$AA$298,16,0) -> IND2302 | P58: =VLOOKUP(A58,Feuil2!$A$1:$AA$298,17,0) -> 1000000
A59: 2300931U | B59: RADAH ESTATE AND BUILDING | C59: =VLOOKUP('E-impôts'!A59,Feuil2!$A$1:$AA$298,4,0) -> #N/A | D59: 44986 | E59: =VLOOKUP('E-impôts'!A59,Feuil2!$A$1:$AA$298,8,0) -> #N/A | F59: =VLOOKUP('E-impôts'!A59,Feuil2!$A$1:$AA$298,24,0) -> #N/A | G59: =VLOOKUP('E-impôts'!A59,Feuil2!$A$1:$AA$298,11,0) -> #N/A | H59: =VLOOKUP('E-impôts'!A59,Feuil2!$A$1:$AA$298,10,0) -> #N/A | I59: =VLOOKUP('E-impôts'!A59,Feuil2!$A$1:$AA$298,5,0) -> #N/A | J59: =VLOOKUP('E-impôts'!A59,Feuil2!$A$1:$AA$298,19,0) -> #N/A | K59: =VLOOKUP('E-impôts'!A59,Feuil2!$A$1:$AA$298,9,0) -> #N/A | L59: =VLOOKUP('E-impôts'!A59,Feuil2!$A$1:$AA$298,15,0) -> #N/A | M59: =VLOOKUP('E-impôts'!A59,Feuil2!$A$1:$AA$298,13,0) -> #N/A | N59: =VLOOKUP('E-impôts'!A59,Feuil2!$A$1:$AA$298,14,0) -> #N/A | O59: =VLOOKUP('E-impôts'!A59,Feuil2!$A$1:$AA$298,16,0) -> #N/A | P59: =VLOOKUP(A59,Feuil2!$A$1:$AA$298,17,0) -> #N/A
A60: 1995089N | B60: PROSPERITE ENTREPRISE | C60: =VLOOKUP('E-impôts'!A60,Feuil2!$A$1:$AA$298,4,0) -> CABINET CFA | D60: 44224 | E60: =VLOOKUP('E-impôts'!A60,Feuil2!$A$1:$AA$298,8,0) -> DCK-CGA2021-Q151 | F60: =VLOOKUP('E-impôts'!A60,Feuil2!$A$1:$AA$298,24,0) -> COCODY ANGRE 7E TRANCHE | G60: =VLOOKUP('E-impôts'!A60,Feuil2!$A$1:$AA$298,11,0) -> TEE | H60: =VLOOKUP('E-impôts'!A60,Feuil2!$A$1:$AA$298,10,0) -> SARL | I60: =VLOOKUP('E-impôts'!A60,Feuil2!$A$1:$AA$298,5,0) -> NULL | J60: =VLOOKUP('E-impôts'!A60,Feuil2!$A$1:$AA$298,19,0) -> 506898900 | K60: =VLOOKUP('E-impôts'!A60,Feuil2!$A$1:$AA$298,9,0) -> NULL | L60: =VLOOKUP('E-impôts'!A60,Feuil2!$A$1:$AA$298,15,0) -> II Plateaux III | M60: =VLOOKUP('E-impôts'!A60,Feuil2!$A$1:$AA$298,13,0) -> NULL | N60: =VLOOKUP('E-impôts'!A60,Feuil2!$A$1:$AA$298,14,0) -> NULL | O60: =VLOOKUP('E-impôts'!A60,Feuil2!$A$1:$AA$298,16,0) -> NULL | P60: =VLOOKUP(A60,Feuil2!$A$1:$AA$298,17,0) -> NULL
A61: 2244195W | B61: PRESTIGE INNOV | C61: =VLOOKUP('E-impôts'!A61,Feuil2!$A$1:$AA$298,4,0) -> DCK | D61: 44953 | E61: =VLOOKUP('E-impôts'!A61,Feuil2!$A$1:$AA$298,8,0) -> DCK-CGA-2023-J019 | F61: =VLOOKUP('E-impôts'!A61,Feuil2!$A$1:$AA$298,24,0) -> COCODY RIVIERA 3 | G61: =VLOOKUP('E-impôts'!A61,Feuil2!$A$1:$AA$298,11,0) -> TEE | H61: =VLOOKUP('E-impôts'!A61,Feuil2!$A$1:$AA$298,10,0) -> SARL | I61: =VLOOKUP('E-impôts'!A61,Feuil2!$A$1:$AA$298,5,0) -> BARRY FACINET | J61: =VLOOKUP('E-impôts'!A61,Feuil2!$A$1:$AA$298,19,0) -> 709310771 | K61: =VLOOKUP('E-impôts'!A61,Feuil2!$A$1:$AA$298,9,0) -> CI-ABJ-03-2022-B13-09162 | L61: =VLOOKUP('E-impôts'!A61,Feuil2!$A$1:$AA$298,15,0) -> II Plateaux III | M61: =VLOOKUP('E-impôts'!A61,Feuil2!$A$1:$AA$298,13,0) -> ES | N61: =VLOOKUP('E-impôts'!A61,Feuil2!$A$1:$AA$298,14,0) -> 73 | O61: J6200 | P61: =VLOOKUP(A61,Feuil2!$A$1:$AA$298,17,0) -> 1000000
A62: 2114065J | B62: POSY SECURITY AND SERVICES | C62: =VLOOKUP('E-impôts'!A62,Feuil2!$A$1:$AA$298,4,0) -> DCK | D62: 44588 | E62: =VLOOKUP('E-impôts'!A62,Feuil2!$A$1:$AA$298,8,0) -> DCK-CGA-2022-J011 | F62: =VLOOKUP('E-impôts'!A62,Feuil2!$A$1:$AA$298,24,0) -> COCODY ANGRE | G62: =VLOOKUP('E-impôts'!A62,Feuil2!$A$1:$AA$298,11,0) -> TEE | H62: =VLOOKUP('E-impôts'!A62,Feuil2!$A$1:$AA$298,10,0) -> SARL | I62: BADO AICHA GRACE | J62: =VLOOKUP('E-impôts'!A62,Feuil2!$A$1:$AA$298,19,0) -> 103041792 | K62: =VLOOKUP('E-impôts'!A62,Feuil2!$A$1:$AA$298,9,0) -> NULL | L62: =VLOOKUP('E-impôts'!A62,Feuil2!$A$1:$AA$298,15,0) -> II Plateaux I | M62: =VLOOKUP('E-impôts'!A62,Feuil2!$A$1:$AA$298,13,0) -> NULL | N62: =VLOOKUP('E-impôts'!A62,Feuil2!$A$1:$AA$298,14,0) -> NULL | O62: O8403 | P62: =VLOOKUP(A62,Feuil2!$A$1:$AA$298,17,0) -> NULL
A63: 1745011T | B63: POHAN KEMOANFOUOGNON AUGUSTE | C63: =VLOOKUP('E-impôts'!A63,Feuil2!$A$1:$AA$298,4,0) -> DCK | D63: 43858 | E63: =VLOOKUP('E-impôts'!A63,Feuil2!$A$1:$AA$298,8,0) -> DCK-CGA2020-A088 | F63: =VLOOKUP('E-impôts'!A63,Feuil2!$A$1:$AA$298,24,0) -> COCODY | G63: =VLOOKUP('E-impôts'!A63,Feuil2!$A$1:$AA$298,11,0) -> TEE | H63: =VLOOKUP('E-impôts'!A63,Feuil2!$A$1:$AA$298,10,0) -> ENTREPRISE INDIVIDUELLE | I63: =VLOOKUP('E-impôts'!A63,Feuil2!$A$1:$AA$298,5,0) -> POHAN KEMOANFOUOGON AUGUTE | J63: =VLOOKUP('E-impôts'!A63,Feuil2!$A$1:$AA$298,19,0) -> 778972145 | K63: =VLOOKUP('E-impôts'!A63,Feuil2!$A$1:$AA$298,9,0) -> CI-ABJ-2017-A-25544 | L63: =VLOOKUP('E-impôts'!A63,Feuil2!$A$1:$AA$298,15,0) -> II Plateaux III | M63: =VLOOKUP('E-impôts'!A63,Feuil2!$A$1:$AA$298,13,0) -> AO | N63: =VLOOKUP('E-impôts'!A63,Feuil2!$A$1:$AA$298,14,0) -> 527 | O63: =VLOOKUP('E-impôts'!A63,Feuil2!$A$1:$AA$298,16,0) -> SCE2399 | P63: =VLOOKUP(A63,Feuil2!$A$1:$AA$298,17,0) -> 0
A64: 2243368K | B64: PIZZA PIQUE VITE | C64: =VLOOKUP('E-impôts'!A64,Feuil2!$A$1:$AA$298,4,0) -> ZADI | D64: 44949 | E64: =VLOOKUP('E-impôts'!A64,Feuil2!$A$1:$AA$298,8,0) -> DCK-CGA2023-J016 | F64: =VLOOKUP('E-impôts'!A64,Feuil2!$A$1:$AA$298,24,0) -> ANGRE TERMINUS 81/8II | G64: =VLOOKUP('E-impôts'!A64,Feuil2!$A$1:$AA$298,11,0) -> TEE | H64: =VLOOKUP('E-impôts'!A64,Feuil2!$A$1:$AA$298,10,0) -> SARL | I64: =VLOOKUP('E-impôts'!A64,Feuil2!$A$1:$AA$298,5,0) -> NULL | J64: =VLOOKUP('E-impôts'!A64,Feuil2!$A$1:$AA$298,19,0) -> 702469090 | K64: =VLOOKUP('E-impôts'!A64,Feuil2!$A$1:$AA$298,9,0) -> NULL | L64: =VLOOKUP('E-impôts'!A64,Feuil2!$A$1:$AA$298,15,0) -> Bingerville | M64: =VLOOKUP('E-impôts'!A64,Feuil2!$A$1:$AA$298,13,0) -> NULL | N64: =VLOOKUP('E-impôts'!A64,Feuil2!$A$1:$AA$298,14,0) -> NULL | O64: =VLOOKUP('E-impôts'!A64,Feuil2!$A$1:$AA$298,16,0) -> NULL | P64: =VLOOKUP(A64,Feuil2!$A$1:$AA$298,17,0) -> NULL
A65: 1927845K | B65: PHILIPPE INES GROUPE | C65: =VLOOKUP('E-impôts'!A65,Feuil2!$A$1:$AA$298,4,0) -> DCK | D65: 44224 | E65: =VLOOKUP('E-impôts'!A65,Feuil2!$A$1:$AA$298,8,0) -> DCK-CGA-2021-Q174 | F65: =VLOOKUP('E-impôts'!A65,Feuil2!$A$1:$AA$298,24,0) -> II PLATEAUX | G65: =VLOOKUP('E-impôts'!A65,Feuil2!$A$1:$AA$298,11,0) -> TEE | H65: =VLOOKUP('E-impôts'!A65,Feuil2!$A$1:$AA$298,10,0) -> SARL | I65: =VLOOKUP('E-impôts'!A65,Feuil2!$A$1:$AA$298,5,0) -> NULL | J65: =VLOOKUP('E-impôts'!A65,Feuil2!$A$1:$AA$298,19,0) -> 77767968 | K65: =VLOOKUP('E-impôts'!A65,Feuil2!$A$1:$AA$298,9,0) -> NULL | L65: =VLOOKUP('E-impôts'!A65,Feuil2!$A$1:$AA$298,15,0) -> II Plateaux II | M65: =VLOOKUP('E-impôts'!A65,Feuil2!$A$1:$AA$298,13,0) -> NULL | N65: =VLOOKUP('E-impôts'!A65,Feuil2!$A$1:$AA$298,14,0) -> NULL | O65: =VLOOKUP('E-impôts'!A65,Feuil2!$A$1:$AA$298,16,0) -> NULL | P65: =VLOOKUP(A65,Feuil2!$A$1:$AA$298,17,0) -> NULL
A66: 1601549L | B66: PHARMA 7 | C66: =VLOOKUP('E-impôts'!A66,Feuil2!$A$1:$AA$298,4,0) -> #N/A | D66: 45127 | E66: =VLOOKUP('E-impôts'!A66,Feuil2!$A$1:$AA$298,8,0) -> DCK-CGA2023-J055 | F66: =VLOOKUP('E-impôts'!A66,Feuil2!$A$1:$AA$298,24,0) -> COCODY II PLATEAUX VALLONS | G66: =VLOOKUP('E-impôts'!A66,Feuil2!$A$1:$AA$298,11,0) -> TEE | H66: =VLOOKUP('E-impôts'!A66,Feuil2!$A$1:$AA$298,10,0) -> SARL | I66: =VLOOKUP('E-impôts'!A66,Feuil2!$A$1:$AA$298,5,0) -> TAI MARC JULES | J66: =VLOOKUP('E-impôts'!A66,Feuil2!$A$1:$AA$298,19,0) -> 07 07 37 45 74 | K66: =VLOOKUP('E-impôts'!A66,Feuil2!$A$1:$AA$298,9,0) -> CI-ABI-2016-B-555 | L66: =VLOOKUP('E-impôts'!A66,Feuil2!$A$1:$AA$298,15,0) -> II Pateaux II | M66: =VLOOKUP('E-impôts'!A66,Feuil2!$A$1:$AA$298,13,0) -> MV | N66: =VLOOKUP('E-impôts'!A66,Feuil2!$A$1:$AA$298,14,0) -> 45 | O66: =VLOOKUP('E-impôts'!A66,Feuil2!$A$1:$AA$298,16,0) -> N/D | P66: =VLOOKUP(A66,Feuil2!$A$1:$AA$298,17,0) -> 1000000
A67: 2136391L | B67: PERFORM WAVE CONSULTING | C67: =VLOOKUP('E-impôts'!A67,Feuil2!$A$1:$AA$298,4,0) -> DCK | D67: 44953 | E67: =VLOOKUP('E-impôts'!A67,Feuil2!$A$1:$AA$298,8,0) -> DCK-CGA-2023-J021 | F67: =VLOOKUP('E-impôts'!A67,Feuil2!$A$1:$AA$298,24,0) -> COCODY II PLATEAUX 7E TRANCHE | G67: =VLOOKUP('E-impôts'!A67,Feuil2!$A$1:$AA$298,11,0) -> TEE | H67: =VLOOKUP('E-impôts'!A67,Feuil2!$A$1:$AA$298,10,0) -> SARL | I67: =VLOOKUP('E-impôts'!A67,Feuil2!$A$1:$AA$298,5,0) -> FONTAINE JULIEN | J67: =VLOOKUP('E-impôts'!A67,Feuil2!$A$1:$AA$298,19,0) -> 797923730 | K67: =VLOOKUP('E-impôts'!A67,Feuil2!$A$1:$AA$298,9,0) -> CI-ABJ-03-2021-B12-02105 | L67: =VLOOKUP('E-impôts'!A67,Feuil2!$A$1:$AA$298,15,0) -> II Plateaux III | M67: =VLOOKUP('E-impôts'!A67,Feuil2!$A$1:$AA$298,13,0) -> OZ | N67: =VLOOKUP('E-impôts'!A67,Feuil2!$A$1:$AA$298,14,0) -> N/D | O67: I550000 | P67: =VLOOKUP(A67,Feuil2!$A$1:$AA$298,17,0) -> 700000
A68: 1985094H | B68: PECAM-SN SERVICES | C68: =VLOOKUP('E-impôts'!A68,Feuil2!$A$1:$AA$298,4,0) -> CABINET CFA | D68: 44224 | E68: =VLOOKUP('E-impôts'!A68,Feuil2!$A$1:$AA$298,8,0) -> DCK-CGA2021-Q170 | F68: =VLOOKUP('E-impôts'!A68,Feuil2!$A$1:$AA$298,24,0) -> COCODY CENTRE | G68: =VLOOKUP('E-impôts'!A68,Feuil2!$A$1:$AA$298,11,0) -> TEE | H68: =VLOOKUP('E-impôts'!A68,Feuil2!$A$1:$AA$298,10,0) -> SARL | I68: =VLOOKUP('E-impôts'!A68,Feuil2!$A$1:$AA$298,5,0) -> NULL | J68: =VLOOKUP('E-impôts'!A68,Feuil2!$A$1:$AA$298,19,0) -> 707181804 | K68: =VLOOKUP('E-impôts'!A68,Feuil2!$A$1:$AA$298,9,0) -> NULL | L68: =VLOOKUP('E-impôts'!A68,Feuil2!$A$1:$AA$298,15,0) -> Cocody | M68: =VLOOKUP('E-impôts'!A68,Feuil2!$A$1:$AA$298,13,0) -> NULL | N68: =VLOOKUP('E-impôts'!A68,Feuil2!$A$1:$AA$298,14,0) -> NULL | O68: =VLOOKUP('E-impôts'!A68,Feuil2!$A$1:$AA$298,16,0) -> NULL | P68: =VLOOKUP(A68,Feuil2!$A$1:$AA$298,17,0) -> NULL
A69: 2193152N | B69: PANDA GROUP 225 SARL | C69: =VLOOKUP('E-impôts'!A69,Feuil2!$A$1:$AA$298,4,0) -> #N/A | D69: 44628 | E69: =VLOOKUP('E-impôts'!A69,Feuil2!$A$1:$AA$298,8,0) -> #N/A | F69: =VLOOKUP('E-impôts'!A69,Feuil2!$A$1:$AA$298,24,0) -> #N/A | G69: =VLOOKUP('E-impôts'!A69,Feuil2!$A$1:$AA$298,11,0) -> #N/A | H69: =VLOOKUP('E-impôts'!A69,Feuil2!$A$1:$AA$298,10,0) -> #N/A | I69: =VLOOKUP('E-impôts'!A69,Feuil2!$A$1:$AA$298,5,0) -> #N/A | J69: =VLOOKUP('E-impôts'!A69,Feuil2!$A$1:$AA$298,19,0) -> #N/A | K69: =VLOOKUP('E-impôts'!A69,Feuil2!$A$1:$AA$298,9,0) -> #N/A | L69: =VLOOKUP('E-impôts'!A69,Feuil2!$A$1:$AA$298,15,0) -> #N/A | M69: =VLOOKUP('E-impôts'!A69,Feuil2!$A$1:$AA$298,13,0) -> #N/A | N69: =VLOOKUP('E-impôts'!A69,Feuil2!$A$1:$AA$298,14,0) -> #N/A | O69: =VLOOKUP('E-impôts'!A69,Feuil2!$A$1:$AA$298,16,0) -> #N/A | P69: =VLOOKUP(A69,Feuil2!$A$1:$AA$298,17,0) -> #N/A
A70: 2016975Q | B70: OZZY A-TRANSPORT | C70: =VLOOKUP('E-impôts'!A70,Feuil2!$A$1:$AA$298,4,0) -> #N/A | D70: 43905 | E70: =VLOOKUP('E-impôts'!A70,Feuil2!$A$1:$AA$298,8,0) -> #N/A | F70: =VLOOKUP('E-impôts'!A70,Feuil2!$A$1:$AA$298,24,0) -> #N/A | G70: =VLOOKUP('E-impôts'!A70,Feuil2!$A$1:$AA$298,11,0) -> #N/A | H70: =VLOOKUP('E-impôts'!A70,Feuil2!$A$1:$AA$298,10,0) -> #N/A | I70: =VLOOKUP('E-impôts'!A70,Feuil2!$A$1:$AA$298,5,0) -> #N/A | J70: =VLOOKUP('E-impôts'!A70,Feuil2!$A$1:$AA$298,19,0) -> #N/A | K70: =VLOOKUP('E-impôts'!A70,Feuil2!$A$1:$AA$298,9,0) -> #N/A | L70: =VLOOKUP('E-impôts'!A70,Feuil2!$A$1:$AA$298,15,0) -> #N/A | M70: =VLOOKUP('E-impôts'!A70,Feuil2!$A$1:$AA$298,13,0) -> #N/A | N70: =VLOOKUP('E-impôts'!A70,Feuil2!$A$1:$AA$298,14,0) -> #N/A | O70: =VLOOKUP('E-impôts'!A70,Feuil2!$A$1:$AA$298,16,0) -> #N/A | P70: =VLOOKUP(A70,Feuil2!$A$1:$AA$298,17,0) -> #N/A
A71: 1304077C | B71: OULD AMAR AHMED | C71: =VLOOKUP('E-impôts'!A71,Feuil2!$A$1:$AA$298,4,0) -> #N/A | D71: 44224 | E71: =VLOOKUP('E-impôts'!A71,Feuil2!$A$1:$AA$298,8,0) -> #N/A | F71: =VLOOKUP('E-impôts'!A71,Feuil2!$A$1:$AA$298,24,0) -> #N/A | G71: =VLOOKUP('E-impôts'!A71,Feuil2!$A$1:$AA$298,11,0) -> #N/A | H71: =VLOOKUP('E-impôts'!A71,Feuil2!$A$1:$AA$298,10,0) -> #N/A | I71: =VLOOKUP('E-impôts'!A71,Feuil2!$A$1:$AA$298,5,0) -> #N/A | J71: =VLOOKUP('E-impôts'!A71,Feuil2!$A$1:$AA$298,19,0) -> #N/A | K71: =VLOOKUP('E-impôts'!A71,Feuil2!$A$1:$AA$298,9,0) -> #N/A | L71: =VLOOKUP('E-impôts'!A71,Feuil2!$A$1:$AA$298,15,0) -> #N/A | M71: =VLOOKUP('E-impôts'!A71,Feuil2!$A$1:$AA$298,13,0) -> #N/A | N71: =VLOOKUP('E-impôts'!A71,Feuil2!$A$1:$AA$298,14,0) -> #N/A | O71: =VLOOKUP('E-impôts'!A71,Feuil2!$A$1:$AA$298,16,0) -> #N/A | P71: =VLOOKUP(A71,Feuil2!$A$1:$AA$298,17,0) -> #N/A
A72: 1414480Q | B72: OUEDRAOGO YOUSSOUF(ETS O.Y) | C72: =VLOOKUP('E-impôts'!A72,Feuil2!$A$1:$AA$298,4,0) -> DCK | D72: 43479 | E72: =VLOOKUP('E-impôts'!A72,Feuil2!$A$1:$AA$298,8,0) -> DCK-CGA2019-A023 | F72: =VLOOKUP('E-impôts'!A72,Feuil2!$A$1:$AA$298,24,0) -> COCODY SAINT JEAN | G72: =VLOOKUP('E-impôts'!A72,Feuil2!$A$1:$AA$298,11,0) -> TEE | H72: =VLOOKUP('E-impôts'!A72,Feuil2!$A$1:$AA$298,10,0) -> ENTREPRISE INDIVIDUELLE | I72: OUEDRAOGO YOUSSOUF(ETS O.Y) | J72: =VLOOKUP('E-impôts'!A72,Feuil2!$A$1:$AA$298,19,0) -> 707582591 | K72: =VLOOKUP('E-impôts'!A72,Feuil2!$A$1:$AA$298,9,0) -> NULL | L72: =VLOOKUP('E-impôts'!A72,Feuil2!$A$1:$AA$298,15,0) -> Cocody | M72: =VLOOKUP('E-impôts'!A72,Feuil2!$A$1:$AA$298,13,0) -> NULL | N72: =VLOOKUP('E-impôts'!A72,Feuil2!$A$1:$AA$298,14,0) -> NULL | O72: G620002 | P72: =VLOOKUP(A72,Feuil2!$A$1:$AA$298,17,0) -> NULL
A73: 2242082Y | B73: OUATTARA AYOUBA | C73: =VLOOKUP('E-impôts'!A73,Feuil2!$A$1:$AA$298,4,0) -> #N/A | D73: 44957 | E73: =VLOOKUP('E-impôts'!A73,Feuil2!$A$1:$AA$298,8,0) -> DCK-CGA2024-A058 | F73: =VLOOKUP('E-impôts'!A73,Feuil2!$A$1:$AA$298,24,0) -> BINGERVILLE GBAGBA | G73: =VLOOKUP('E-impôts'!A73,Feuil2!$A$1:$AA$298,11,0) -> TEE | H73: =VLOOKUP('E-impôts'!A73,Feuil2!$A$1:$AA$298,10,0) -> ENTREPRISE INDIVIDUELLE | I73: =VLOOKUP('E-impôts'!A73,Feuil2!$A$1:$AA$298,5,0) -> OUATTARA AYOUBA | J73: =VLOOKUP('E-impôts'!A73,Feuil2!$A$1:$AA$298,19,0) -> 709595813 | K73: =VLOOKUP('E-impôts'!A73,Feuil2!$A$1:$AA$298,9,0) -> CI-ABJ-03-2022-A10-01730 | L73: =VLOOKUP('E-impôts'!A73,Feuil2!$A$1:$AA$298,15,0) -> Bingerville | M73: =VLOOKUP('E-impôts'!A73,Feuil2!$A$1:$AA$298,13,0) -> 0 | N73: =VLOOKUP('E-impôts'!A73,Feuil2!$A$1:$AA$298,14,0) -> 0 | O73: =VLOOKUP('E-impôts'!A73,Feuil2!$A$1:$AA$298,16,0) -> SCE1702 | P73: =VLOOKUP(A73,Feuil2!$A$1:$AA$298,17,0) -> 0
A74: 2242082Y | B74: OUATTARA AYOUBA | C74: =VLOOKUP('E-impôts'!A74,Feuil2!$A$1:$AA$298,4,0) -> #N/A | D74: 44957 | E74: =VLOOKUP('E-impôts'!A74,Feuil2!$A$1:$AA$298,8,0) -> DCK-CGA2024-A058 | F74: =VLOOKUP('E-impôts'!A74,Feuil2!$A$1:$AA$298,24,0) -> BINGERVILLE GBAGBA | G74: =VLOOKUP('E-impôts'!A74,Feuil2!$A$1:$AA$298,11,0) -> TEE | H74: =VLOOKUP('E-impôts'!A74,Feuil2!$A$1:$AA$298,10,0) -> ENTREPRISE INDIVIDUELLE | I74: =VLOOKUP('E-impôts'!A74,Feuil2!$A$1:$AA$298,5,0) -> OUATTARA AYOUBA | J74: =VLOOKUP('E-impôts'!A74,Feuil2!$A$1:$AA$298,19,0) -> 709595813 | K74: =VLOOKUP('E-impôts'!A74,Feuil2!$A$1:$AA$298,9,0) -> CI-ABJ-03-2022-A10-01730 | L74: =VLOOKUP('E-impôts'!A74,Feuil2!$A$1:$AA$298,15,0) -> Bingerville | M74: =VLOOKUP('E-impôts'!A74,Feuil2!$A$1:$AA$298,13,0) -> 0 | N74: =VLOOKUP('E-impôts'!A74,Feuil2!$A$1:$AA$298,14,0) -> 0 | O74: =VLOOKUP('E-impôts'!A74,Feuil2!$A$1:$AA$298,16,0) -> SCE1702 | P74: =VLOOKUP(A74,Feuil2!$A$1:$AA$298,17,0) -> 0
A75: 0194302G | B75: ORSOT Bosson Josephine Laure | C75: =VLOOKUP('E-impôts'!A75,Feuil2!$A$1:$AA$298,4,0) -> #N/A | D75: 43479 | E75: =VLOOKUP('E-impôts'!A75,Feuil2!$A$1:$AA$298,8,0) -> #N/A | F75: =VLOOKUP('E-impôts'!A75,Feuil2!$A$1:$AA$298,24,0) -> #N/A | G75: =VLOOKUP('E-impôts'!A75,Feuil2!$A$1:$AA$298,11,0) -> #N/A | H75: =VLOOKUP('E-impôts'!A75,Feuil2!$A$1:$AA$298,10,0) -> #N/A | I75: =VLOOKUP('E-impôts'!A75,Feuil2!$A$1:$AA$298,5,0) -> #N/A | J75: =VLOOKUP('E-impôts'!A75,Feuil2!$A$1:$AA$298,19,0) -> #N/A | K75: =VLOOKUP('E-impôts'!A75,Feuil2!$A$1:$AA$298,9,0) -> #N/A | L75: =VLOOKUP('E-impôts'!A75,Feuil2!$A$1:$AA$298,15,0) -> #N/A | M75: =VLOOKUP('E-impôts'!A75,Feuil2!$A$1:$AA$298,13,0) -> #N/A | N75: =VLOOKUP('E-impôts'!A75,Feuil2!$A$1:$AA$298,14,0) -> #N/A | O75: =VLOOKUP('E-impôts'!A75,Feuil2!$A$1:$AA$298,16,0) -> #N/A | P75: =VLOOKUP(A75,Feuil2!$A$1:$AA$298,17,0) -> #N/A
A76: 1947542X | B76: OREMUS SERVICES | C76: =VLOOKUP('E-impôts'!A76,Feuil2!$A$1:$AA$298,4,0) -> DCK | D76: 45322 | E76: =VLOOKUP('E-impôts'!A76,Feuil2!$A$1:$AA$298,8,0) -> DCK-CGA2024-A050 | F76: =VLOOKUP('E-impôts'!A76,Feuil2!$A$1:$AA$298,24,0) -> COCODY II PLATEAUX VALLON | G76: =VLOOKUP('E-impôts'!A76,Feuil2!$A$1:$AA$298,11,0) -> TEE | H76: =VLOOKUP('E-impôts'!A76,Feuil2!$A$1:$AA$298,10,0) -> SARL | I76: =VLOOKUP('E-impôts'!A76,Feuil2!$A$1:$AA$298,5,0) -> YEBOUE EPSE BOUAH ADJOUA IRENE | J76: =VLOOKUP('E-impôts'!A76,Feuil2!$A$1:$AA$298,19,0) -> 707830824 | K76: =VLOOKUP('E-impôts'!A76,Feuil2!$A$1:$AA$298,9,0) -> CI-ABJ-2019-B-17445 | L76: =VLOOKUP('E-impôts'!A76,Feuil2!$A$1:$AA$298,15,0) -> II Pateaux II | M76: =VLOOKUP('E-impôts'!A76,Feuil2!$A$1:$AA$298,13,0) -> N/D | N76: =VLOOKUP('E-impôts'!A76,Feuil2!$A$1:$AA$298,14,0) -> N/D | O76: N770002 | P76: =VLOOKUP(A76,Feuil2!$A$1:$AA$298,17,0) -> 5000000
A77: 1913158U | B77: ONYX GROUP PUDER | C77: =VLOOKUP('E-impôts'!A77,Feuil2!$A$1:$AA$298,4,0) -> #N/A | D77: 44592 | E77: =VLOOKUP('E-impôts'!A77,Feuil2!$A$1:$AA$298,8,0) -> #N/A | F77: =VLOOKUP('E-impôts'!A77,Feuil2!$A$1:$AA$298,24,0) -> #N/A | G77: =VLOOKUP('E-impôts'!A77,Feuil2!$A$1:$AA$298,11,0) -> #N/A | H77: =VLOOKUP('E-impôts'!A77,Feuil2!$A$1:$AA$298,10,0) -> #N/A | I77: =VLOOKUP('E-impôts'!A77,Feuil2!$A$1:$AA$298,5,0) -> #N/A | J77: =VLOOKUP('E-impôts'!A77,Feuil2!$A$1:$AA$298,19,0) -> #N/A | K77: =VLOOKUP('E-impôts'!A77,Feuil2!$A$1:$AA$298,9,0) -> #N/A | L77: =VLOOKUP('E-impôts'!A77,Feuil2!$A$1:$AA$298,15,0) -> #N/A | M77: =VLOOKUP('E-impôts'!A77,Feuil2!$A$1:$AA$298,13,0) -> #N/A | N77: =VLOOKUP('E-impôts'!A77,Feuil2!$A$1:$AA$298,14,0) -> #N/A | O77: =VLOOKUP('E-impôts'!A77,Feuil2!$A$1:$AA$298,16,0) -> #N/A | P77: =VLOOKUP(A77,Feuil2!$A$1:$AA$298,17,0) -> #N/A
A78: 0510821Y | B78: OLALEKAN DAVID OLALEKAN | C78: =VLOOKUP('E-impôts'!A78,Feuil2!$A$1:$AA$298,4,0) -> #N/A | D78: 43857 | E78: =VLOOKUP('E-impôts'!A78,Feuil2!$A$1:$AA$298,8,0) -> #N/A | F78: =VLOOKUP('E-impôts'!A78,Feuil2!$A$1:$AA$298,24,0) -> #N/A | G78: =VLOOKUP('E-impôts'!A78,Feuil2!$A$1:$AA$298,11,0) -> #N/A | H78: =VLOOKUP('E-impôts'!A78,Feuil2!$A$1:$AA$298,10,0) -> #N/A | I78: =VLOOKUP('E-impôts'!A78,Feuil2!$A$1:$AA$298,5,0) -> #N/A | J78: =VLOOKUP('E-impôts'!A78,Feuil2!$A$1:$AA$298,19,0) -> #N/A | K78: =VLOOKUP('E-impôts'!A78,Feuil2!$A$1:$AA$298,9,0) -> #N/A | L78: =VLOOKUP('E-impôts'!A78,Feuil2!$A$1:$AA$298,15,0) -> #N/A | M78: =VLOOKUP('E-impôts'!A78,Feuil2!$A$1:$AA$298,13,0) -> #N/A | N78: =VLOOKUP('E-impôts'!A78,Feuil2!$A$1:$AA$298,14,0) -> #N/A | O78: =VLOOKUP('E-impôts'!A78,Feuil2!$A$1:$AA$298,16,0) -> #N/A | P78: =VLOOKUP(A78,Feuil2!$A$1:$AA$298,17,0) -> #N/A
A79: 2144859H | B79: OKEY GROUP | C79: =VLOOKUP('E-impôts'!A79,Feuil2!$A$1:$AA$298,4,0) -> CABINET CFA | D79: 44592 | E79: =VLOOKUP('E-impôts'!A79,Feuil2!$A$1:$AA$298,8,0) -> DCK-CGA2022-J044 | F79: =VLOOKUP('E-impôts'!A79,Feuil2!$A$1:$AA$298,24,0) -> COCODY RIVIERA II | G79: =VLOOKUP('E-impôts'!A79,Feuil2!$A$1:$AA$298,11,0) -> TEE | H79: =VLOOKUP('E-impôts'!A79,Feuil2!$A$1:$AA$298,10,0) -> SARL | I79: =VLOOKUP('E-impôts'!A79,Feuil2!$A$1:$AA$298,5,0) -> NULL | J79: =VLOOKUP('E-impôts'!A79,Feuil2!$A$1:$AA$298,19,0) -> 789843555 | K79: =VLOOKUP('E-impôts'!A79,Feuil2!$A$1:$AA$298,9,0) -> NULL | L79: =VLOOKUP('E-impôts'!A79,Feuil2!$A$1:$AA$298,15,0) -> Riviera I | M79: =VLOOKUP('E-impôts'!A79,Feuil2!$A$1:$AA$298,13,0) -> NULL | N79: =VLOOKUP('E-impôts'!A79,Feuil2!$A$1:$AA$298,14,0) -> NULL | O79: =VLOOKUP('E-impôts'!A79,Feuil2!$A$1:$AA$298,16,0) -> NULL | P79: =VLOOKUP(A79,Feuil2!$A$1:$AA$298,17,0) -> NULL
A80: 2242840T | B80: OILFIELD ENGINEERING AND SERVICES GROUP SARL | C80: =VLOOKUP('E-impôts'!A80,Feuil2!$A$1:$AA$298,4,0) -> #N/A | D80: 45322 | E80: =VLOOKUP('E-impôts'!A80,Feuil2!$A$1:$AA$298,8,0) -> DCK-CGA2024-A061 | F80: =VLOOKUP('E-impôts'!A80,Feuil2!$A$1:$AA$298,24,0) -> BINGERVILLE AKWE DJEMIN FACE A L'EGLISE METHODISTE | G80: =VLOOKUP('E-impôts'!A80,Feuil2!$A$1:$AA$298,11,0) -> TEE | H80: =VLOOKUP('E-impôts'!A80,Feuil2!$A$1:$AA$298,10,0) -> SARL | I80: =VLOOKUP('E-impôts'!A80,Feuil2!$A$1:$AA$298,5,0) -> YAPO JEAN-MARIUS | J80: =VLOOKUP('E-impôts'!A80,Feuil2!$A$1:$AA$298,19,0) -> 707008495 | K80: =VLOOKUP('E-impôts'!A80,Feuil2!$A$1:$AA$298,9,0) -> CI-ABJ-03-2022-B12-04022 | L80: =VLOOKUP('E-impôts'!A80,Feuil2!$A$1:$AA$298,15,0) -> Riviera II | M80: =VLOOKUP('E-impôts'!A80,Feuil2!$A$1:$AA$298,13,0) -> ND | N80: =VLOOKUP('E-impôts'!A80,Feuil2!$A$1:$AA$298,14,0) -> ND | O80: =VLOOKUP('E-impôts'!A80,Feuil2!$A$1:$AA$298,16,0) -> IND0201 | P80: =VLOOKUP(A80,Feuil2!$A$1:$AA$298,17,0) -> 1000000
A81: 2110932L | B81: O' D'AFRIQUE | C81: =VLOOKUP('E-impôts'!A81,Feuil2!$A$1:$AA$298,4,0) -> CABINET CFA | D81: 44265 | E81: =VLOOKUP('E-impôts'!A81,Feuil2!$A$1:$AA$298,8,0) -> DCK-CGA2021-Q169 | F81: =VLOOKUP('E-impôts'!A81,Feuil2!$A$1:$AA$298,24,0) -> ANGRE 8E TRANCHE | G81: =VLOOKUP('E-impôts'!A81,Feuil2!$A$1:$AA$298,11,0) -> TEE | H81: =VLOOKUP('E-impôts'!A81,Feuil2!$A$1:$AA$298,10,0) -> SARL | I81: =VLOOKUP('E-impôts'!A81,Feuil2!$A$1:$AA$298,5,0) -> AMICHIA AMOIN MARIE CLAIRE | J81: =VLOOKUP('E-impôts'!A81,Feuil2!$A$1:$AA$298,19,0) -> 708759006 | K81: =VLOOKUP('E-impôts'!A81,Feuil2!$A$1:$AA$298,9,0) -> CI-ABJ-03-2023-B22-00002 | L81: =VLOOKUP('E-impôts'!A81,Feuil2!$A$1:$AA$298,15,0) -> II Pateaux I | M81: =VLOOKUP('E-impôts'!A81,Feuil2!$A$1:$AA$298,13,0) -> N/D | N81: =VLOOKUP('E-impôts'!A81,Feuil2!$A$1:$AA$298,14,0) -> N/D | O81: =VLOOKUP('E-impôts'!A81,Feuil2!$A$1:$AA$298,16,0) -> N/D | P81: =VLOOKUP(A81,Feuil2!$A$1:$AA$298,17,0) -> 1000000
A82: 2033895A | B82: N3H IMMOBILIER CÔTE D'IVOIRE | C82: =VLOOKUP('E-impôts'!A82,Feuil2!$A$1:$AA$298,4,0) -> GOHI | D82: 44592 | E82: =VLOOKUP('E-impôts'!A82,Feuil2!$A$1:$AA$298,8,0) -> DCK-CGA2022-J046 | F82: =VLOOKUP('E-impôts'!A82,Feuil2!$A$1:$AA$298,24,0) -> COCODY BLAUCKAUSS | G82: =VLOOKUP('E-impôts'!A82,Feuil2!$A$1:$AA$298,11,0) -> TEE | H82: =VLOOKUP('E-impôts'!A82,Feuil2!$A$1:$AA$298,10,0) -> SAS | I82: =VLOOKUP('E-impôts'!A82,Feuil2!$A$1:$AA$298,5,0) -> NULL | J82: =VLOOKUP('E-impôts'!A82,Feuil2!$A$1:$AA$298,19,0) -> 0 | K82: =VLOOKUP('E-impôts'!A82,Feuil2!$A$1:$AA$298,9,0) -> NULL | L82: =VLOOKUP('E-impôts'!A82,Feuil2!$A$1:$AA$298,15,0) -> Cocody | M82: =VLOOKUP('E-impôts'!A82,Feuil2!$A$1:$AA$298,13,0) -> NULL | N82: =VLOOKUP('E-impôts'!A82,Feuil2!$A$1:$AA$298,14,0) -> NULL | O82: =VLOOKUP('E-impôts'!A82,Feuil2!$A$1:$AA$298,16,0) -> NULL | P82: =VLOOKUP(A82,Feuil2!$A$1:$AA$298,17,0) -> NULL
A83: 2401945K | B83: NOVATEL TECHNOLOGY | C83: =VLOOKUP('E-impôts'!A83,Feuil2!$A$1:$AA$298,4,0) -> #N/A | D83: 45462 | E83: =VLOOKUP('E-impôts'!A83,Feuil2!$A$1:$AA$298,8,0) -> #N/A | F83: =VLOOKUP('E-impôts'!A83,Feuil2!$A$1:$AA$298,24,0) -> #N/A | G83: =VLOOKUP('E-impôts'!A83,Feuil2!$A$1:$AA$298,11,0) -> #N/A | H83: =VLOOKUP('E-impôts'!A83,Feuil2!$A$1:$AA$298,10,0) -> #N/A | I83: =VLOOKUP('E-impôts'!A83,Feuil2!$A$1:$AA$298,5,0) -> #N/A | J83: =VLOOKUP('E-impôts'!A83,Feuil2!$A$1:$AA$298,19,0) -> #N/A | K83: =VLOOKUP('E-impôts'!A83,Feuil2!$A$1:$AA$298,9,0) -> #N/A | L83: =VLOOKUP('E-impôts'!A83,Feuil2!$A$1:$AA$298,15,0) -> #N/A | M83: =VLOOKUP('E-impôts'!A83,Feuil2!$A$1:$AA$298,13,0) -> #N/A | N83: =VLOOKUP('E-impôts'!A83,Feuil2!$A$1:$AA$298,14,0) -> #N/A | O83: =VLOOKUP('E-impôts'!A83,Feuil2!$A$1:$AA$298,16,0) -> #N/A | P83: =VLOOKUP(A83,Feuil2!$A$1:$AA$298,17,0) -> #N/A
A84: 2305435H | B84: NOKOMA GROUP | C84: =VLOOKUP('E-impôts'!A84,Feuil2!$A$1:$AA$298,4,0) -> #N/A | D84: 45321 | E84: =VLOOKUP('E-impôts'!A84,Feuil2!$A$1:$AA$298,8,0) -> DCK-CGA2024-A085 | F84: =VLOOKUP('E-impôts'!A84,Feuil2!$A$1:$AA$298,24,0) -> COCODY ANGRE DJOROGOBITE 2 | G84: =VLOOKUP('E-impôts'!A84,Feuil2!$A$1:$AA$298,11,0) -> TEE | H84: =VLOOKUP('E-impôts'!A84,Feuil2!$A$1:$AA$298,10,0) -> SARL | I84: =VLOOKUP('E-impôts'!A84,Feuil2!$A$1:$AA$298,5,0) -> OUEDRAOGO WENPANGA MARIUS | J84: =VLOOKUP('E-impôts'!A84,Feuil2!$A$1:$AA$298,19,0) -> 07 07 79 93 33 65 | K84: =VLOOKUP('E-impôts'!A84,Feuil2!$A$1:$AA$298,9,0) -> CI-ABJ-03-2023-B12-05456 | L84: =VLOOKUP('E-impôts'!A84,Feuil2!$A$1:$AA$298,15,0) -> II Plateaux Djibi | M84: =VLOOKUP('E-impôts'!A84,Feuil2!$A$1:$AA$298,13,0) -> VZ | N84: =VLOOKUP('E-impôts'!A84,Feuil2!$A$1:$AA$298,14,0) -> 50 | O84: =VLOOKUP('E-impôts'!A84,Feuil2!$A$1:$AA$298,16,0) -> IND1504 | P84: =VLOOKUP(A84,Feuil2!$A$1:$AA$298,17,0) -> 1000000
A85: 2151700M | B85: NJIR INVEST S.A.R.L | C85: =VLOOKUP('E-impôts'!A85,Feuil2!$A$1:$AA$298,4,0) -> KOFFI ALBERT | D85: 44589 | E85: =VLOOKUP('E-impôts'!A85,Feuil2!$A$1:$AA$298,8,0) -> DCK-CGA2022-J025 | F85: =VLOOKUP('E-impôts'!A85,Feuil2!$A$1:$AA$298,24,0) -> ABATTA | G85: =VLOOKUP('E-impôts'!A85,Feuil2!$A$1:$AA$298,11,0) -> TEE | H85: =VLOOKUP('E-impôts'!A85,Feuil2!$A$1:$AA$298,10,0) -> SARL | I85: =VLOOKUP('E-impôts'!A85,Feuil2!$A$1:$AA$298,5,0) -> NULL | J85: =VLOOKUP('E-impôts'!A85,Feuil2!$A$1:$AA$298,19,0) -> 505199503 | K85: =VLOOKUP('E-impôts'!A85,Feuil2!$A$1:$AA$298,9,0) -> NULL | L85: =VLOOKUP('E-impôts'!A85,Feuil2!$A$1:$AA$298,15,0) -> Bingerville | M85: =VLOOKUP('E-impôts'!A85,Feuil2!$A$1:$AA$298,13,0) -> NULL | N85: =VLOOKUP('E-impôts'!A85,Feuil2!$A$1:$AA$298,14,0) -> NULL | O85: =VLOOKUP('E-impôts'!A85,Feuil2!$A$1:$AA$298,16,0) -> NULL | P85: =VLOOKUP(A85,Feuil2!$A$1:$AA$298,17,0) -> NULL
A86: 2301751W | B86: NICKO EXAUCEE | C86: =VLOOKUP('E-impôts'!A86,Feuil2!$A$1:$AA$298,4,0) -> #N/A | D86: 45069 | E86: =VLOOKUP('E-impôts'!A86,Feuil2!$A$1:$AA$298,8,0) -> #N/A | F86: =VLOOKUP('E-impôts'!A86,Feuil2!$A$1:$AA$298,24,0) -> #N/A | G86: =VLOOKUP('E-impôts'!A86,Feuil2!$A$1:$AA$298,11,0) -> #N/A | H86: =VLOOKUP('E-impôts'!A86,Feuil2!$A$1:$AA$298,10,0) -> #N/A | I86: =VLOOKUP('E-impôts'!A86,Feuil2!$A$1:$AA$298,5,0) -> #N/A | J86: =VLOOKUP('E-impôts'!A86,Feuil2!$A$1:$AA$298,19,0) -> #N/A | K86: =VLOOKUP('E-impôts'!A86,Feuil2!$A$1:$AA$298,9,0) -> #N/A | L86: =VLOOKUP('E-impôts'!A86,Feuil2!$A$1:$AA$298,15,0) -> #N/A | M86: =VLOOKUP('E-impôts'!A86,Feuil2!$A$1:$AA$298,13,0) -> #N/A | N86: =VLOOKUP('E-impôts'!A86,Feuil2!$A$1:$AA$298,14,0) -> #N/A | O86: =VLOOKUP('E-impôts'!A86,Feuil2!$A$1:$AA$298,16,0) -> #N/A | P86: =VLOOKUP(A86,Feuil2!$A$1:$AA$298,17,0) -> #N/A
A87: 0310365V | B87: N'GUESSAN née N'GORAN ANNE | C87: =VLOOKUP('E-impôts'!A87,Feuil2!$A$1:$AA$298,4,0) -> #N/A | D87: 43857 | E87: =VLOOKUP('E-impôts'!A87,Feuil2!$A$1:$AA$298,8,0) -> #N/A | F87: =VLOOKUP('E-impôts'!A87,Feuil2!$A$1:$AA$298,24,0) -> #N/A | G87: =VLOOKUP('E-impôts'!A87,Feuil2!$A$1:$AA$298,11,0) -> #N/A | H87: =VLOOKUP('E-impôts'!A87,Feuil2!$A$1:$AA$298,10,0) -> #N/A | I87: =VLOOKUP('E-impôts'!A87,Feuil2!$A$1:$AA$298,5,0) -> #N/A | J87: =VLOOKUP('E-impôts'!A87,Feuil2!$A$1:$AA$298,19,0) -> #N/A | K87: =VLOOKUP('E-impôts'!A87,Feuil2!$A$1:$AA$298,9,0) -> #N/A | L87: =VLOOKUP('E-impôts'!A87,Feuil2!$A$1:$AA$298,15,0) -> #N/A | M87: =VLOOKUP('E-impôts'!A87,Feuil2!$A$1:$AA$298,13,0) -> #N/A | N87: =VLOOKUP('E-impôts'!A87,Feuil2!$A$1:$AA$298,14,0) -> #N/A | O87: =VLOOKUP('E-impôts'!A87,Feuil2!$A$1:$AA$298,16,0) -> #N/A | P87: =VLOOKUP(A87,Feuil2!$A$1:$AA$298,17,0) -> #N/A
A88: 1307492V | B88: N'GUESSAN ATTIEGOUA ANNE ELLA | C88: =VLOOKUP('E-impôts'!A88,Feuil2!$A$1:$AA$298,4,0) -> DCK | D88: 43479 | E88: =VLOOKUP('E-impôts'!A88,Feuil2!$A$1:$AA$298,8,0) -> DCK-CGA2019-A010 | F88: =VLOOKUP('E-impôts'!A88,Feuil2!$A$1:$AA$298,24,0) -> II PLATEUX VALLON | G88: =VLOOKUP('E-impôts'!A88,Feuil2!$A$1:$AA$298,11,0) -> TEE | H88: =VLOOKUP('E-impôts'!A88,Feuil2!$A$1:$AA$298,10,0) -> ENTREPRISE INDIVIDUELLE | I88: N'GUESSAN ATTIEGOUA ANNE ELLA | J88: =VLOOKUP('E-impôts'!A88,Feuil2!$A$1:$AA$298,19,0) -> 708048295 | K88: =VLOOKUP('E-impôts'!A88,Feuil2!$A$1:$AA$298,9,0) -> NULL | L88: =VLOOKUP('E-impôts'!A88,Feuil2!$A$1:$AA$298,15,0) -> II Plateaux II | M88: =VLOOKUP('E-impôts'!A88,Feuil2!$A$1:$AA$298,13,0) -> NULL | N88: =VLOOKUP('E-impôts'!A88,Feuil2!$A$1:$AA$298,14,0) -> NULL | O88: H51001 | P88: =VLOOKUP(A88,Feuil2!$A$1:$AA$298,17,0) -> NULL
A89: 1619903H | B89: NEDJMA SARLU | C89: =VLOOKUP('E-impôts'!A89,Feuil2!$A$1:$AA$298,4,0) -> DCK | D89: 43479 | E89: =VLOOKUP('E-impôts'!A89,Feuil2!$A$1:$AA$298,8,0) -> DCK-CGA2019-A029 | F89: =VLOOKUP('E-impôts'!A89,Feuil2!$A$1:$AA$298,24,0) -> COCODY RIVIERA BONOUMIN | G89: =VLOOKUP('E-impôts'!A89,Feuil2!$A$1:$AA$298,11,0) -> TEE | H89: =VLOOKUP('E-impôts'!A89,Feuil2!$A$1:$AA$298,10,0) -> SARL | I89: =VLOOKUP('E-impôts'!A89,Feuil2!$A$1:$AA$298,5,0) -> NULL | J89: =VLOOKUP('E-impôts'!A89,Feuil2!$A$1:$AA$298,19,0) -> 707070102 | K89: =VLOOKUP('E-impôts'!A89,Feuil2!$A$1:$AA$298,9,0) -> NULL | L89: =VLOOKUP('E-impôts'!A89,Feuil2!$A$1:$AA$298,15,0) -> II Plateaux I | M89: =VLOOKUP('E-impôts'!A89,Feuil2!$A$1:$AA$298,13,0) -> NULL | N89: =VLOOKUP('E-impôts'!A89,Feuil2!$A$1:$AA$298,14,0) -> NULL | O89: =VLOOKUP('E-impôts'!A89,Feuil2!$A$1:$AA$298,16,0) -> NULL | P89: =VLOOKUP(A89,Feuil2!$A$1:$AA$298,17,0) -> NULL
A90: 1748908X | B90: N'DAH AFFOUE JOSIANE | C90: =VLOOKUP('E-impôts'!A90,Feuil2!$A$1:$AA$298,4,0) -> #N/A | D90: 44224 | E90: =VLOOKUP('E-impôts'!A90,Feuil2!$A$1:$AA$298,8,0) -> #N/A | F90: =VLOOKUP('E-impôts'!A90,Feuil2!$A$1:$AA$298,24,0) -> #N/A | G90: =VLOOKUP('E-impôts'!A90,Feuil2!$A$1:$AA$298,11,0) -> #N/A | H90: =VLOOKUP('E-impôts'!A90,Feuil2!$A$1:$AA$298,10,0) -> #N/A | I90: =VLOOKUP('E-impôts'!A90,Feuil2!$A$1:$AA$298,5,0) -> #N/A | J90: =VLOOKUP('E-impôts'!A90,Feuil2!$A$1:$AA$298,19,0) -> #N/A | K90: =VLOOKUP('E-impôts'!A90,Feuil2!$A$1:$AA$298,9,0) -> #N/A | L90: =VLOOKUP('E-impôts'!A90,Feuil2!$A$1:$AA$298,15,0) -> #N/A | M90: =VLOOKUP('E-impôts'!A90,Feuil2!$A$1:$AA$298,13,0) -> #N/A | N90: =VLOOKUP('E-impôts'!A90,Feuil2!$A$1:$AA$298,14,0) -> #N/A | O90: =VLOOKUP('E-impôts'!A90,Feuil2!$A$1:$AA$298,16,0) -> #N/A | P90: =VLOOKUP(A90,Feuil2!$A$1:$AA$298,17,0) -> #N/A
A91: 2304040S | B91: NAOMI TRANSPORT | C91: =VLOOKUP('E-impôts'!A91,Feuil2!$A$1:$AA$298,4,0) -> #N/A | D91: 45316 | E91: =VLOOKUP('E-impôts'!A91,Feuil2!$A$1:$AA$298,8,0) -> DCK-CGA2024-A036 | F91: =VLOOKUP('E-impôts'!A91,Feuil2!$A$1:$AA$298,24,0) -> ANGRE STAR 8Ã¨me | G91: =VLOOKUP('E-impôts'!A91,Feuil2!$A$1:$AA$298,11,0) -> TEE | H91: =VLOOKUP('E-impôts'!A91,Feuil2!$A$1:$AA$298,10,0) -> SARL | I91: =VLOOKUP('E-impôts'!A91,Feuil2!$A$1:$AA$298,5,0) -> DJAHO SERAPHIN | J91: =VLOOKUP('E-impôts'!A91,Feuil2!$A$1:$AA$298,19,0) -> 779241124 | K91: =VLOOKUP('E-impôts'!A91,Feuil2!$A$1:$AA$298,9,0) -> CI-ABJ-03-2023-B12-05053 | L91: =VLOOKUP('E-impôts'!A91,Feuil2!$A$1:$AA$298,15,0) -> II Pateaux I | M91: =VLOOKUP('E-impôts'!A91,Feuil2!$A$1:$AA$298,13,0) -> 0 | N91: =VLOOKUP('E-impôts'!A91,Feuil2!$A$1:$AA$298,14,0) -> 0 | O91: =VLOOKUP('E-impôts'!A91,Feuil2!$A$1:$AA$298,16,0) -> 0 | P91: =VLOOKUP(A91,Feuil2!$A$1:$AA$298,17,0) -> 1000000
A92: 2109934S | B92: NAME CI | C92: =VLOOKUP('E-impôts'!A92,Feuil2!$A$1:$AA$298,4,0) -> #N/A | D92: 45321 | E92: =VLOOKUP('E-impôts'!A92,Feuil2!$A$1:$AA$298,8,0) -> DCK-CGA2024-A082 | F92: =VLOOKUP('E-impôts'!A92,Feuil2!$A$1:$AA$298,24,0) -> ABIDJAN COCODY RIVIERA PALMERAIE RUE MINISTRE | G92: =VLOOKUP('E-impôts'!A92,Feuil2!$A$1:$AA$298,11,0) -> TEE | H92: =VLOOKUP('E-impôts'!A92,Feuil2!$A$1:$AA$298,10,0) -> SARL | I92: =VLOOKUP('E-impôts'!A92,Feuil2!$A$1:$AA$298,5,0) -> AMEYAO BORIS AUDREY | J92: =VLOOKUP('E-impôts'!A92,Feuil2!$A$1:$AA$298,19,0) -> 708152404 | K92: =VLOOKUP('E-impôts'!A92,Feuil2!$A$1:$AA$298,9,0) -> CI-ABJ-03-2021-B12-00567 | L92: =VLOOKUP('E-impôts'!A92,Feuil2!$A$1:$AA$298,15,0) -> Riviera II | M92: =VLOOKUP('E-impôts'!A92,Feuil2!$A$1:$AA$298,13,0) -> VX | N92: =VLOOKUP('E-impôts'!A92,Feuil2!$A$1:$AA$298,14,0) -> 228 | O92: =VLOOKUP('E-impôts'!A92,Feuil2!$A$1:$AA$298,16,0) -> SCE0106 | P92: =VLOOKUP(A92,Feuil2!$A$1:$AA$298,17,0) -> 1000000
A93: 2023515A | B93: MULTISERVICES | C93: =VLOOKUP('E-impôts'!A93,Feuil2!$A$1:$AA$298,4,0) -> DCK | D93: 45321 | E93: =VLOOKUP('E-impôts'!A93,Feuil2!$A$1:$AA$298,8,0) -> 0 | F93: =VLOOKUP('E-impôts'!A93,Feuil2!$A$1:$AA$298,24,0) -> COCODY II PLATEAUX VALLON | G93: =VLOOKUP('E-impôts'!A93,Feuil2!$A$1:$AA$298,11,0) -> RME | H93: =VLOOKUP('E-impôts'!A93,Feuil2!$A$1:$AA$298,10,0) -> SA | I93: =VLOOKUP('E-impôts'!A93,Feuil2!$A$1:$AA$298,5,0) -> NULL | J93: =VLOOKUP('E-impôts'!A93,Feuil2!$A$1:$AA$298,19,0) -> 757315050 | K93: =VLOOKUP('E-impôts'!A93,Feuil2!$A$1:$AA$298,9,0) -> NULL | L93: =VLOOKUP('E-impôts'!A93,Feuil2!$A$1:$AA$298,15,0) -> II Plateaux II | M93: =VLOOKUP('E-impôts'!A93,Feuil2!$A$1:$AA$298,13,0) -> NULL | N93: =VLOOKUP('E-impôts'!A93,Feuil2!$A$1:$AA$298,14,0) -> NULL | O93: =VLOOKUP('E-impôts'!A93,Feuil2!$A$1:$AA$298,16,0) -> NULL | P93: =VLOOKUP(A93,Feuil2!$A$1:$AA$298,17,0) -> NULL
A94: 2213255G | B94: MOVATEC | C94: =VLOOKUP('E-impôts'!A94,Feuil2!$A$1:$AA$298,4,0) -> KOFFI ALBERT | D94: 44935 | E94: =VLOOKUP('E-impôts'!A94,Feuil2!$A$1:$AA$298,8,0) -> DCK-CGA2023-J001 | F94: =VLOOKUP('E-impôts'!A94,Feuil2!$A$1:$AA$298,24,0) -> BINGERVILLE | G94: =VLOOKUP('E-impôts'!A94,Feuil2!$A$1:$AA$298,11,0) -> TEE | H94: =VLOOKUP('E-impôts'!A94,Feuil2!$A$1:$AA$298,10,0) -> SARL | I94: =VLOOKUP('E-impôts'!A94,Feuil2!$A$1:$AA$298,5,0) -> NULL | J94: =VLOOKUP('E-impôts'!A94,Feuil2!$A$1:$AA$298,19,0) -> 759166503 | K94: =VLOOKUP('E-impôts'!A94,Feuil2!$A$1:$AA$298,9,0) -> NULL | L94: =VLOOKUP('E-impôts'!A94,Feuil2!$A$1:$AA$298,15,0) -> Bingerville | M94: =VLOOKUP('E-impôts'!A94,Feuil2!$A$1:$AA$298,13,0) -> NULL | N94: =VLOOKUP('E-impôts'!A94,Feuil2!$A$1:$AA$298,14,0) -> NULL | O94: =VLOOKUP('E-impôts'!A94,Feuil2!$A$1:$AA$298,16,0) -> NULL | P94: =VLOOKUP(A94,Feuil2!$A$1:$AA$298,17,0) -> NULL
A95: 2213711Z | B95: MOHAMED ZEINI OULD | C95: =VLOOKUP('E-impôts'!A95,Feuil2!$A$1:$AA$298,4,0) -> #N/A | D95: 44614 | E95: =VLOOKUP('E-impôts'!A95,Feuil2!$A$1:$AA$298,8,0) -> #N/A | F95: =VLOOKUP('E-impôts'!A95,Feuil2!$A$1:$AA$298,24,0) -> #N/A | G95: =VLOOKUP('E-impôts'!A95,Feuil2!$A$1:$AA$298,11,0) -> #N/A | H95: =VLOOKUP('E-impôts'!A95,Feuil2!$A$1:$AA$298,10,0) -> #N/A | I95: =VLOOKUP('E-impôts'!A95,Feuil2!$A$1:$AA$298,5,0) -> #N/A | J95: =VLOOKUP('E-impôts'!A95,Feuil2!$A$1:$AA$298,19,0) -> #N/A | K95: =VLOOKUP('E-impôts'!A95,Feuil2!$A$1:$AA$298,9,0) -> #N/A | L95: =VLOOKUP('E-impôts'!A95,Feuil2!$A$1:$AA$298,15,0) -> #N/A | M95: =VLOOKUP('E-impôts'!A95,Feuil2!$A$1:$AA$298,13,0) -> #N/A | N95: =VLOOKUP('E-impôts'!A95,Feuil2!$A$1:$AA$298,14,0) -> #N/A | O95: =VLOOKUP('E-impôts'!A95,Feuil2!$A$1:$AA$298,16,0) -> #N/A | P95: =VLOOKUP(A95,Feuil2!$A$1:$AA$298,17,0) -> #N/A
A96: 1905397V | B96: MOHAMED AMAR MOHAMED LEMIN | C96: =VLOOKUP('E-impôts'!A96,Feuil2!$A$1:$AA$298,4,0) -> #N/A | D96: 43860 | E96: =VLOOKUP('E-impôts'!A96,Feuil2!$A$1:$AA$298,8,0) -> #N/A | F96: =VLOOKUP('E-impôts'!A96,Feuil2!$A$1:$AA$298,24,0) -> #N/A | G96: =VLOOKUP('E-impôts'!A96,Feuil2!$A$1:$AA$298,11,0) -> #N/A | H96: =VLOOKUP('E-impôts'!A96,Feuil2!$A$1:$AA$298,10,0) -> #N/A | I96: =VLOOKUP('E-impôts'!A96,Feuil2!$A$1:$AA$298,5,0) -> #N/A | J96: =VLOOKUP('E-impôts'!A96,Feuil2!$A$1:$AA$298,19,0) -> #N/A | K96: =VLOOKUP('E-impôts'!A96,Feuil2!$A$1:$AA$298,9,0) -> #N/A | L96: =VLOOKUP('E-impôts'!A96,Feuil2!$A$1:$AA$298,15,0) -> #N/A | M96: =VLOOKUP('E-impôts'!A96,Feuil2!$A$1:$AA$298,13,0) -> #N/A | N96: =VLOOKUP('E-impôts'!A96,Feuil2!$A$1:$AA$298,14,0) -> #N/A | O96: =VLOOKUP('E-impôts'!A96,Feuil2!$A$1:$AA$298,16,0) -> #N/A | P96: =VLOOKUP(A96,Feuil2!$A$1:$AA$298,17,0) -> #N/A
A97: 9819464H | B97: MLE MASSEMORY FOFANA (ETS MAFODI) | C97: =VLOOKUP('E-impôts'!A97,Feuil2!$A$1:$AA$298,4,0) -> CABINET CFA | D97: 44222 | E97: =VLOOKUP('E-impôts'!A97,Feuil2!$A$1:$AA$298,8,0) -> DCK-CGA2021-Q137 | F97: =VLOOKUP('E-impôts'!A97,Feuil2!$A$1:$AA$298,24,0) -> ANGRE CAFEIIER | G97: =VLOOKUP('E-impôts'!A97,Feuil2!$A$1:$AA$298,11,0) -> TEE | H97: =VLOOKUP('E-impôts'!A97,Feuil2!$A$1:$AA$298,10,0) -> ENTREPRISE INDIVIDUELLE | I97: =VLOOKUP('E-impôts'!A97,Feuil2!$A$1:$AA$298,5,0) -> NULL | J97: =VLOOKUP('E-impôts'!A97,Feuil2!$A$1:$AA$298,19,0) -> 0 | K97: =VLOOKUP('E-impôts'!A97,Feuil2!$A$1:$AA$298,9,0) -> NULL | L97: =VLOOKUP('E-impôts'!A97,Feuil2!$A$1:$AA$298,15,0) -> II Plateaux II | M97: =VLOOKUP('E-impôts'!A97,Feuil2!$A$1:$AA$298,13,0) -> NULL | N97: =VLOOKUP('E-impôts'!A97,Feuil2!$A$1:$AA$298,14,0) -> NULL | O97: =VLOOKUP('E-impôts'!A97,Feuil2!$A$1:$AA$298,16,0) -> NULL | P97: =VLOOKUP(A97,Feuil2!$A$1:$AA$298,17,0) -> NULL
A98: 2164413N | B98: MIWA ENTREPRISE SARL | C98: =VLOOKUP('E-impôts'!A98,Feuil2!$A$1:$AA$298,4,0) -> #N/A | D98: 44939 | E98: =VLOOKUP('E-impôts'!A98,Feuil2!$A$1:$AA$298,8,0) -> #N/A | F98: =VLOOKUP('E-impôts'!A98,Feuil2!$A$1:$AA$298,24,0) -> #N/A | G98: =VLOOKUP('E-impôts'!A98,Feuil2!$A$1:$AA$298,11,0) -> #N/A | H98: =VLOOKUP('E-impôts'!A98,Feuil2!$A$1:$AA$298,10,0) -> #N/A | I98: =VLOOKUP('E-impôts'!A98,Feuil2!$A$1:$AA$298,5,0) -> #N/A | J98: =VLOOKUP('E-impôts'!A98,Feuil2!$A$1:$AA$298,19,0) -> #N/A | K98: =VLOOKUP('E-impôts'!A98,Feuil2!$A$1:$AA$298,9,0) -> #N/A | L98: =VLOOKUP('E-impôts'!A98,Feuil2!$A$1:$AA$298,15,0) -> #N/A | M98: =VLOOKUP('E-impôts'!A98,Feuil2!$A$1:$AA$298,13,0) -> #N/A | N98: =VLOOKUP('E-impôts'!A98,Feuil2!$A$1:$AA$298,14,0) -> #N/A | O98: =VLOOKUP('E-impôts'!A98,Feuil2!$A$1:$AA$298,16,0) -> #N/A | P98: =VLOOKUP(A98,Feuil2!$A$1:$AA$298,17,0) -> #N/A
A99: 2242477J | B99: MITA PRODUCTION SARL | C99: =VLOOKUP('E-impôts'!A99,Feuil2!$A$1:$AA$298,4,0) -> KOFFI ALBERT | D99: 44760 | E99: =VLOOKUP('E-impôts'!A99,Feuil2!$A$1:$AA$298,8,0) -> DCK-CGA2022-J071 | F99: =VLOOKUP('E-impôts'!A99,Feuil2!$A$1:$AA$298,24,0) -> BINGERVILLE PARIS VILLAGE | G99: =VLOOKUP('E-impôts'!A99,Feuil2!$A$1:$AA$298,11,0) -> TEE | H99: =VLOOKUP('E-impôts'!A99,Feuil2!$A$1:$AA$298,10,0) -> SARL | I99: =VLOOKUP('E-impôts'!A99,Feuil2!$A$1:$AA$298,5,0) -> NULL | J99: =VLOOKUP('E-impôts'!A99,Feuil2!$A$1:$AA$298,19,0) -> 777328417 | K99: =VLOOKUP('E-impôts'!A99,Feuil2!$A$1:$AA$298,9,0) -> NULL | L99: =VLOOKUP('E-impôts'!A99,Feuil2!$A$1:$AA$298,15,0) -> Bingerville | M99: =VLOOKUP('E-impôts'!A99,Feuil2!$A$1:$AA$298,13,0) -> NULL | N99: =VLOOKUP('E-impôts'!A99,Feuil2!$A$1:$AA$298,14,0) -> NULL | O99: =VLOOKUP('E-impôts'!A99,Feuil2!$A$1:$AA$298,16,0) -> NULL | P99: =VLOOKUP(A99,Feuil2!$A$1:$AA$298,17,0) -> NULL
A100: 1732648R | B100: MINES IMPORT-EXPORT | D100: 43844 | I100: =VLOOKUP('E-impôts'!A100,Feuil2!$A$1:$AA$298,5,0) -> #N/A | L100: =VLOOKUP('E-impôts'!A100,Feuil2!$A$1:$AA$298,15,0) -> #N/A
...

Sheet Feuil2
A1: numcc | B1: userid | C1: company | D1: Portefeuilles | E1: identification | F1: fonction | G1: numcga | H1: numadh | I1: numrccm | J1: formjurid | K1: regime | L1: acti_prin | M1: section | N1: parcelle | O1: imp_centre | P1: codeacti | Q1: montcapit | R1: emailetprse | S1: phonenumber | T1: country | U1: city | V1: zip | W1: state | X1: address | Y1: website | Z1: datecreated | AA1: active
A2: 4105181N | B2: 1 | C2: HONDE REINE BELLE | D2: =VLOOKUP('[1]tblclients (1)'!A2,[1]Feuil1!$A$1:$G$203,4,0) -> DCK | E2: NULL | F2: NULL | G2: DCK-001 | H2: DCK-CGA2019-A026 | I2: NULL | J2: ENTREPRISE INDIVIDUELLE | K2: TEE | L2: NULL | M2: NULL | N2: NULL | O2: II Plateaux II | P2: NULL | Q2: NULL | R2: NULL | S2: 707059199 | T2: 54 | U2: Abidjan | V2: NULL | W2: NULL | X2: COCODY II PLATEAUX VALLONS | Y2: NULL | Z2: 43466 | AA2: 1
A3: 1526919K | B3: 2 | C3: GOLY ADJOUA EDITH ESTELLE | D3: =VLOOKUP('[1]tblclients (1)'!A3,[1]Feuil1!$A$1:$G$203,4,0) -> DCK | E3: GOLY ADJOUA EDITH ESTELLE | F3: Exploitante individuelle | G3: DCK-002 | H3: DCK-CGA2019-A013 | I3: CI-ABJ-2015-A-3981 | J3: ENTREPRISE INDIVIDUELLE | K3: TEE | L3: Fourniture de bureau | M3: EV | N3: 541 | O3: II Plateaux III | P3: CCE1501 | R3: N/D | S3: 758840340 | T3: 54 | U3: Abidjan | V3: 09 BP 1976 ABID | W3: N/D | X3: COCODY RIVERA BONOUMIN | Y3: N/D | Z3: 43466 | AA3: 1
A4: 1435907M | B4: 3 | C4: ETTE DJEKET CORINE EPSE AVOAKA | D4: =VLOOKUP('[1]tblclients (1)'!A4,[1]Feuil1!$A$1:$G$203,4,0) -> DCK | E4: NULL | F4: NULL | G4: DCK-003 | H4: DCK-CGA2020-A050 | I4: NULL | J4: ENTREPRISE INDIVIDUELLE | K4: TEE | L4: NULL | M4: NULL | N4: NULL | O4: Cocody | P4: NULL | Q4: NULL | R4: NULL | S4: 707114141 | T4: 54 | U4: Abidjan | V4: NULL | W4: NULL | X4: COCODY BLOCKAUSS | Y4: NULL | Z4: 43471 | AA4: 1
A5: 0323332D | B5: 4 | C5: KONATE Harouna | D5: =VLOOKUP('[1]tblclients (1)'!A5,[1]Feuil1!$A$1:$G$203,4,0) -> DCK | E5: NULL | F5: NULL | G5: DCK-004 | H5: DCK-CGA2019-A039 | I5: NULL | J5: ENTREPRISE INDIVIDUELLE | K5: TEE | L5: NULL | M5: NULL | N5: NULL | O5: Cocody | P5: NULL | Q5: NULL | R5: NULL | S5: 707941178 | T5: 54 | U5: Abidjan | V5: NULL | W5: NULL | X5: COCODY SAINT JEAN | Y5: NULL | Z5: 43479 | AA5: 1
A6: 1507261D | B6: 5 | C6: ZANGRE HAROUNA | D6: =VLOOKUP('[1]tblclients (1)'!A6,[1]Feuil1!$A$1:$G$203,4,0) -> DCK | E6: NULL | F6: NULL | G6: DCK-005 | H6: DCK-CGA2019-A024 | I6: NULL | J6: ENTREPRISE INDIVIDUELLE | K6: TEE | L6: NULL | M6: NULL | N6: NULL | O6: Cocody | P6: NULL | Q6: NULL | R6: NULL | S6: 505843545 | T6: 54 | U6: Abidjan | V6: NULL | W6: NULL | X6: COCODY SAINT JEAN | Y6: NULL | Z6: 43479 | AA6: 1
A7: 1414480Q | B7: 6 | C7: OUEDRAOGO YOUSSOUF | D7: =VLOOKUP('[1]tblclients (1)'!A7,[1]Feuil1!$A$1:$G$203,4,0) -> DCK | E7: NULL | F7: NULL | G7: DCK-006 | H7: DCK-CGA2019-A023 | I7: NULL | J7: ENTREPRISE INDIVIDUELLE | K7: TEE | L7: NULL | M7: NULL | N7: NULL | O7: Cocody | P7: NULL | Q7: NULL | R7: NULL | S7: 707582591 | T7: 54 | U7: Abidjan | V7: NULL | W7: NULL | X7: COCODY SAINT JEAN | Y7: NULL | Z7: 43479 | AA7: 1
A8: 1827528R | B8: 7 | C8: YAGUERA & COMPAGNIE | D8: =VLOOKUP('[1]tblclients (1)'!A8,[1]Feuil1!$A$1:$G$203,4,0) -> DCK | E8: NULL | F8: NULL | G8: DCK-007 | H8: DCK-CGA2019-A007 | I8: NULL | J8: SARL | K8: TEE | L8: NULL | M8: NULL | N8: NULL | O8: II Plateaux I | P8: NULL | Q8: NULL | R8: NULL | S8: 789844008 | T8: 54 | U8: Abidjan | V8: NULL | W8: NULL | X8: COCODY ANGRE 7E TRANCHE | Y8: NULL | Z8: 43479 | AA8: 1
A9: 1619903H | B9: 8 | C9: NEDJMA SARLU | D9: =VLOOKUP('[1]tblclients (1)'!A9,[1]Feuil1!$A$1:$G$203,4,0) -> DCK | E9: NULL | F9: NULL | G9: DCK-008 | H9: DCK-CGA2019-A029 | I9: NULL | J9: SARL | K9: TEE | L9: NULL | M9: NULL | N9: NULL | O9: II Plateaux I | P9: NULL | Q9: NULL | R9: NULL | S9: 707070102 | T9: 54 | U9: Abidjan | V9: NULL | W9: NULL | X9: COCODY RIVIERA BONOUMIN | Y9: NULL | Z9: 43479 | AA9: 1
A10: 1530324W | B10: 9 | C10: CONCEPT IMAGE | D10: =VLOOKUP('[1]tblclients (1)'!A10,[1]Feuil1!$A$1:$G$203,4,0) -> DCK | G10: DCK-009 | H10: DCK-CGA2019-B036 | J10: SARL | K10: RME | O10: II Plateaux II | S10: 101017474 | T10: 54 | U10: Abidjan | X10: COCODY II PLATAUX SIDECI | Z10: 43479 | AA10: 1
A11: 0735268S | B11: 10 | C11: COFFI MARIE COLETTE | D11: =VLOOKUP('[1]tblclients (1)'!A11,[1]Feuil1!$A$1:$G$203,4,0) -> DCK | E11: NULL | F11: NULL | G11: DCK-010 | H11: DCK-CGA2019-A022 | I11: NULL | J11: ENTREPRISE INDIVIDUELLE | K11: TEE | L11: NULL | M11: NULL | N11: NULL | O11: II Plateaux II | P11: NULL | Q11: NULL | R11: NULL | S11: 707435252 | T11: 54 | U11: Abidjan | V11: NULL | W11: NULL | X11: COCODY VALLON | Y11: NULL | Z11: 43479 | AA11: 1
A12: 9410895U | B12: 11 | C12: YERE LOU EPSE YACE NENENAN BLANCHE | D12: =VLOOKUP('[1]tblclients (1)'!A12,[1]Feuil1!$A$1:$G$203,4,0) -> DCK | E12: NULL | F12: NULL | G12: DCK-011 | H12: DCK-CGA2019-A040 | I12: NULL | J12: ENTREPRISE INDIVIDUELLE | K12: TEE | L12: NULL | M12: NULL | N12: NULL | O12: II Plateaux II | P12: NULL | Q12: NULL | R12: NULL | S12: 707070392 | T12: 54 | U12: Abidjan | V12: NULL | W12: NULL | X12: COCODY II PLATEAUX VALLON | Y12: NULL | Z12: 43479 | AA12: 1
A13: 1307492V | B13: 12 | C13: N'GUESSAN ATTIEGOUA ANNE ELLA | D13: =VLOOKUP('[1]tblclients (1)'!A13,[1]Feuil1!$A$1:$G$203,4,0) -> DCK | E13: NULL | F13: NULL | G13: DCK-012 | H13: DCK-CGA2019-A010 | I13: NULL | J13: ENTREPRISE INDIVIDUELLE | K13: TEE | L13: NULL | M13: NULL | N13: NULL | O13: II Plateaux II | P13: NULL | Q13: NULL | R13: NULL | S13: 708048295 | T13: 54 | U13: Abidjan | V13: NULL | W13: NULL | X13: II PLATEUX VALLON | Y13: NULL | Z13: 43479 | AA13: 1
A14: 1220791C | B14: 13 | C14: KOUAME KONAN FIRMIN | D14: =VLOOKUP('[1]tblclients (1)'!A14,[1]Feuil1!$A$1:$G$203,4,0) -> DCK | E14: KOUAME KONAN FIRMIN | F14: Exploitant individuel | G14: DCK-013 | H14: DCK-CGA2019-A016 | I14: N/D | J14: ENTREPRISE INDIVIDUELLE | K14: TEE | L14: TRAVAUX DE TELECOM
A15: 1321944W | B15: 14 | C15: KIMOU ERIC HERVE | D15: =VLOOKUP('[1]tblclients (1)'!A15,[1]Feuil1!$A$1:$G$203,4,0) -> DCK | E15: KIMOU ERIC | F15: Exploitant individuel | G15: DCK-014 | H15: DCK-CGA2019-A019 | J15: ENTREPRISE INDIVIDUELLE | K15: TEE | S15: 101800240 | T15: 54 | U15: Abidjan | X15: COCODY RIVIERA BONOUMIN | Z15: 43479 | AA15: 1
A16: 0709432N | B16: 15 | C16: YIRA SIAKA | D16: =VLOOKUP('[1]tblclients (1)'!A16,[1]Feuil1!$A$1:$G$203,4,0) -> DCK | E16: YIRA SIAKA | F16: PROPRIETAIRE | G16: DCK-015 | H16: DCK-CGA2019-A005 | I16: 09 BP 2525 ABIDJAN 09 | J16: ENTREPRISE INDIVIDUELLE | K16: TEE | L16: Transport et prestation de services | M16: N/D | N16: N/D | O16: II Plateaux III | P16: SCE2103 | Q16: 6000000 | R16: N/D | S16: 757740598 | T16: 54 | U16: Abidjan | V16: 225 | W16: N/D | X16: COCODY RIVIERA BONOUMIN | Z16: 43479 | AA16: 1
A17: 0514603E | B17: 16 | C17: ZALLE MAHAMOUD | D17: =VLOOKUP('[1]tblclients (1)'!A17,[1]Feuil1!$A$1:$G$203,4,0) -> DCK | E17: ZALLE MAHAMOUD | F17: Exploitant Individuel | G17: DCK-016 | H17: DCK-CGA2019-A025 | I17: CI-ABJ-2011-A-6598 | J17: ENTREPRISE INDIVIDUELLE | K17: TEE | L17: QUINCAILLERIE | M17: N/D | N17: N/D | O17: II Plateaux Djibi | P17: N/D | R17: N/D | S17: 505938989 | T17: 54 | U17: Abidjan | V17: N/D | W17: N/D | X17: COCODY ANGRE-DJIBI | Y17: N/D | Z17: 43479 | AA17: 1
A18: 1526973R | B18: 17 | C18: CENTRE D'EDUCATION ROUTIERE EN COTE D'IVOIRE | D18: =VLOOKUP('[1]tblclients (1)'!A18,[1]Feuil1!$A$1:$G$203,4,0) -> DCK | E18: NULL | F18: NULL | G18: DCK-017 | H18: DCK-CGA2019-B031 | I18: NULL | J18: SARL | K18: RME | L18: NULL | M18: NULL | N18: NULL | O18: Riviera I | P18: NULL | Q18: NULL | R18: NULL | S18: 757893651 | T18: 54 | U18: Abidjan | V18: NULL | W18: NULL | X18: RIVIERA LES JARDINS | Y18: NULL | Z18: 43479 | AA18: 1
A19: 1019140H | B19: 18 | C19: CISSE MOUSSA | D19: =VLOOKUP('[1]tblclients (1)'!A19,[1]Feuil1!$A$1:$G$203,4,0) -> DCK | E19: NULL | F19: NULL | G19: DCK-018 | H19: DCK-CGA2019-A001 | I19: NULL | J19: ENTREPRISE INDIVIDUELLE | K19: TEE | L19: NULL | M19: NULL | N19: NULL | O19: Riviera II | P19: NULL | Q19: NULL | R19: NULL | S19: 505050371 | T19: 54 | U19: Abidjan | V19: NULL | W19: NULL | X19: COCODY RIVIERA FAYA | Y19: NULL | Z19: 43479 | AA19: 1
A20: 1220743K | B20: 19 | C20: CISSE MOHMED SANASSY | D20: =VLOOKUP('[1]tblclients (1)'!A20,[1]Feuil1!$A$1:$G$203,4,0) -> DCK | E20: NULL | F20: NULL | G20: DCK-019 | H20: DCK-CGA2019-A028 | I20: NULL | J20: ENTREPRISE INDIVIDUELLE | K20: TEE | L20: NULL | M20: NULL | N20: NULL | O20: Riviera II | P20: NULL | Q20: NULL | R20: NULL | S20: 779941955 | T20: 54 | U20: Abidjan | V20: NULL | W20: NULL | X20: COCODY RIVIERA PALMERAIE | Y20: NULL | Z20: 43479 | AA20: 1
A21: 1807923J | B21: 20 | C21: EKYM SARL | D21: =VLOOKUP('[1]tblclients (1)'!A21,[1]Feuil1!$A$1:$G$203,4,0) -> DCK | E21: KOUADIO AHOU MICHAELLE | F21: GÃ©rante | G21: DCK-020 | H21: DCK-CGA2019-A006 | I21: CI-ABJ-2018-B-04208 | J21: SARL | K21: TEE | L21: Fournitures de bureaux, Restauration, BÃ¢timent | M21: EV | N21: 222 | O21: II Plateaux III | P21: SCE0203 | Q21: 1000000 | R21: N/D | S21: 102377494 | T21: 54 | U21: Abidjan | V21: 22 BP 799 ABIDJ | W21: N/D | X21: COCODY II PLATEAUX ANGRE | Y21: N/D | Z21: 43479 | AA21: 1
A22: 1648392M | B22: 21 | C22: KOUAME FIENI MYRIAME-CHRISTELLE | D22: =VLOOKUP('[1]tblclients (1)'!A22,[1]Feuil1!$A$1:$G$203,4,0) -> DCK | E22: NULL | F22: NULL | G22: DCK-021 | H22: DCK-CGA2019-A005 | I22: NULL | J22: ENTREPRISE INDIVIDUELLE | K22: TEE | L22: NULL | M22: NULL | N22: NULL | O22: Cocody | P22: NULL | Q22: NULL | R22: NULL | S22: 707063365 | T22: 54 | U22: Abidjan | V22: NULL | W22: NULL | X22: COCODY RIVIERA BONOUMIN | Y22: NULL | Z22: 43522 | AA22: 1
A23: 1212885P | B23: 22 | C23: YAO N'GUESSAN ADELE EPSE DJEDJE | D23: =VLOOKUP('[1]tblclients (1)'!A23,[1]Feuil1!$A$1:$G$203,4,0) -> DCK | E23: YOA N'GUESSAN ADELE EPSE DJEDJE | F23: Exploitante Individuelle | G23: DCK-022 | H23: DCK-CGA2019-A027 | I23: CI-ABJ-2012-A-1024 | J23: ENTREPRISE INDIVIDUELLE | K23: TEE | L23: ALIMENTATION GENERALE ET TRANSFERT D'ARGENT | M23: ABC | N23: 39 | O23: II Plateaux III | P23: SCE0101 | R23: N/D | S23: 505060740 | T23: 54 | U23: Abidjan | W23: N/D | X23: RIVIERA BONOUMIN | Y23: N/D | Z23: 43844 | AA23: 1
A24: 0714977C | B24: 23 | C24: YACE EMMANUELLE | D24: =VLOOKUP('[1]tblclients (1)'!A24,[1]Feuil1!$A$1:$G$203,4,0) -> DCK | E24: YACE EMMANUELLE | F24: Exploitante individuelle | G24: DCK-023 | H24: DCK-CGA2019-A014 | I24: CI-ABJ-2014-A-1249 | J24: ENTREPRISE INDIVIDUELLE | K24: TEE | L24: LOCATION DE SALLE ET TRAITEUR | M24: OZ | N24: 207 | O24: II Plateaux III | P24: SCE0708 | R24: N/D | S24: 707070392 | T24: 54 | U24: Abidjan | W24: N/D | X24: COCODY ANGRE 7E TRANCHE | Z24: 43844 | AA24: 1
A25: 1800364M | B25: 24 | C25: YAKIM DESIGN | D25: =VLOOKUP('[1]tblclients (1)'!A25,[1]Feuil1!$A$1:$G$203,4,0) -> DCK | E25: NULL | F25: NULL | G25: DCK-024 | H25: DCK-CGA2020-A104 | I25: NULL | J25: SARL | K25: TEE | L25: NULL | M25: NULL | N25: NULL | O25: II Plateaux I | P25: NULL | Q25: NULL | R25: NULL | S25: 2722413235 | T25: 54 | U25: Abidjan | V25: NULL | W25: NULL | X25: II PLATEAUX LES PERLES | Y25: NULL | Z25: 43845 | AA25: 1
A26: 1900445C | B26: 25 | C26: YAO N'DRI FRANCK AIME | D26: =VLOOKUP('[1]tblclients (1)'!A26,[1]Feuil1!$A$1:$G$203,4,0) -> DCK | E26: YAO N'DRI FRANCK AIME | F26: Exploitant Individuel | G26: DCK-025 | H26: DCK-CGA2020-A051 | J26: ENTREPRISE INDIVIDUELLE | K26: TEE | L26: PRESTATIONS MEDICALE | M26: ABH | N26: 10 | O26: II Plateaux III | P26: SCE1601 | R26: N/D | S26: 708112943 | T26: 54 | U26: Abidjan | W26: N/D | X26: COCODY BONOUMIN | Z26: 43847 | AA26: 1
A27: 1745011T | B27: 26 | C27: POHAN KEMOANFOUOGNON AUGUSTE | D27: =VLOOKUP('[1]tblclients (1)'!A27,[1]Feuil1!$A$1:$G$203,4,0) -> DCK | E27: POHAN KEMOANFOUOGON AUGUTE | F27: Exploitant individuel | G27: DCK-026 | H27: DCK-CGA2020-A088 | I27: CI-ABJ-2017-A-25544 | J27: ENTREPRISE INDIVIDUELLE | K27: TEE | L27: ASSISTANCE VOYAGE ET ETUDES, FORMATION, DIVERS | M27: AO | N27: 527 | O27: II Plateaux III | P27: SCE2399 | R27: N/D | S27: 778972145 | T27: 54 | U27: Abidjan | W27: N/D | X27: COCODY | Y27: N/D | Z27: 43858 | AA27: 1
A28: 2042595N | B28: 27 | C28: CNK INTERNATIONAL GROUP SARL | D28: =VLOOKUP('[1]tblclients (1)'!A28,[1]Feuil1!$A$1:$G$203,4,0) -> DCK | E28: NULL | F28: NULL | G28: DCK-027 | H28: DCK-CGA2020-A-111 | I28: NULL | J28: SARL | K28: TEE | L28: NULL | M28: NULL | N28: NULL | O28: Riviera I | P28: NULL | Q28: NULL | R28: NULL | S28: 779190538 | T28: 54 | U28: Abidjan | V28: NULL | W28: NULL | X28: COCODY RIVERA II CITE ESTUDIANTINE | Y28: NULL | Z28: 44111 | AA28: 1
A29: 1006441X | B29: 28 | C29: ETUDE DE MAITRE DIDIER DOUGOUE | D29: =VLOOKUP('[1]tblclients (1)'!A29,[1]Feuil1!$A$1:$G$203,4,0) -> DCK | E29: NULL | F29: NULL | G29: DCK-028 | H29: DCK-CGA2019-A120 | I29: NULL | J29: ENTREPRISE INDIVIDUELLE | K29: TEE | L29: NULL | M29: NULL | N29: NULL | O29: II Plateaux I | P29: NULL | Q29: NULL | R29: NULL | S29: 2722527459 | T29: 54 | U29: Abidjan | V29: NULL | W29: NULL | X29: COCODY ANGRE LES OSCARS | Y29: NULL | Z29: 44197 | AA29: 1
A30: 1351303J | B30: 29 | C30: NEYD DISTRIBUTION | D30: =VLOOKUP('[1]tblclients (1)'!A30,[1]Feuil1!$A$1:$G$203,4,0) -> DCK | E30: NULL | F30: NULL | G30: DCK-029 | H30: DCK-CGA2019-A118 | I30: NULL | J30: ENTREPRISE INDIVIDUELLE | K30: TEE | L30: NULL | M30: NULL | N30: NULL | O30: II Plateaux II | P30: NULL | Q30: NULL | R30: NULL | S30: 708302596 | T30: 54 | U30: Abidjan | V30: NULL | W30: NULL | X30: ANGRE 8E TRANCHE | Y30: NULL | Z30: 44197 | AA30: 1
A31: 0317890C | B31: 30 | C31: SCPA TAKORE, KONAN & ASSOCIES | D31: =VLOOKUP('[1]tblclients (1)'!A31,[1]Feuil1!$A$1:$G$203,4,0) -> DCK | E31: NULL | F31: NULL | G31: DCK-030 | H31: DCK-CGA2019-A119 | I31: NULL | J31: SOCIÃ‰TÃ‰ CIVILE | K31: TEE | L31: NULL | M31: NULL | N31: NULL | O31: II Plateaux II | P31: NULL | Q31: NULL | R31: NULL | S31: 2522014025 | T31: 54 | U31: Abidjan | V31: NULL | W31: NULL | X31: II PLATEAUX VALLON | Y31: NULL | Z31: 44197 | AA31: 1
A32: 1940880C | B32: 31 | C32: BOHIYA SERVICES SARL | D32: =VLOOKUP('[1]tblclients (1)'!A32,[1]Feuil1!$A$1:$G$203,4,0) -> DCK | E32: DANHI HENRY DELPHIN | F32: Co-gÃ©rant | G32: DCK-031 | H32: DCK-CGA2019-A117 | I32: CI-ABJ-2019-B-14607 | J32: SARL | K32: TEE | L32: VENTE DE TITRE DE TRANSPORT AERIEN ET TERRESTRE,MONETIQUE ET TRANSFERT D4ARGENT RAPIDE NATIONAUX ET INTERNATIONAUX | M32: OZ | N32: 281 | O32: II Plateaux III | P32: SCE0313 | Q32: 1000000 | R32: N/D | S32: 2722594787 | T32: 54 | U32: Abidjan | W32: BS SARL | X32: COCODY ANGRE 7E TRANCHE | Y32: N/D | Z32: 44197 | AA32: 1
A33: 2035080J | B33: 32 | C33: DEBOLYINSTRUMENTS SARL | D33: =VLOOKUP('[1]tblclients (1)'!A33,[1]Feuil1!$A$1:$G$203,4,0) -> DCK | E33: NULL | F33: NULL | G33: DCK-032 | H33: DCK-CGA2020-A115 | I33: NULL | J33: SARL | K33: TEE | L33: NULL | M33: NULL | N33: NULL | O33: Riviera I | P33: NULL | Q33: NULL | R33: NULL | S33: 707053694 | T33: 54 | U33: Abidjan | V33: NULL | W33: NULL | X33: RIVIERA 3 MOSQUEE | Y33: NULL | Z33: 44197 | AA33: 1
A34: 1224798B | B34: 33 | C34: KADIO-MOROKRO MAUD AICHA (FOR MEN) | D34: =VLOOKUP('[1]tblclients (1)'!A34,[1]Feuil1!$A$1:$G$203,4,0) -> DCK | E34: NULL | F34: NULL | G34: DCK-033 | H34: DCK-CGA-2021-Q154 | I34: NULL | J34: ENTREPRISE INDIVIDUELLE | K34: TEE | L34: NULL | M34: NULL | N34: NULL | O34: II Plateaux II | P34: NULL | Q34: NULL | R34: NULL | S34: 749820808 | T34: 54 | U34: Abidjan | V34: NULL | W34: NULL | X34: COCODY II PLATEAUX VALLON | Y34: NULL | Z34: 44224 | AA34: 1
A35: 1927845K | B35: 34 | C35: PHILIPPE INES GROUP | D35: =VLOOKUP('[1]tblclients (1)'!A35,[1]Feuil1!$A$1:$G$203,4,0) -> DCK | E35: NULL | F35: NULL | G35: DCK-034 | H35: DCK-CGA-2021-Q174 | I35: NULL | J35: SARL | K35: TEE | L35: NULL | M35: NULL | N35: NULL | O35: II Plateaux II | P35: NULL | Q35: NULL | R35: NULL | S35: 77767968 | T35: 54 | U35: Abidjan | V35: NULL | W35: NULL | X35: II PLATEAUX | Y35: NULL | Z35: 44224 | AA35: 1
A36: 1947542X | B36: 35 | C36: OREMUS SARLU | D36: =VLOOKUP('[1]tblclients (1)'!A36,[1]Feuil1!$A$1:$G$203,4,0) -> DCK | E36: YEBOUE EPSE BOUAH ADJOUA IRENE | F36: GÃ©rante | G36: DCK-035 | H36: DCK-CGA2024-A050 | I36: CI-ABJ-2019-B-17445 | J36: SARL | K36: TEE | L36: LOCATIONS MATERIELS ,EVEMENTIELS,LOCATION VEHICULE | M36: N/D | N36: N/D | O36: II Pateaux II | P36: SCC0701 | Q36: 5000000 | R36: N/D | S36: 707830824 | T36: 54 | U36: Abidjan | V36: 08 BP 21115 ABI | W36: N/D | X36: COCODY II PLATEAUX VALLON | Y36: N/D | Z36: 44224 | AA36: 1
A37: 2110646D | B37: 36 | C37: IVOIR QUALITE ET SERVICES | D37: =VLOOKUP('[1]tblclients (1)'!A37,[1]Feuil1!$A$1:$G$203,4,0) -> DCK | E37: NULL | F37: NULL | G37: DCK-036 | H37: DCK-CGA-2021-Q172 | I37: NULL | J37: SARL | K37: RME | L37: NULL | M37: NULL | N37: NULL | O37: II Plateaux I | P37: NULL | Q37: NULL | R37: NULL | S37: 2722427504 | T37: 54 | U37: Abidjan | V37: NULL | W37: NULL | X37: COCODY-ANGRÃ‰-CITÃ‰ BEL HORIZON | Y37: NULL | Z37: 44264 | AA37: 1
A38: 2196217J | B38: 37 | C38: SANTE & SECURITE AU TRAVAIL | D38: =VLOOKUP('[1]tblclients (1)'!A38,[1]Feuil1!$A$1:$G$203,4,0) -> DCK | E38: NULL | F38: NULL | G38: DCK-037 | H38: DCK-CGA-2022-J002 | I38: NULL | J38: SARL | K38: TEE | L38: NULL | M38: NULL | N38: NULL | O38: Riviera I | P38: NULL | Q38: NULL | R38: NULL | S38: 566284952 | T38: 54 | U38: Abidjan | V38: NULL | W38: NULL | X38: COCODY RIVIERA GOLF ANONO | Y38: NULL | Z38: 44564 | AA38: 1
A39: 1865233X | B39: 38 | C39: YAPO YAPO GHISLAIN CYRILLE | D39: =VLOOKUP('[1]tblclients (1)'!A39,[1]Feuil1!$A$1:$G$203,4,0) -> DCK | E39: NULL | F39: NULL | G39: DCK-038 | H39: DCK-CGA-2022-J004 | I39: NULL | J39: ENTREPRISE INDIVIDUELLE | K39: TEE | L39: NULL | M39: NULL | N39: NULL | O39: Riviera I | P39: NULL | Q39: NULL | R39: NULL | S39: 778120796 | T39: 54 | U39: Abidjan | V39: NULL | W39: NULL | X39: COCODY RIVIERA II | Y39: NULL | Z39: 44574 | AA39: 1
A40: 2114065J | B40: 39 | C40: POSY SECURITY AND SERVICES | D40: =VLOOKUP('[1]tblclients (1)'!A40,[1]Feuil1!$A$1:$G$203,4,0) -> DCK | E40: NULL | F40: NULL | G40: DCK-039 | H40: DCK-CGA-2022-J011 | I40: NULL | J40: SARL | K40: TEE | L40: NULL | M40: NULL | N40: NULL | O40: II Plateaux I | P40: NULL | Q40: NULL | R40: NULL | S40: 103041792 | T40: 54 | U40: Abidjan | V40: NULL | W40: NULL | X40: COCODY ANGRE | Y40: NULL | Z40: 44588 | AA40: 1
A41: 2224403Z | B41: 40 | C41: MIGHTY SPIRIT GROUP | D41: =VLOOKUP('[1]tblclients (1)'!A41,[1]Feuil1!$A$1:$G$203,4,0) -> DCK | E41: NULL | F41: NULL | G41: DCK-040 | H41: DCK-CGA-2022-J055 | I41: NULL | J41: SARL | K41: TEE | L41: NULL | M41: NULL | N41: NULL | O41: Riviera II | P41: NULL | Q41: NULL | R41: NULL | S41: 707102042 | T41: 54 | U41: Abidjan | V41: NULL | W41: NULL | X41: COCODY RIVERA FAYA | Y41: NULL | Z41: 44628 | AA41: 1
A42: 1643628L | B42: 41 | C42: GAYE ABO ALBARETTE JOSEE | D42: =VLOOKUP('[1]tblclients (1)'!A42,[1]Feuil1!$A$1:$G$203,4,0) -> DCK | E42: NULL | F42: NULL | G42: DCK-041 | H42: DCK-CGA-2022-J063 | I42: NULL | J42: ENTREPRISE INDIVIDUELLE | K42: TEE | L42: NULL | M42: NULL | N42: NULL | O42: II Plateaux I | P42: NULL | Q42: NULL | R42: NULL | S42: 757284028 | T42: 54 | U42: Abidjan | V42: NULL | W42: NULL | X42: COCODY II PLATEAUX 8E TRANCHE | Y42: NULL | Z42: 44680 | AA42: 1
A43: 2227520U | B43: 42 | C43: CKK SERVICES & LOGISTICS | D43: =VLOOKUP('[1]tblclients (1)'!A43,[1]Feuil1!$A$1:$G$203,4,0) -> DCK | E43: NULL | F43: NULL | G43: DCK-042 | H43: DCK-CGA-2022-J065 | I43: NULL | J43: SARL | K43: TEE | L43: NULL | M43: NULL | N43: NULL | O43: II Plateaux I | P43: NULL | Q43: NULL | R43: NULL | S43: 707578383 | T43: 54 | U43: Abidjan | V43: NULL | W43: NULL | X43: COCODY ANGRE 8E TRANCHE | Y43: NULL | Z43: 44680 | AA43: 1
A44: 1728145D | B44: 43 | C44: KHORA SARL | D44: =VLOOKUP('[1]tblclients (1)'!A44,[1]Feuil1!$A$1:$G$203,4,0) -> DCK | E44: NULL | F44: NULL | G44: DCK-043 | H44: DCK-CGA-2023-J003 | I44: NULL | J44: SARL | K44: TEE | L44: NULL | M44: NULL | N44: NULL | O44: II Plateaux II | P44: NULL | Q44: NULL | R44: NULL | S44: 707262649 | T44: 54 | U44: Abidjan | V44: NULL | W44: NULL | X44: COCODY II PLATEAUX | Y44: NULL | Z44: 44939 | AA44: 1
A45: 2164509F | B45: 44 | C45: LEADER WORLD PERFECT | D45: =VLOOKUP('[1]tblclients (1)'!A45,[1]Feuil1!$A$1:$G$203,4,0) -> DCK | E45: Mme SANFO | F45: GÃ©rante | G45: DCK-044 | H45: DCK-CGA-2022-J012 | I45: CI-ABJ-2021-03729 | J45: SARL | K45: TEE | L45: COMMERCE GENERALE-INFORMATIQUE | M45: SZ | N45: 71 | O45: II Plateaux III | P45: CCE1402 | Q45: 1000000 | R45: N/D | S45: 747994794 | T45: 54 | U45: Abidjan | V45: 06 BP 2346 ABID | W45: LWP | X45: COCODY ATTOBAN | Y45: N/D | Z45: 44952 | AA45: 1
A46: 1821484C | B46: 45 | C46: COM & CONFORT SARL | D46: =VLOOKUP('[1]tblclients (1)'!A46,[1]Feuil1!$A$1:$G$203,4,0) -> DCK | E46: GOSSE ANGE SAINT CLAIR | F46: GÃ©rant | G46: DCK-045 | H46: DCK-CGA-2022-J013 | I46: CI-ABJ-2018-B-10503 | J46: SARL | K46: TEE | L46: CABINET CONSEIL EN COMMUNICATION-IMPRESSION-PUBLICITE | M46: AO | N46: 527 | O46: II Plateaux III | P46: IND1504 | Q46: 1000000 | R46: N/D | S46: 709310771 | T46: 54 | U46: Abidjan | V46: BP 330 BINGERVI | W46: N/D | X46: COCODY RIVIERA | Y46: N/D | Z46: 44952 | AA46: 1
A47: 2244195W | B47: 46 | C47: PRESTIGE INNOV SARLU | D47: =VLOOKUP('[1]tblclients (1)'!A47,[1]Feuil1!$A$1:$G$203,4,0) -> DCK | E47: BARRY FACINET | F47: GERANT | G47: DCK-046 | H47: DCK-CGA-2023-J019 | I47: CI-ABJ-03-2022-B13-09162 | J47: SARL | K47: TEE | L47: SOLUTION-INFORMATIQUE-CONSULTING | M47: ES | N47: 73 | O47: II Plateaux III | P47: SCE0801 | Q47: 1000000 | R47: N/D | S47: 709310771 | T47: 54 | U47: Abidjan | V47: 12 BP 1661 ABID | W47: N/D | X47: COCODY RIVIERA 3 | Y47: N/D | Z47: 44953 | AA47: 1
A48: 2136391L | B48: 47 | C48: PERFORM WAVE CONSULTING | D48: =VLOOKUP('[1]tblclients (1)'!A48,[1]Feuil1!$A$1:$G$203,4,0) -> DCK | E48: FONTAINE JULIEN | F48: GÃ©rant | G48: DCK-047 | H48: DCK-CGA-2023-J021 | I48: CI-ABJ-03-2021-B12-02105 | J48: SARL | K48: TEE | L48: TIC, DEVELOPPEMENT INFORMATIQUE | M48: OZ | N48: N/D | O48: II Plateaux III | P48: SCE0804 | Q48: 700000 | R48: N/D | S48: 797923730 | T48: 54 | U48: Abidjan | V48: 28 BP 1676 ABID | W48: N/D | X48: COCODY II PLATEAUX 7E TRANCHE | Y48: N/D | Z48: 44953 | AA48: 1
A49: 2241768C | B49: 48 | C49: J&K CONSULTING SARLU | D49: =VLOOKUP('[1]tblclients (1)'!A49,[1]Feuil1!$A$1:$G$203,4,0) -> DCK | E49: DJOGBENOU JEAN NOEL | F49: GÃ©rant | G49: DCK-048 | H49: DCK-CGA-2022-J030 | I49: CI-ABJ-03-2022-B12-02388 | J49: SARL | K49: TEE | L49: FORAMATION-CONSEIL-ETUDE | M49: AO | N49: 527 | O49: II Plateaux III | P49: SCE0802 | Q49: 10000000 | R49: N/D | S49: 708414136 | T49: 54 | U49: Abidjan | V49: 09 BP 290 ABIDJ | W49: N/D | X49: COCODY RIVIERA 3 BONOUMIN | Y49: N/D | Z49: 44956 | AA49: 1
A50: 2243769Z | B50: 49 | C50: VIDAS GROUP HOLDING | D50: =VLOOKUP('[1]tblclients (1)'!A50,[1]Feuil1!$A$1:$G$203,4,0) -> DCK | E50: DJOGBENOU | F50: JEAN NOEL | G50: DCK-049 | H50: DCK-CGA-2022-J031 | I50: CI-ABJ-03-B17-00080 | J50: SARL | K50: TEE | L50: FORMATION-CONSEIL-ETUDE-VENTE | M50: AO | N50: 13 | O50: II Plateaux III | P50: SCE1504 | Q50: 10000000 | R50: N/D | S50: 708414136 | T50: 54 | U50: Abidjan | V50: 09 BP 290 ABIDJ | W50: N/D | X50: COCODY BONOUMIN | Y50: N/D | Z50: 44956 | AA50: 1
A51: 2243064N | B51: 50 | C51: BIOFOSSE GROUP SARL | D51: =VLOOKUP('[1]tblclients (1)'!A51,[1]Feuil1!$A$1:$G$203,4,0) -> DCK | E51: NULL | F51: NULL | G51: DCK-050 | H51: DCK-CGA2023-J032 | I51: NULL | J51: SARL | K51: TEE | L51: NULL | M51: NULL | N51: NULL | O51: Cocody | P51: NULL | Q51: NULL | R51: NULL | S51: 767787637 | T51: 54 | U51: Abidjan | V51: NULL | W51: NULL | X51: COCODY MERMOZ | Y51: NULL | Z51: 44957 | AA51: 1
A52: 2023515A | B52: 51 | C52: MULSERVICES SA | D52: =VLOOKUP('[1]tblclients (1)'!A52,[1]Feuil1!$A$1:$G$203,4,0) -> DCK | E52: NULL | F52: NULL | G52: DCK-051 | I52: NULL | J52: SA | K52: RME | L52: NULL | M52: NULL | N52: NULL | O52: II Plateaux II | P52: NULL | Q52: NULL | R52: NULL | S52: 757315050 | T52: 54 | U52: Abidjan | V52: NULL | W52: NULL | X52: COCODY II PLATEAUX VALLON | Y52: NULL | Z52: 0000-00-00 | AA52: 1
A53: 1809549M | B53: 52 | C53: MABARA SERVICES | D53: =VLOOKUP('[1]tblclients (1)'!A53,[1]Feuil1!$A$1:$G$203,4,0) -> DCK | E53: DOUMBIA MASSANKE | F53: GÃ©rante | G53: DCK-052 | H53: DCK-CGA2019-A008 | I53: CI-ABJ-2018-B-04500 | J53: SARL | K53: TEE | L53: Alimentation, fournitures techniques | M53: MN | N53: 300 | O53: II Plateaux Djibi | P53: CCE0101 | Q53: 1000000 | R53: N/D | S53: 708762020 | T53: 54 | U53: Abidjan | V53: 11 BP 2710 ABID | W53: N/D | X53: ANGRE BESSIKOI | Y53: N/D | Z53: 43479 | AA53: 1
A54: 1342660S | B54: 53 | C54: HAMDOUN HASSAN | D54: =VLOOKUP('[1]tblclients (1)'!A54,[1]Feuil1!$A$1:$G$203,4,0) -> DCK | E54: HAMDOUN HASSAN | F54: Exploitant individuel | G54: DCK-053 | H54: DCK-CGA2021-Q182 | I54: CI-ABJ-2015-A-8889 | J54: ENTREPRISE INDIVIDUELLE | K54: TEE | L54: LABO PHOTO | M54: HL | N54: 850 | O54: II Plateaux Djibi | P54: ART0403 | R54: N/D | S54: 565009518 | T54: 54 | U54: Abidjan | V54: N/D | W54: N/D | X54: ANGRE 8E TRANCHE MANDELA | Z54: 44224 | AA54: 1
A55: 9207146M | B55: 54 | C55: DOCTEUR DIOULO MATHURIN | D55: =VLOOKUP('[1]tblclients (1)'!A55,[1]Feuil1!$A$1:$G$203,4,0) -> DCK | E55: DOCTEUR DIOULO MATHURIN | F55: Exploitant individuel | G55: DCK-054 | H55: DCK-CGA2021-Q173 | I55: CI-ABJ-1992-A-165699 | J55: ENTREPRISE INDIVIDUELLE | K55: TEE | L55: CABINET MEDICAL | M55: N/D | N55: N/D | O55: II Plateaux III | P55: N/D | R55: N/D | S55: 2722430459 | T55: 54 | U55: Abidjan | V55: 08 BP 27 ABIDJA | W55: N/D | X55: COCODY | Z55: 44224 | AA55: 1
A56: 2213255G | B56: 55 | C56: MOVATEC | D56: =VLOOKUP('[1]tblclients (1)'!A56,[1]Feuil1!$A$1:$G$203,4,0) -> KOFFI ALBERT | E56: NULL | F56: NULL | G56: DCK-055 | H56: DCK-CGA2023-J001 | I56: NULL | J56: SARL | K56: TEE | L56: NULL | M56: NULL | N56: NULL | O56: Bingerville | P56: NULL | Q56: NULL | R56: NULL | S56: 759166503 | T56: 54 | U56: Abidjan | V56: NULL | W56: NULL | X56: BINGERVILLE | Y56: NULL | Z56: 44935 | AA56: 1
A57: 2244612N | B57: 56 | C57: SOCIETE DE MAINTENANCE ET D'INGENIERIE | D57: =VLOOKUP('[1]tblclients (1)'!A57,[1]Feuil1!$A$1:$G$203,4,0) -> KOFFI ALBERT | E57: NULL | F57: NULL | G57: DCK-056 | H57: DCK-CGA2023-J002 | I57: NULL | J57: SARL | K57: TEE | L57: NULL | M57: NULL | N57: NULL | O57: Bingerville | P57: NULL | Q57: NULL | R57: NULL | S57: 584483480 | T57: 54 | U57: Abidjan | V57: NULL | W57: NULL | X57: BINGERVILLE | Y57: NULL | Z57: 44935 | AA57: 1
A58: 2164416N | B58: 57 | C58: MIWA ENTREPRISE | D58: =VLOOKUP('[1]tblclients (1)'!A58,[1]Feuil1!$A$1:$G$203,4,0) -> KOFFI ALBERT | E58: NULL | F58: NULL | G58: DCK-057 | H58: DCK-CGA2023-J005 | I58: NULL | J58: SARL | K58: TEE | L58: NULL | M58: NULL | N58: NULL | O58: Bingerville | P58: NULL | Q58: NULL | R58: NULL | S58: 777478849 | T58: 54 | U58: Abidjan | V58: NULL | W58: NULL | X58: BINGERVILLE RESIDENTIEL | Y58: NULL | Z58: 44939 | AA58: 1
A59: 2243334B | B59: 58 | C59: GROUP INNOV SERVICE | D59: =VLOOKUP('[1]tblclients (1)'!A59,[1]Feuil1!$A$1:$G$203,4,0) -> KOFFI ALBERT | E59: NULL | F59: NULL | G59: DCK-058 | H59: DCK-CGA2023-J006 | I59: NULL | J59: SARL | K59: TEE | L59: NULL | M59: NULL | N59: NULL | O59: Bingerville | P59: NULL | Q59: NULL | R59: NULL | S59: 759484148 | T59: 54 | U59: Abidjan | V59: NULL | W59: NULL | X59: BINGERVILLE | Y59: NULL | Z59: 44939 | AA59: 1
A60: 2244355H | B60: 59 | C60: AHETOU BIJOUX SARL | D60: =VLOOKUP('[1]tblclients (1)'!A60,[1]Feuil1!$A$1:$G$203,4,0) -> KOFFI ALBERT | E60: NULL | F60: NULL | G60: DCK-059 | H60: DCK-CGA2023-J009 | I60: NULL | J60: SARL | K60: TEE | L60: NULL | M60: NULL | N60: NULL | O60: Bingerville | P60: NULL | Q60: NULL | R60: NULL | S60: 707719065 | T60: 54 | U60: Abidjan | V60: NULL | W60: NULL | X60: RIVIERA 4 M'POUTO | Y60: NULL | Z60: 44942 | AA60: 1
A61: 1825074K | B61: 60 | C61: AFRICAN LEADERS CONSULTING GROUP | D61: =VLOOKUP('[1]tblclients (1)'!A61,[1]Feuil1!$A$1:$G$203,4,0) -> KOFFI ALBERT | E61: NULL | F61: NULL | G61: DCK-060 | H61: DCK-CGA2023-J015 | I61: NULL | J61: SARL | K61: TEE | L61: NULL | M61: NULL | N61: NULL | O61: Bingerville | P61: NULL | Q61: NULL | R61: NULL | S61: 789901646 | T61: 54 | U61: Abidjan | V61: NULL | W61: NULL | X61: BINGERVILLE | Y61: NULL | Z61: 44952 | AA61: 1
A62: 1985323J | B62: 61 | C62: AS SAMAD-CMS | D62: =VLOOKUP('[1]tblclients (1)'!A62,[1]Feuil1!$A$1:$G$203,4,0) -> KOFFI ALBERT | E62: ASSANVO DJEDJOU FRANCK | F62: GERANT | G62: DCK-061 | H62: DCK-CGA2023-J016 | J62: SARL | K62: TEE | S62: 707719624 | T62: 54 | U62: Abidjan | X62: BINGERVILLE | Z62: 44952 | AA62: 1
A63: 2230526V | B63: 62 | C63: ARIELLE CONSTRUCTION | D63: =VLOOKUP('[1]tblclients (1)'!A63,[1]Feuil1!$A$1:$G$203,4,0) -> KOFFI ALBERT | E63: NULL | F63: NULL | G63: DCK-062 | H63: DCK-CGA2023-J022 | I63: NULL | J63: SARL | K63: TEE | L63: NULL | M63: NULL | N63: NULL | O63: Bingerville | P63: NULL | Q63: NULL | R63: NULL | S63: 708410032 | T63: 54 | U63: Abidjan | V63: NULL | W63: NULL | X63: BINGERVILLE | Y63: NULL | Z63: 44953 | AA63: 1
A64: 2242794R | B64: 63 | C64: BODI NEGOCE TRANSPORT ET BATIMENT SARL | D64: =VLOOKUP('[1]tblclients (1)'!A64,[1]Feuil1!$A$1:$G$203,4,0) -> KOFFI ALBERT | E64: NULL | F64: NULL | G64: DCK-063 | H64: DCK-CGA2023-J023 | I64: NULL | J64: SARL | K64: TEE | L64: NULL | M64: NULL | N64: NULL | O64: Riviera II | P64: NULL | Q64: NULL | R64: NULL | S64: 709340500 | T64: 54 | U64: Abidjan | V64: NULL | W64: NULL | X64: COCODY FAYA AKOUEDO | Y64: NULL | Z64: 44953 | AA64: 1
A65: 2244592K | B65: 64 | C65: DIVERS TRAVAUX ET MAINTENANCE | D65: =VLOOKUP('[1]tblclients (1)'!A65,[1]Feuil1!$A$1:$G$203,4,0) -> KOFFI ALBERT | E65: NULL | F65: NULL | G65: DCK-064 | H65: DCK-CGA2023-J024 | I65: NULL | J65: SARL | K65: TEE | L65: NULL | M65: NULL | N65: NULL | O65: Bingerville | P65: NULL | Q65: NULL | R65: NULL | S65: 759484148 | T65: 54 | U65: Abidjan | V65: NULL | W65: NULL | X65: BINGERVILLE | Y65: NULL | Z65: 44953 | AA65: 1
A66: 2243163E | B66: 65 | C66: KARMEL'S | D66: =VLOOKUP('[1]tblclients (1)'!A66,[1]Feuil1!$A$1:$G$203,4,0) -> KOFFI ALBERT | E66: NULL | F66: NULL | G66: DCK-065 | H66: DCK-CGA2023-J025 | I66: NULL | J66: SARL | K66: TEE | L66: NULL | M66: NULL | N66: NULL | O66: Bingerville | P66: NULL | Q66: NULL | R66: NULL | S66: 505095033 | T66: 54 | U66: Abidjan | V66: NULL | W66: NULL | X66: BINGERVILLE | Y66: NULL | Z66: 44953 | AA66: 1
A67: 2188428W | B67: 66 | C67: TETIALI ALICE | D67: =VLOOKUP('[1]tblclients (1)'!A67,[1]Feuil1!$A$1:$G$203,4,0) -> KOFFI ALBERT | E67: NULL | F67: NULL | G67: DCK-066 | H67: DCK-CGA2023-J026 | I67: NULL | J67: ENTREPRISE INDIVIDUELLE | K67: TEE | L67: NULL | M67: NULL | N67: NULL | O67: Riviera II | P67: NULL | Q67: NULL | R67: NULL | S67: 102942319 | T67: 54 | U67: Abidjan | V67: NULL | W67: NULL | X67: COCODY AKOUEDO | Y67: NULL | Z67: 44953 | AA67: 1
A68: 2207048P | B68: 67 | C68: GROUPE RADIUS AFRIQUE | D68: =VLOOKUP('[1]tblclients (1)'!A68,[1]Feuil1!$A$1:$G$203,4,0) -> KOFFI ALBERT | E68: NULL | F68: NULL | G68: DCK-067 | H68: DCK-CGA2023-J027 | I68: NULL | J68: SARL | K68: TEE | L68: NULL | M68: NULL | N68: NULL | O68: Bingerville | P68: NULL | Q68: NULL | R68: NULL | S68: 565117105 | T68: 54 | U68: Abidjan | V68: NULL | W68: NULL | X68: BINGERVILLE FEKESSE | Y68: NULL | Z68: 44953 | AA68: 1
A69: 1832429K | B69: 68 | C69: ETS SUCCES | D69: =VLOOKUP('[1]tblclients (1)'!A69,[1]Feuil1!$A$1:$G$203,4,0) -> KOFFI ALBERT | E69: NULL | F69: NULL | G69: DCK-068 | H69: DCK-CGA2023-J028 | I69: NULL | J69: SARL | K69: TEE | L69: NULL | M69: NULL | N69: NULL | O69: Bingerville | P69: NULL | Q69: NULL | R69: NULL | S69: 153207528 | T69: 54 | U69: Abidjan | V69: NULL | W69: NULL | X69: COCODY ABATTA | Y69: NULL | Z69: 44953 | AA69: 1
A70: 1907515M | B70: 69 | C70: CANAAN GROUP INDUSTRIE | D70: =VLOOKUP('[1]tblclients (1)'!A70,[1]Feuil1!$A$1:$G$203,4,0) -> KOFFI ALBERT | E70: NULL | F70: NULL | G70: DCK-069 | H70: DCK-CGA2023-J029 | I70: NULL | J70: SARL | K70: TEE | L70: NULL | M70: NULL | N70: NULL | O70: Riviera I | P70: NULL | Q70: NULL | R70: NULL | S70: 708757335 | T70: 54 | U70: Abidjan | V70: NULL | W70: NULL | X70: COCODY RIVIERA | Y70: NULL | Z70: 44953 | AA70: 1
A71: 2228002E | B71: 70 | C71: COULIBALY YACOUBA | D71: =VLOOKUP('[1]tblclients (1)'!A71,[1]Feuil1!$A$1:$G$203,4,0) -> KOFFI ALBERT | E71: NULL | F71: NULL | G71: DCK-070 | H71: DCK-CGA2022-J036 | I71: NULL | J71: ENTREPRISE INDIVIDUELLE | K71: TEE | L71: NULL | M71: NULL | N71: NULL | O71: Bingerville | P71: NULL | Q71: NULL | R71: NULL | S71: 707582582 | T71: 54 | U71: Abidjan | V71: NULL | W71: NULL | X71: ABATTA | Y71: NULL | Z71: 44957 | AA71: 1
A72: 2242412G | B72: 71 | C72: LOTUS PHARMA SARL | D72: =VLOOKUP('[1]tblclients (1)'!A72,[1]Feuil1!$A$1:$G$203,4,0) -> KOFFI ALBERT | E72: NULL | F72: NULL | G72: DCK-071 | H72: DCK-CGA2023-J043 | I72: NULL | J72: SARL | K72: TEE | L72: NULL | M72: NULL | N72: NULL | O72: Riviera I | P72: NULL | Q72: NULL | R72: NULL | S72: 757404308 | T72: 54 | U72: Abidjan | V72: NULL | W72: NULL | X72: COCODY RIVERA PALMERAIE | Y72: NULL | Z72: 44957 | AA72: 1
A73: 2301391H | B73: 72 | C73: DID AFRICA | D73: =VLOOKUP('[1]tblclients (1)'!A73,[1]Feuil1!$A$1:$G$203,4,0) -> KOFFI ALBERT | E73: NULL | F73: NULL | G73: DCK-072 | H73: DCK-CGA2023-J053 | I73: NULL | J73: SARL | K73: TEE | L73: NULL | M73: NULL | N73: NULL | O73: Bingerville | P73: NULL | Q73: NULL | R73: NULL | S73: 506497308 | T73: 54 | U73: Abidjan | V73: NULL | W73: NULL | X73: BINGERVILLE CITE DES GRACES II | Y73: NULL | Z73: 45099 | AA73: 1
A74: 1938295X | B74: 73 | C74: ETS ISAHORA | D74: =VLOOKUP('[1]tblclients (1)'!A74,[1]Feuil1!$A$1:$G$203,4,0) -> KOFFI ALBERT | E74: NULL | F74: NULL | G74: DCK-073 | H74: DCK-CGA2022-J016 | I74: NULL | J74: SARL | K74: TEE | L74: NULL | M74: NULL | N74: NULL | O74: Bingerville | P74: NULL | Q74: NULL | R74: NULL | S74: 708529890 | T74: 54 | U74: Abidjan | V74: NULL | W74: NULL | X74: BINGERVILLE CITE FEKRESSE | Y74: NULL | Z74: 44589 | AA74: 1
... A81: 1802101W | B81: 80 | C81: FIXWALL BUILDING | D81: =VLOOKUP('[1]tblclients (1)'!A81,[1]Feuil1!$A$1:$G$203,4,0) -> KOFFI ALBERT | E81: NULL | F81: NULL | G81: DCK-080 | H81: DCK-CGA2022-J009 | I81: NULL | J81: SARL | K81: TEE | L81: NULL | M81: NULL | N81: NULL | O81: Bingerville | P81: NULL | Q81: NULL | R81: NULL | S81: 505040051 | T81: 54 | U81: Abidjan | V81: NULL | W81: NULL | X81: COCODY ABATTA | Y81: NULL | Z81: 44588 | AA81: 1
A82: 2150505H | B82: 81 | C82: CENTRE OPTIQUE LORIAL | D82: =VLOOKUP('[1]tblclients (1)'!A82,[1]Feuil1!$A$1:$G$203,4,0) -> KOFFI ALBERT | G82: DCK-081 | H82: DCK-CGA2022-J010 | J82: SARL | K82: TEE | O82: II Plateaux Djibi | S82: 768713339 | T82: 54 | U82: Abidjan | X82: COCODY | Z82: 44588 | AA82: 1
A83: 2173312Z | B83: 82 | C83: BODI BONDAH NEGOCE TRAVAUX PUBLIC | D83: =VLOOKUP('[1]tblclients (1)'!A83,[1]Feuil1!$A$1:$G$203,4,0) -> KOFFI ALBERT | E83: NULL | F83: NULL | G83: DCK-082 | H83: DCK-CGA2022-J017 | I83: NULL | J83: SARL | K83: TEE | L83: NULL | M83: NULL | N83: NULL | O83: Bingerville | P83: NULL | Q83: NULL | R83: NULL | S83: 777237255 | T83: 54 | U83: Abidjan | V83: NULL | W83: NULL | X83: BINGERVILLE ELOITE | Y83: NULL | Z83: 44589 | AA83: 1
A84: 1602307K | B84: 83 | C84: KOFFI GABOUET BEHIBRO ALFRED | D84: =VLOOKUP('[1]tblclients (1)'!A84,[1]Feuil1!$A$1:$G$203,4,0) -> KOFFI ALBERT | E84: NULL | F84: NULL | G84: DCK-083 | H84: DCK-CGA2022-J018 | I84: NULL | J84: ENTREPRISE INDIVIDUELLE | K84: TEE | L84: NULL | M84: NULL | N84: NULL | O84: Bingerville | P84: NULL | Q84: NULL | R84: NULL | S84: 708247146 | T84: 54 | U84: Abidjan | V84: NULL | W84: NULL | X84: BINGERVILLE | Y84: NULL | Z84: 44589 | AA84: 1
A85: 2179332B | B85: 84 | C85: IMAN TRANSIT ET LOGISTIQUES | D85: =VLOOKUP('[1]tblclients (1)'!A85,[1]Feuil1!$A$1:$G$203,4,0) -> KOFFI ALBERT | G85: DCK-084 | H85: DCK-CGA2022-J020 | J85: SARL | K85: TEE | O85: Bingerville | S85: 789549220 | T85: 54 | U85: Abidjan | X85: COCODY RIVIERA | Z85: 44589 | AA85: 1
A86: 2127301Z | B86: 85 | C86: ETS GREEN GARDEN SARL | D86: =VLOOKUP('[1]tblclients (1)'!A86,[1]Feuil1!$A$1:$G$203,4,0) -> KOFFI ALBERT | E86: NULL | F86: NULL | G86: DCK-085 | H86: DCK-CGA2022-J022 | I86: NULL | J86: SARL | K86: TEE | L86: NULL | M86: NULL | N86: NULL | O86: Bingerville | P86: NULL | Q86: NULL | R86: NULL | S86: 777328417 | T86: 54 | U86: Abidjan | V86: NULL | W86: NULL | X86: BINGERVILLE | Y86: NULL | Z86: 44589 | AA86: 1
A87: 2045884K | B87: 86 | C87: BRIN 2 DOUCEUR EVENT SARL | D87: =VLOOKUP('[1]tblclients (1)'!A87,[1]Feuil1!$A$1:$G$203,4,0) -> KOFFI ALBERT | E87: NULL | F87: NULL | G87: DCK-086 | H87: DCK-CGA2022-J023 | I87: NULL | J87: SARL | K87: TEE | L87: NULL | M87: NULL | N87: NULL | O87: Bingerville | P87: NULL | Q87: NULL | R87: NULL | S87: 777973637 | T87: 54 | U87: Abidjan | V87: NULL | W87: NULL | X87: BINGERVILLE SCI CARRIERE | Y87: NULL | Z87: 44589 | AA87: 1
A88: 2151700M | B88: 87 | C88: NJIR INVEST SARL | D88: =VLOOKUP('[1]tblclients (1)'!A88,[1]Feuil1!$A$1:$G$203,4,0) -> KOFFI ALBERT | E88: NULL | F88: NULL | G88: DCK-087 | H88: DCK-CGA2022-J025 | I88: NULL | J88: SARL | K88: TEE | L88: NULL | M88: NULL | N88: NULL | O88: Bingerville | P88: NULL | Q88: NULL | R88: NULL | S88: 505199503 | T88: 54 | U88: Abidjan | V88: NULL | W88: NULL | X88: ABATTA | Y88: NULL | Z88: 44589 | AA88: 1
A89: 2025933F | B89: 89 | C89: E 2 K CONSTRUCTION | D89: =VLOOKUP('[1]tblclients (1)'!A89,[1]Feuil1!$A$1:$G$203,4,0) -> KOFFI ALBERT | G89: DCK-089 | H89: DCK-CGA2022-J069 | J89: SARL | K89: TEE | O89: Bingerville | S89: 707243416 | T89: 54 | U89: Abidjan | X89: BINGERVILLE | Z89: 44589 | AA89: 1
A90: 2190423P | B90: 90 | C90: STENO GROUP | D90: =VLOOKUP('[1]tblclients (1)'!A90,[1]Feuil1!$A$1:$G$203,4,0) -> KOFFI ALBERT | E90: NULL | F90: NULL | G90: DCK-090 | H90: DCK-CGA2022-J070 | I90: NULL | J90: SARL | K90: TEE | L90: NULL | M90: NULL | N90: NULL | O90: Bingerville | P90: NULL | Q90: NULL | R90: NULL | T90: 54 | U90: Abidjan | V90: NULL | W90: NULL | X90: BINGERVILLE AKANDJE | Y90: NULL | Z90: 44589 | AA90: 1
A91: 2241802W | B91: 91 | C91: GLORY TEAM INTERNATIONAL | D91: =VLOOKUP('[1]tblclients (1)'!A91,[1]Feuil1!$A$1:$G$203,4,0) -> KOFFI ALBERT | E91: NULL | F91: NULL | G91: DCK-091 | H91: DCK-CGA2022-J074 | I91: NULL | J91: SARL | K91: TEE | L91: NULL | M91: NULL | N91: NULL | O91: Bingerville | P91: NULL | Q91: NULL | R91: NULL | S91: 777328417 | T91: 54 | U91: Abidjan | V91: NULL | W91: NULL | Y91: NULL | Z91: 44760 | AA91: 1
A92: 2124572M | B92: 92 | C92: KOUAME KOUAKOU MAXIME | D92: =VLOOKUP('[1]tblclients (1)'!A92,[1]Feuil1!$A$1:$G$203,4,0) -> KONGOZA HARMEL | E92: NULL | F92: NULL | G92: DCK-092 | H92: DCK-CGA2023-J017 | I92: NULL | J92: ENTREPRISE INDIVIDUELLE | K92: TEE | L92: NULL | M92: NULL | N92: NULL | O92: II Plateaux II | P92: NULL | Q92: NULL | R92: NULL | T92: 54 | U92: Abidjan | V92: NULL | W92: NULL | Y92: NULL | Z92: 44951 | AA92: 1
A93: 2242835K | B93: 93 | C93: YANKAN-MO SARLU | D93: =VLOOKUP('[1]tblclients (1)'!A93,[1]Feuil1!$A$1:$G$203,4,0) -> GOHI | E93: NULL | F93: NULL | G93: DCK-093 | H93: DCK-CGA2023-J018 | I93: NULL | J93: SARL | K93: TEE | L93: NULL | M93: NULL | N93: NULL | O93: II Plateaux I | P93: NULL | Q93: NULL | R93: NULL | S93: 757118226 | T93: 54 | U93: Abidjan | V93: NULL | W93: NULL | X93: COCODY ANGRE 7E TRANCHE OSCARS | Y93: NULL | Z93: 44951 | AA93: 1
A94: 2217860F | B94: 94 | C94: KOUMA MAMANI PRESTIGE | D94: =VLOOKUP('[1]tblclients (1)'!A94,[1]Feuil1!$A$1:$G$203,4,0) -> KONGOZA HARMEL | E94: NULL | F94: NULL | G94: DCK-094 | H94: DCK-CGA2023-J032 | I94: NULL | J94: ENTREPRISE INDIVIDUELLE | K94: TEE | L94: NULL | M94: NULL | N94: NULL | O94: II Plateaux I | P94: NULL | Q94: NULL | R94: NULL | T94: 54 | U94: Abidjan | V94: NULL | W94: NULL | Y94: NULL | Z94: 44956 | AA94: 1
A95: 2245374G | B95: 95 | C95: SAYNI ET SON | D95: =VLOOKUP('[1]tblclients (1)'!A95,[1]Feuil1!$A$1:$G$203,4,0) -> GOHI | E95: NULL | F95: NULL | G95: DCK-095 | H95: DCK-CGA2023-J035 | I95: NULL | J95: SARL | K95: TEE | L95: NULL | M95: NULL | N95: NULL | O95: Riviera II | P95: NULL | Q95: NULL | R95: NULL | S95: 708824664 | T95: 54 | U95: Abidjan | V95: NULL | W95: NULL | X95: COCODY RIVIERA BONOUMIN | Y95: NULL | Z95: 44956 | AA95: 1
A96: 2124572M | B96: 96 | C96: GOHI INDUSTRIES GROUP | D96: =VLOOKUP('[1]tblclients (1)'!A96,[1]Feuil1!$A$1:$G$203,4,0) -> GOHI | E96: NULL | F96: NULL | G96: DCK-096 | H96: DCK-CGA2022-J012 | I96: NULL | J96: SARL | K96: TEE | L96: NULL | M96: NULL | N96: NULL | O96: II Plateaux I | P96: NULL | Q96: NULL | R96: NULL | S96: 709767690 | T96: 54 | U96: Abidjan | V96: NULL | W96: NULL | X96: COCODY ANGRE 7E TRANCHE | Y96: NULL | Z96: 44589 | AA96: 1
A97: 2186865J | B97: 97 | C97: ASSISTANCE INTERMEDIATE LEADERS ET PARTNERS | D97: =VLOOKUP('[1]tblclients (1)'!A97,[1]Feuil1!$A$1:$G$203,4,0) -> GOHI | E97: NULL | F97: NULL | G97: DCK-097 | H97: DCK-CGA2022-J015 | I97: NULL | J97: SARL | K97: TEE | L97: NULL | M97: NULL | N97: NULL | O97: II Plateaux I | P97: NULL | Q97: NULL | R97: NULL | S97: 709767690 | T97: 54 | U97: Abidjan | V97: NULL | W97: NULL | X97: COCODY ANGRE 7E TRANCHE | Y97: NULL | Z97: 44589 | AA97: 1
A98: 2013593F | B98: 98 | C98: GROUPE ZOUHOU ET FILS SARL | D98: =VLOOKUP('[1]tblclients (1)'!A98,[1]Feuil1!$A$1:$G$203,4,0) -> GOHI | E98: NULL | F98: NULL | G98: DCK-098 | H98: DCK-CGA2022-J034 | I98: NULL | J98: SARL | K98: TEE | L98: NULL | M98: NULL | N98: NULL | O98: Riviera I | P98: NULL | Q98: NULL | R98: NULL | S98: 707278352 | T98: 54 | U98: Abidjan | V98: NULL | W98: NULL | X98: COCODY RIVIERA M'POUTO CITE CAD | Y98: NULL | Z98: 44589 | AA98: 1
A99: 2166687T | B99: 99 | C99: ENTREPRISE FADIKA IMANE HASSANE HASSANE | D99: =VLOOKUP('[1]tblclients (1)'!A99,[1]Feuil1!$A$1:$G$203,4,0) -> GOHI | G99: DCK-099 | H99: DCK-CGA2021-Q185 | J99: SARL | K99: TEE | O99: II Pateaux II | S99: 505596296 | T99: 54 | U99: Abidjan | X99: COCODY | Z99: 44490 | AA99: 1
A100: 2033895A | B100: 100 | C100: N3H IMMOBILIER CÃ”TE D'IVOIRE | D100: =VLOOKUP('[1]tblclients (1)'!A100,[1]Feuil1!$A$1:$G$203,4,0) -> GOHI | E100: NULL | F100: NULL | G100: DCK-100 | H100: DCK-CGA2022-J046 | I100: NULL | J100: SAS | K100: TEE | L100: NULL | M100: NULL | N100: NULL | O100: Cocody | P100: NULL | Q100: NULL | R100: NULL | T100: 54 | U100: Abidjan | V100: NULL | W100: NULL | X100: COCODY BLAUCKAUSS | Y100: NULL | Z100: 44592 | AA100: 1
A101: 1814915G | B101: 101 | C101: ELECTRICITE-ELECTRONIQUE-PLURIEL ET ASSISTANCE | D101: =VLOOKUP('[1]tblclients (1)'!A101,[1]Feuil1!$A$1:$G$203,4,0) -> GOHI | E101: NULL | F101: NULL | G101: DCK-101 | H101: DCK-CGA2022-J013 | I101: NULL | J101: SARL | K101: TEE | L101: NULL | M101: NULL | N101: NULL | O101: II Plateaux I | P101: NULL | Q101: NULL | R101: NULL | S101: 708247146 | T101: 54 | U101: Abidjan | V101: NULL | W101: NULL | X101: COCODY PLATEAU DOKUI | Y101: NULL | Z101: 44589 | AA101: 1
A102: 2052608M | B102: 102 | C102: CITY ADS | D102: =VLOOKUP('[1]tblclients (1)'!A102,[1]Feuil1!$A$1:$G$203,4,0) -> GOHI | E102: NULL | F102: NULL | G102: DCK-102 | H102: DCK-CGA2022-J014 | I102: NULL | J102: SARL | K102: TEE | L102: NULL | M102: NULL | N102: NULL | O102: Cocody | P102: NULL | Q102: NULL | R102: NULL | S102: 555800500 | T102: 54 | U102: Abidjan | V102: NULL | W102: NULL | X102: COCODY BLAUCKAUSS | Y102: NULL | Z102: 44589 | AA102: 1
A103: 2165858D | B103: 103 | C103: SOCIETE DE TRANSPORT MAMADOU ET FRERES | D103: =VLOOKUP('[1]tblclients (1)'!A103,[1]Feuil1!$A$1:$G$203,4,0) -> GOHI | E103: NULL | F103: NULL | G103: DCK-103 | H103: DCK-CGA2021-Q184 | I103: NULL | J103: SARL | K103: TEE | L103: NULL | M103: NULL | N103: NULL | O103: II Plateaux II | P103: NULL | Q103: NULL | R103: NULL | S103: 757921316 | T103: 54 | U103: Abidjan | V103: NULL | W103: NULL | X103: COCODY II PLATEAUX | Y103: NULL | Z103: 44472 | AA103: 1
A104: 2037325R | B104: 104 | C104: 2N IMMOBILIER | D104: =VLOOKUP('[1]tblclients (1)'!A104,[1]Feuil1!$A$1:$G$203,4,0) -> CABINET CFA | E104: NULL | F104: NULL | G104: DCK-104 | H104: DCK-CGA2019-A006 | I104: NULL | J104: SARL | K104: TEE | L104: NULL | M104: NULL | N104: NULL | O104: II Plateaux I | P104: NULL | Q104: NULL | R104: NULL | S104: 708514241 | T104: 54 | U104: Abidjan | V104: NULL | W104: NULL | X104: DEUX PLATEAUX SICOGI | Y104: NULL | Z104: 43479 | AA104: 1
A105: 1850348X | B105: 105 | C105: 5 PAINS 2 POISSONS | D105: =VLOOKUP('[1]tblclients (1)'!A105,[1]Feuil1!$A$1:$G$203,4,0) -> CABINET CFA | E105: NULL | F105: NULL | G105: DCK-105 | H105: DCK-CGA2021-Q165 | I105: NULL | J105: SARL | K105: TEE | L105: NULL | M105: NULL | N105: NULL | O105: Cocody | P105: NULL | Q105: NULL | R105: NULL | S105: 708047428 | T105: 54 | U105: Abidjan | V105: NULL | W105: NULL | X105: COCODY CENTRE FACE INADES | Y105: NULL | Z105: 44224 | AA105: 1
A106: 0309226W | B106: 106 | C106: ABOA DETCHO JEAN PIERRE | D106: =VLOOKUP('[1]tblclients (1)'!A106,[1]Feuil1!$A$1:$G$203,4,0) -> CABINET CFA | E106: NULL | F106: NULL | G106: DCK-106 | H106: DCK-CGA2021-Q125 | I106: NULL | J106: ENTREPRISE INDIVIDUELLE | K106: TEE | L106: NULL | M106: NULL | N106: NULL | O106: Cocody | P106: NULL | Q106: NULL | R106: NULL | S106: 505074836 | T106: 54 | U106: Abidjan | V106: NULL | W106: NULL | X106: LYCEE TECHNIQUE | Y106: NULL | Z106: 0000-00-00 | AA106: 1
...

Sheet Feuil1
A1: numcc | B1: userid | C1: company | D1: vat | E1: identification | F1: fonction | G1: numcga | H1: numadh | I1: numrccm | J1: formjurid | K1: regime | L1: acti_prin | M1: section | N1: parcelle | O1: imp_centre | P1: codeacti | Q1: montcapit | R1: emailetprse | S1: phonenumber | T1: country | U1: city | V1: zip | W1: state | X1: address | Y1: website | Z1: datecreated | AA1: active | AB1: leadid | AC1: billing_street | AD1: billing_city | AE1: billing_state | AF1: billing_zip | AG1: billing_country | AH1: shipping_street | AI1: shipping_city | AJ1: shipping_state | AK1: shipping_zip | AL1: shipping_country | AM1: longitude | AN1: latitude | AO1: default_language | AP1: default_currency | AQ1: show_primary_contact | AR1: stripe_id | AS1: registration_confirmed | AT1: addedfrom
A2: 4105181N | B2: 1 | C2: HONDE REINE BELLE | D2: NULL | E2: NULL | F2: NULL | G2: DCK-001 | H2: DCK-CGA2019-A026 | I2: NULL | J2: ENTREPRISE INDIVIDUELLE | K2: TEE | L2: NULL | M2: NULL | N2: NULL | O2: II Plateaux II | P2: NULL | Q2: NULL | R2: NULL | S2: 707059199 | T2: 54 | U2: Abidjan | V2: NULL | W2: NULL | X2: COCODY II PLATEAUX VALLONS | Y2: NULL | Z2: 43466 | AA2: 1 | AB2: NULL | AC2: NULL | AD2: NULL | AE2: NULL | AF2: NULL | AG2: NULL | AH2: NULL | AI2: NULL | AJ2: NULL | AK2: NULL | AL2: NULL | AM2: NULL | AN2: NULL | AO2: NULL | AP2: 3 | AQ2: 1 | AR2: NULL | AS2: 1 | AT2: 1
A3: 1526919K | B3: 2 | C3: GOLY ADJOUA EDITH ESTELLE | D3: NULL | E3: GOLY ADJOUA EDITH ESTELLE | F3: Exploitante individuelle | G3: DCK-002 | H3: DCK-CGA2019-A013 | I3: CI-ABJ-2015-A-3981 | J3: ENTREPRISE INDIVIDUELLE | K3: TEE | L3: Fourniture de bureau | M3: EV | N3: 541 | O3: II Plateaux III | P3: CCE1501 | R3: N/D | S3: 758840340 | T3: 54 | U3: Abidjan | V3: 09 BP 1976 ABID | W3: N/D | X3: COCODY RIVERA BONOUMIN | Y3: N/D | Z3: 43466 | AA3: 1 | AB3: NULL | AC3: NULL | AG3: 0 | AL3: 0 | AM3: NULL | AN3: NULL | AO3: NULL | AP3: 0 | AQ3: 1 | AR3: NULL | AS3: 1 | AT3: 1
A4: 1435907M | B4: 3 | C4: ETTE DJEKET CORINE EPSE AVOAKA | D4: NULL | E4: NULL | F4: NULL | G4: DCK-003 | H4: DCK-CGA2020-A050 | I4: NULL | J4: ENTREPRISE INDIVIDUELLE | K4: TEE | L4: NULL | M4: NULL | N4: NULL | O4: Cocody | P4: NULL | Q4: NULL | R4: NULL | S4: 707114141 | T4: 54 | U4: Abidjan | V4: NULL | W4: NULL | X4: COCODY BLOCKAUSS | Y4: NULL | Z4: 43471 | AA4: 1 | AB4: NULL | AC4: NULL | AD4: NULL | AE4: NULL | AF4: NULL | AG4: NULL | AH4: NULL | AI4: NULL | AJ4: NULL | AK4: NULL | AL4: NULL | AM4: NULL | AN4: NULL | AO4: NULL | AP4: 3 | AQ4: 1 | AR4: NULL | AS4: 1 | AT4: 1
A5: 0323332D | B5: 4 | C5: KONATE Harouna | D5: NULL | E5: NULL | F5: NULL | G5: DCK-004 | H5: DCK-CGA2019-A039 | I5: NULL | J5: ENTREPRISE INDIVIDUELLE | K5: TEE | L5: NULL | M5: NULL | N5: NULL | O5: Cocody | P5: NULL | Q5: NULL | R5: NULL | S5: 707941178 | T5: 54 | U5: Abidjan | V5: NULL | W5: NULL | X5: COCODY SAINT JEAN | Y5: NULL | Z5: 43479 | AA5: 1 | AB5: NULL | AC5: NULL | AD5: NULL | AE5: NULL | AF5: NULL | AG5: NULL | AH5: NULL | AI5: NULL | AJ5: NULL | AK5: NULL | AL5: NULL | AM5: NULL | AN5: NULL | AO5: NULL | AP5: 3 | AQ5: 1 | AR5: NULL | AS5: 1 | AT5: 1
A6: 1507261D | B6: 5 | C6: ZANGRE HAROUNA | D6: NULL | E6: NULL | F6: NULL | G6: DCK-005 | H6: DCK-CGA2019-A024 | I6: NULL | J6: ENTREPRISE INDIVIDUELLE | K6: TEE | L6: NULL | M6: NULL | N6: NULL | O6: Cocody | P6: NULL | Q6: NULL | R6: NULL | S6: 505843545 | T6: 54 | U6: Abidjan | V6: NULL | W6: NULL | X6: COCODY SAINT JEAN | Y6: NULL | Z6: 43479 | AA6: 1 | AB6: NULL | AC6: NULL | AD6: NULL | AE6: NULL | AF6: NULL | AG6: NULL | AH6: NULL | AI6: NULL | AJ6: NULL | AK6: NULL | AL6: NULL | AM6: NULL | AN6: NULL | AO6: NULL | AP6: 3 | AQ6: 1 | AR6: NULL | AS6: 1 | AT6: 1
A7: 1414480Q | B7: 6 | C7: OUEDRAOGO YOUSSOUF | D7: NULL | E7: NULL | F7: NULL | G7: DCK-006 | H7: DCK-CGA2019-A023 | I7: NULL | J7: ENTREPRISE INDIVIDUELLE | K7: TEE | L7: NULL | M7: NULL | N7: NULL | O7: Cocody | P7: NULL | Q7: NULL | R7: NULL | S7: 707582591 | T7: 54 | U7: Abidjan | V7: NULL | W7: NULL | X7: COCODY SAINT JEAN | Y7: NULL | Z7: 43479 | AA7: 1 | AB7: NULL | AC7: NULL | AD7: NULL | AE7: NULL | AF7: NULL | AG7: NULL | AH7: NULL | AI7: NULL | AJ7: NULL | AK7: NULL | AL7: NULL | AM7: NULL | AN7: NULL | AO7: NULL | AP7: 3 | AQ7: 1 | AR7: NULL | AS7: 1 | AT7: 1
A8: 1827528R | B8: 7 | C8: YAGUERA & COMPAGNIE | D8: NULL | E8: NULL | F8: NULL | G8: DCK-007 | H8: DCK-CGA2019-A007 | I8: NULL | J8: SARL | K8: TEE | L8: NULL | M8: NULL | N8: NULL | O8: II Plateaux I | P8: NULL | Q8: NULL | R8: NULL | S8: 789844008 | T8: 54 | U8: Abidjan | V8: NULL | W8: NULL | X8: COCODY ANGRE 7E TRANCHE | Y8: NULL | Z8: 43479 | AA8: 1 | AB8: NULL | AC8: NULL | AD8: NULL | AE8: NULL | AF8: NULL | AG8: NULL | AH8: NULL | AI8: NULL | AJ8: NULL | AK8: NULL | AL8: NULL | AM8: NULL | AN8: NULL | AO8: NULL | AP8: 3 | AQ8: 1 | AR8: NULL | AS8: 1 | AT8: 1
A9: 1619903H | B9: 8 | C9: NEDJMA SARLU | D9: NULL | E9: NULL | F9: NULL | G9: DCK-008 | H9: DCK-CGA2019-A029 | I9: NULL | J9: SARL | K9: TEE | L9: NULL | M9: NULL | N9: NULL | O9: II Plateaux I | P9: NULL | Q9: NULL | R9: NULL | S9: 707070102 | T9: 54 | U9: Abidjan | V9: NULL | W9: NULL | X9: COCODY RIVIERA BONOUMIN | Y9: NULL | Z9: 43479 | AA9: 1 | AB9: NULL | AC9: NULL | AD9: NULL | AE9: NULL | AF9: NULL | AG9: NULL | AH9: NULL | AI9: NULL | AJ9: NULL | AK9: NULL | AL9: NULL | AM9: NULL | AN9: NULL | AO9: NULL | AP9: 3 | AQ9: 1 | AR9: NULL | AS9: 1 | AT9: 1
A10: 1530324W | B10: 9 | C10: CONCEPT IMAGE | D10: 27 | G10: DCK-009 | H10: DCK-CGA2019-B036 | J10: SARL | K10: RME | O10: II Plateaux II | S10: 101017474 | T10: 54 | U10: Abidjan | X10: COCODY II PLATAUX SIDECI | Z10: 43479 | AA10: 1 | AB10: NULL | AG10: 0 | AL10: 0 | AM10: NULL | AN10: NULL | AO10: NULL | AP10: 0 | AQ10: 1 | AR10: NULL | AS10: 1 | AT10: 1
A11: 0735268S | B11: 10 | C11: COFFI MARIE COLETTE | D11: NULL | E11: NULL | F11: NULL | G11: DCK-010 | H11: DCK-CGA2019-A022 | I11: NULL | J11: ENTREPRISE INDIVIDUELLE | K11: TEE | L11: NULL | M11: NULL | N11: NULL | O11: II Plateaux II | P11: NULL | Q11: NULL | R11: NULL | S11: 707435252 | T11: 54 | U11: Abidjan | V11: NULL | W11: NULL | X11: COCODY VALLON | Y11: NULL | Z11: 43479 | AA11: 1 | AB11: NULL | AC11: NULL | AD11: NULL | AE11: NULL | AF11: NULL | AG11: NULL | AH11: NULL | AI11: NULL | AJ11: NULL | AK11: NULL | AL11: NULL | AM11: NULL | AN11: NULL | AO11: NULL | AP11: 3 | AQ11: 1 | AR11: NULL | AS11: 1 | AT11: 1
A12: 9410895U | B12: 11 | C12: YERE LOU EPSE YACE NENENAN BLANCHE | D12: NULL | E12: NULL | F12: NULL | G12: DCK-011 | H12: DCK-CGA2019-A040 | I12: NULL | J12: ENTREPRISE INDIVIDUELLE | K12: TEE | L12: NULL | M12: NULL | N12: NULL | O12: II Plateaux II | P12: NULL | Q12: NULL | R12: NULL | S12: 707070392 | T12: 54 | U12: Abidjan | V12: NULL | W12: NULL | X12: COCODY II PLATEAUX VALLON | Y12: NULL | Z12: 43479 | AA12: 1 | AB12: NULL | AC12: NULL | AD12: NULL | AE12: NULL | AF12: NULL | AG12: NULL | AH12: NULL | AI12: NULL | AJ12: NULL | AK12: NULL | AL12: NULL | AM12: NULL | AN12: NULL | AO12: NULL | AP12: 3 | AQ12: 1 | AR12: NULL | AS12: 1 | AT12: 1
A13: 1307492V | B13: 12 | C13: N'GUESSAN ATTIEGOUA ANNE ELLA | D13: NULL | E13: NULL | F13: NULL | G13: DCK-012 | H13: DCK-CGA2019-A010 | I13: NULL | J13: ENTREPRISE INDIVIDUELLE | K13: TEE | L13: NULL | M13: NULL | N13: NULL | O13: II Plateaux II | P13: NULL | Q13: NULL | R13: NULL | S13: 708048295 | T13: 54 | U13: Abidjan | V13: NULL | W13: NULL | X13: II PLATEUX VALLON | Y13: NULL | Z13: 43479 | AA13: 1 | AB13: NULL | AC13: NULL | AD13: NULL | AE13: NULL | AF13: NULL | AG13: NULL | AH13: NULL | AI13: NULL | AJ13: NULL | AK13: NULL | AL13: NULL | AM13: NULL | AN13: NULL | AO13: NULL | AP13: 3 | AQ13: 1 | AR13: NULL | AS13: 1 | AT13: 1
A14: 1220791C | B14: 13 | C14: KOUAME KONAN FIRMIN | D14: NULL | E14: KOUAME KONAN FIRMIN | F14: Exploitant individuel | G14: DCK-013 | H14: DCK-CGA2019-A016 | I14: N/D | J14: ENTREPRISE INDIVIDUELLE | K14: TEE | L14: TRAVAUX DE TELECOM
A15: 1321944W | B15: 14 | C15: KIMOU ERIC HERVE | D15: NULL | E15: KIMOU ERIC | F15: Exploitant individuel | G15: DCK-014 | H15: DCK-CGA2019-A019 | J15: ENTREPRISE INDIVIDUELLE | K15: TEE | S15: 101800240 | T15: 54 | U15: Abidjan | X15: COCODY RIVIERA BONOUMIN | Z15: 43479 | AA15: 1 | AB15: NULL | AC15: NULL | AG15: 0 | AL15: 0 | AM15: NULL | AN15: NULL | AO15: NULL | AP15: 0 | AQ15: 1 | AR15: NULL | AS15: 1 | AT15: 1
A16: 0709432N | B16: 15 | C16: YIRA SIAKA | D16: NULL | E16: YIRA SIAKA | F16: PROPRIETAIRE | G16: DCK-015 | H16: DCK-CGA2019-A005 | I16: 09 BP 2525 ABIDJAN 09 | J16: ENTREPRISE INDIVIDUELLE | K16: TEE | L16: Transport et prestation de services | M16: N/D | N16: N/D | O16: II Plateaux III | P16: SCE2103 | Q16: 6000000 | R16: N/D | S16: 757740598 | T16: 54 | U16: Abidjan | V16: 225 | W16: N/D | X16: COCODY RIVIERA BONOUMIN | Z16: 43479 | AA16: 1 | AB16: NULL | AC16: NULL | AG16: 0 | AL16: 0 | AM16: NULL | AN16: NULL | AO16: NULL | AP16: 0 | AQ16: 1 | AR16: NULL | AS16: 1 | AT16: 1
A17: 0514603E | B17: 16 | C17: ZALLE MAHAMOUD | D17: NULL | E17: ZALLE MAHAMOUD | F17: Exploitant Individuel | G17: DCK-016 | H17: DCK-CGA2019-A025 | I17: CI-ABJ-2011-A-6598 | J17: ENTREPRISE INDIVIDUELLE | K17: TEE | L17: QUINCAILLERIE | M17: N/D | N17: N/D | O17: II Plateaux Djibi | P17: N/D | R17: N/D | S17: 505938989 | T17: 54 | U17: Abidjan | V17: N/D | W17: N/D | X17: COCODY ANGRE-DJIBI | Y17: N/D | Z17: 43479 | AA17: 1 | AB17: NULL | AC17: NULL | AG17: 0 | AL17: 0 | AM17: NULL | AN17: NULL | AO17: NULL | AP17: 0 | AQ17: 1 | AR17: NULL | AS17: 1 | AT17: 1
A18: 1526973R | B18: 17 | C18: CENTRE D'EDUCATION ROUTIERE EN COTE D'IVOIRE | D18: NULL | E18: NULL | F18: NULL | G18: DCK-017 | H18: DCK-CGA2019-B031 | I18: NULL | J18: SARL | K18: RME | L18: NULL | M18: NULL | N18: NULL | O18: Riviera I | P18: NULL | Q18: NULL | R18: NULL | S18: 757893651 | T18: 54 | U18: Abidjan | V18: NULL | W18: NULL | X18: RIVIERA LES JARDINS | Y18: NULL | Z18: 43479 | AA18: 1 | AB18: NULL | AC18: NULL | AD18: NULL | AE18: NULL | AF18: NULL | AG18: NULL | AH18: NULL | AI18: NULL | AJ18: NULL | AK18: NULL | AL18: NULL | AM18: NULL | AN18: NULL | AO18: NULL | AP18: 3 | AQ18: 1 | AR18: NULL | AS18: 1 | AT18: 1
A19: 1019140H | B19: 18 | C19: CISSE MOUSSA | D19: NULL | E19: NULL | F19: NULL | G19: DCK-018 | H19: DCK-CGA2019-A001 | I19: NULL | J19: ENTREPRISE INDIVIDUELLE | K19: TEE | L19: NULL | M19: NULL | N19: NULL | O19: Riviera II | P19: NULL | Q19: NULL | R19: NULL | S19: 505050371 | T19: 54 | U19: Abidjan | V19: NULL | W19: NULL | X19: COCODY RIVIERA FAYA | Y19: NULL | Z19: 43479 | AA19: 1 | AB19: NULL | AC19: NULL | AD19: NULL | AE19: NULL | AF19: NULL | AG19: NULL | AH19: NULL | AI19: NULL | AJ19: NULL | AK19: NULL | AL19: NULL | AM19: NULL | AN19: NULL | AO19: NULL | AP19: 3 | AQ19: 1 | AR19: NULL | AS19: 1 | AT19: 1
A20: 1220743K | B20: 19 | C20: CISSE MOHMED SANASSY | D20: NULL | E20: NULL | F20: NULL | G20: DCK-019 | H20: DCK-CGA2019-A028 | I20: NULL | J20: ENTREPRISE INDIVIDUELLE | K20: TEE | L20: NULL | M20: NULL | N20: NULL | O20: Riviera II | P20: NULL | Q20: NULL | R20: NULL | S20: 779941955 | T20: 54 | U20: Abidjan | V20: NULL | W20: NULL | X20: COCODY RIVIERA PALMERAIE | Y20: NULL | Z20: 43479 | AA20: 1 | AB20: NULL | AC20: NULL | AD20: NULL | AE20: NULL | AF20: NULL | AG20: NULL | AH20: NULL | AI20: NULL | AJ20: NULL | AK20: NULL | AL20: NULL | AM20: NULL | AN20: NULL | AO20: NULL | AP20: 3 | AQ20: 1 | AR20: NULL | AS20: 1 | AT20: 1
A21: 1807923J | B21: 20 | C21: EKYM SARL | D21: NULL | E21: KOUADIO AHOU MICHAELLE | F21: GÃ©rante | G21: DCK-020 | H21: DCK-CGA2019-A006 | I21: CI-ABJ-2018-B-04208 | J21: SARL | K21: TEE | L21: Fournitures de bureaux, Restauration, BÃ¢timent | M21: EV | N21: 222 | O21: II Plateaux III | P21: SCE0203 | Q21: 1000000 | R21: N/D | S21: 102377494 | T21: 54 | U21: Abidjan | V21: 22 BP 799 ABIDJ | W21: N/D | X21: COCODY II PLATEAUX ANGRE | Y21: N/D | Z21: 43479 | AA21: 1 | AB21: NULL | AC21: NULL | AG21: 0 | AL21: 0 | AM21: NULL | AN21: NULL | AO21: NULL | AP21: 0 | AQ21: 1 | AR21: NULL | AS21: 1 | AT21: 1
A22: 1648392M | B22: 21 | C22: KOUAME FIENI MYRIAME-CHRISTELLE | D22: NULL | E22: NULL | F22: NULL | G22: DCK-021 | H22: DCK-CGA2019-A005 | I22: NULL | J22: ENTREPRISE INDIVIDUELLE | K22: TEE | L22: NULL | M22: NULL | N22: NULL | O22: Cocody | P22: NULL | Q22: NULL | R22: NULL | S22: 707063365 | T22: 54 | U22: Abidjan | V22: NULL | W22: NULL | X22: COCODY RIVIERA BONOUMIN | Y22: NULL | Z22: 43522 | AA22: 1 | AB22: NULL | AC22: NULL | AD22: NULL | AE22: NULL | AF22: NULL | AG22: NULL | AH22: NULL | AI22: NULL | AJ22: NULL | AK22: NULL | AL22: NULL | AM22: NULL | AN22: NULL | AO22: NULL | AP22: 3 | AQ22: 1 | AR22: NULL | AS22: 1 | AT22: 1
A23: 1212885P | B23: 22 | C23: YAO N'GUESSAN ADELE EPSE DJEDJE | D23: 0 | E23: YOA N'GUESSAN ADELE EPSE DJEDJE | F23: Exploitante Individuelle | G23: DCK-022 | H23: DCK-CGA2019-A027 | I23: CI-ABJ-2012-A-1024 | J23: ENTREPRISE INDIVIDUELLE | K23: TEE | L23: ALIMENTATION GENERALE ET TRANSFERT D'ARGENT | M23: ABC | N23: 39 | O23: II Plateaux III | P23: SCE0101 | R23: N/D | S23: 505060740 | T23: 54 | U23: Abidjan | W23: N/D | X23: RIVIERA BONOUMIN | Y23: N/D | Z23: 43844 | AA23: 1 | AB23: NULL | AC23: NULL | AG23: 0 | AL23: 0 | AM23: NULL | AN23: NULL | AO23: NULL | AP23: 0 | AQ23: 1 | AR23: NULL | AS23: 1 | AT23: 1
A24: 0714977C | B24: 23 | C24: YACE EMMANUELLE | D24: NULL | E24: YACE EMMANUELLE | F24: Exploitante individuelle | G24: DCK-023 | H24: DCK-CGA2019-A014 | I24: CI-ABJ-2014-A-1249 | J24: ENTREPRISE INDIVIDUELLE | K24: TEE | L24: LOCATION DE SALLE ET TRAITEUR | M24: OZ | N24: 207 | O24: II Plateaux III | P24: SCE0708 | R24: N/D | S24: 707070392 | T24: 54 | U24: Abidjan | W24: N/D | X24: COCODY ANGRE 7E TRANCHE | Z24: 43844 | AA24: 1 | AB24: NULL | AC24: NULL | AG24: 0 | AL24: 0 | AM24: NULL | AN24: NULL | AO24: NULL | AP24: 0 | AQ24: 1 | AR24: NULL | AS24: 1 | AT24: 1
A25: 1800364M | B25: 24 | C25: YAKIM DESIGN | D25: NULL | E25: NULL | F25: NULL | G25: DCK-024 | H25: DCK-CGA2020-A104 | I25: NULL | J25: SARL | K25: TEE | L25: NULL | M25: NULL | N25: NULL | O25: II Plateaux I | P25: NULL | Q25: NULL | R25: NULL | S25: 2722413235 | T25: 54 | U25: Abidjan | V25: NULL | W25: NULL | X25: II PLATEAUX LES PERLES | Y25: NULL | Z25: 43845 | AA25: 1 | AB25: NULL | AC25: NULL | AD25: NULL | AE25: NULL | AF25: NULL | AG25: NULL | AH25: NULL | AI25: NULL | AJ25: NULL | AK25: NULL | AL25: NULL | AM25: NULL | AN25: NULL | AO25: NULL | AP25: 3 | AQ25: 1 | AR25: NULL | AS25: 1 | AT25: 1
A26: 1900445C | B26: 25 | C26: YAO N'DRI FRANCK AIME | D26: NULL | E26: YAO N'DRI FRANCK AIME | F26: Exploitant Individuel | G26: DCK-025 | H26: DCK-CGA2020-A051 | J26: ENTREPRISE INDIVIDUELLE | K26: TEE | L26: PRESTATIONS MEDICALE | M26: ABH | N26: 10 | O26: II Plateaux III | P26: SCE1601 | R26: N/D | S26: 708112943 | T26: 54 | U26: Abidjan | W26: N/D | X26: COCODY BONOUMIN | Z26: 43847 | AA26: 1 | AB26: NULL | AC26: NULL | AG26: 0 | AL26: 0 | AM26: NULL | AN26: NULL | AO26: NULL | AP26: 0 | AQ26: 1 | AR26: NULL | AS26: 1 | AT26: 1
A27: 1745011T | B27: 26 | C27: POHAN KEMOANFOUOGNON AUGUSTE | D27: NULL | E27: POHAN KEMOANFOUOGON AUGUTE | F27: Exploitant individuel | G27: DCK-026 | H27: DCK-CGA2020-A088 | I27: CI-ABJ-2017-A-25544 | J27: ENTREPRISE INDIVIDUELLE | K27: TEE | L27: ASSISTANCE VOYAGE ET ETUDES, FORMATION, DIVERS | M27: AO | N27: 527 | O27: II Plateaux III | P27: SCE2399 | R27: N/D | S27: 778972145 | T27: 54 | U27: Abidjan | W27: N/D | X27: COCODY | Y27: N/D | Z27: 43858 | AA27: 1 | AB27: NULL | AC27: NULL | AG27: 0 | AL27: 0 | AM27: NULL | AN27: NULL | AO27: NULL | AP27: 0 | AQ27: 1 | AR27: NULL | AS27: 1 | AT27: 1
A28: 2042595N | B28: 27 | C28: CNK INTERNATIONAL GROUP SARL | D28: NULL | E28: NULL | F28: NULL | G28: DCK-027 | H28: DCK-CGA2020-A-111 | I28: NULL | J28: SARL | K28: TEE | L28: NULL | M28: NULL | N28: NULL | O28: Riviera I | P28: NULL | Q28: NULL | R28: NULL | S28: 779190538 | T28: 54 | U28: Abidjan | V28: NULL | W28: NULL | X28: COCODY RIVERA II CITE ESTUDIANTINE | Y28: NULL | Z28: 44111 | AA28: 1 | AB28: NULL | AC28: NULL | AD28: NULL | AE28: NULL | AF28: NULL | AG28: NULL | AH28: NULL | AI28: NULL | AJ28: NULL | AK28: NULL | AL28: NULL | AM28: NULL | AN28: NULL | AO28: NULL | AP28: 3 | AQ28: 1 | AR28: NULL | AS28: 1 | AT28: 1
A29: 1006441X | B29: 28 | C29: ETUDE DE MAITRE DIDIER DOUGOUE | D29: NULL | E29: NULL | F29: NULL | G29: DCK-028 | H29: DCK-CGA2019-A120 | I29: NULL | J29: ENTREPRISE INDIVIDUELLE | K29: TEE | L29: NULL | M29: NULL | N29: NULL | O29: II Plateaux I | P29: NULL | Q29: NULL | R29: NULL | S29: 2722527459 | T29: 54 | U29: Abidjan | V29: NULL | W29: NULL | X29: COCODY ANGRE LES OSCARS | Y29: NULL | Z29: 44197 | AA29: 1 | AB29: NULL | AC29: NULL | AD29: NULL | AE29: NULL | AF29: NULL | AG29: NULL | AH29: NULL | AI29: NULL | AJ29: NULL | AK29: NULL | AL29: NULL | AM29: NULL | AN29: NULL | AO29: NULL | AP29: 3 | AQ29: 1 | AR29: NULL | AS29: 1 | AT29: 1
A30: 1351303J | B30: 29 | C30: NEYD DISTRIBUTION | D30: NULL | E30: NULL | F30: NULL | G30: DCK-029 | H30: DCK-CGA2019-A118 | I30: NULL | J30: ENTREPRISE INDIVIDUELLE | K30: TEE | L30: NULL | M30: NULL | N30: NULL | O30: II Plateaux II | P30: NULL | Q30: NULL | R30: NULL | S30: 708302596 | T30: 54 | U30: Abidjan | V30: NULL | W30: NULL | X30: ANGRE 8E TRANCHE | Y30: NULL | Z30: 44197 | AA30: 1 | AB30: NULL | AC30: NULL | AD30: NULL | AE30: NULL | AF30: NULL | AG30: NULL | AH30: NULL | AI30: NULL | AJ30: NULL | AK30: NULL | AL30: NULL | AM30: NULL | AN30: NULL | AO30: NULL | AP30: 3 | AQ30: 1 | AR30: NULL | AS30: 1 | AT30: 1
A31: 0317890C | B31: 30 | C31: SCPA TAKORE, KONAN & ASSOCIES | D31: NULL | E31: NULL | F31: NULL | G31: DCK-030 | H31: DCK-CGA2019-A119 | I31: NULL | J31: SOCIÃ‰TÃ‰ CIVILE | K31: TEE | L31: NULL | M31: NULL | N31: NULL | O31: II Plateaux II | P31: NULL | Q31: NULL | R31: NULL | S31: 2522014025 | T31: 54 | U31: Abidjan | V31: NULL | W31: NULL | X31: II PLATEAUX VALLON | Y31: NULL | Z31: 44197 | AA31: 1 | AB31: NULL | AC31: NULL | AD31: NULL | AE31: NULL | AF31: NULL | AG31: NULL | AH31: NULL | AI31: NULL | AJ31: NULL | AK31: NULL | AL31: NULL | AM31: NULL | AN31: NULL | AO31: NULL | AP31: 3 | AQ31: 1 | AR31: NULL | AS31: 1 | AT31: 1
A32: 1940880C | B32: 31 | C32: BOHIYA SERVICES SARL | D32: NULL | E32: DANHI HENRY DELPHIN | F32: Co-gÃ©rant | G32: DCK-031 | H32: DCK-CGA2019-A117 | I32: CI-ABJ-2019-B-14607 | J32: SARL | K32: TEE | L32: VENTE DE TITRE DE TRANSPORT AERIEN ET TERRESTRE,MONETIQUE ET TRANSFERT D4ARGENT RAPIDE NATIONAUX ET INTERNATIONAUX | M32: OZ | N32: 281 | O32: II Plateaux III | P32: SCE0313 | Q32: 1000000 | R32: N/D | S32: 2722594787 | T32: 54 | U32: Abidjan | W32: BS SARL | X32: COCODY ANGRE 7E TRANCHE | Y32: N/D | Z32: 44197 | AA32: 1 | AB32: NULL | AC32: NULL | AG32: 0 | AL32: 0 | AM32: NULL | AN32: NULL | AO32: NULL | AP32: 0 | AQ32: 1 | AR32: NULL | AS32: 1 | AT32: 1
A33: 2035080J | B33: 32 | C33: DEBOLYINSTRUMENTS SARL | D33: NULL | E33: NULL | F33: NULL | G33: DCK-032 | H33: DCK-CGA2020-A115 | I33: NULL | J33: SARL | K33: TEE | L33: NULL | M33: NULL | N33: NULL | O33: Riviera I | P33: NULL | Q33: NULL | R33: NULL | S33: 707053694 | T33: 54 | U33: Abidjan | V33: NULL | W33: NULL | X33: RIVIERA 3 MOSQUEE | Y33: NULL | Z33: 44197 | AA33: 1 | AB33: NULL | AC33: NULL | AD33: NULL | AE33: NULL | AF33: NULL | AG33: NULL | AH33: NULL | AI33: NULL | AJ33: NULL | AK33: NULL | AL33: NULL | AM33: NULL | AN33: NULL | AO33: NULL | AP33: 3 | AQ33: 1 | AR33: NULL | AS33: 1 | AT33: 1
A34: 1224798B | B34: 33 | C34: KADIO-MOROKRO MAUD AICHA (FOR MEN) | D34: NULL | E34: NULL | F34: NULL | G34: DCK-033 | H34: DCK-CGA-2021-Q154 | I34: NULL | J34: ENTREPRISE INDIVIDUELLE | K34: TEE | L34: NULL | M34: NULL | N34: NULL | O34: II Plateaux II | P34: NULL | Q34: NULL | R34: NULL | S34: 749820808 | T34: 54 | U34: Abidjan | V34: NULL | W34: NULL | X34: COCODY II PLATEAUX VALLON | Y34: NULL | Z34: 44224 | AA34: 1 | AB34: NULL | AC34: NULL | AD34: NULL | AE34: NULL | AF34: NULL | AG34: NULL | AH34: NULL | AI34: NULL | AJ34: NULL | AK34: NULL | AL34: NULL | AM34: NULL | AN34: NULL | AO34: NULL | AP34: 3 | AQ34: 1 | AR34: NULL | AS34: 1 | AT34: 1
A35: 1927845K | B35: 34 | C35: PHILIPPE INES GROUP | D35: NULL | E35: NULL | F35: NULL | G35: DCK-034 | H35: DCK-CGA-2021-Q174 | I35: NULL | J35: SARL | K35: TEE | L35: NULL | M35: NULL | N35: NULL | O35: II Plateaux II | P35: NULL | Q35: NULL | R35: NULL | S35: 77767968 | T35: 54 | U35: Abidjan | V35: NULL | W35: NULL | X35: II PLATEAUX | Y35: NULL | Z35: 44224 | AA35: 1 | AB35: NULL | AC35: NULL | AD35: NULL | AE35: NULL | AF35: NULL | AG35: NULL | AH35: NULL | AI35: NULL | AJ35: NULL | AK35: NULL | AL35: NULL | AM35: NULL | AN35: NULL | AO35: NULL | AP35: 3 | AQ35: 1 | AR35: NULL | AS35: 1 | AT35: 1
A36: 1947542X | B36: 35 | C36: OREMUS SARLU | D36: 76 | E36: YEBOUE EPSE BOUAH ADJOUA IRENE | F36: GÃ©rante | G36: DCK-035 | H36: DCK-CGA2024-A050 | I36: CI-ABJ-2019-B-17445 | J36: SARL | K36: TEE | L36: LOCATIONS MATERIELS ,EVEMENTIELS,LOCATION VEHICULE | M36: N/D | N36: N/D | O36: II Pateaux II | P36: SCC0701 | Q36: 5000000 | R36: N/D | S36: 707830824 | T36: 54 | U36: Abidjan | V36: 08 BP 21115 ABI | W36: N/D | X36: COCODY II PLATEAUX VALLON | Y36: N/D | Z36: 44224 | AA36: 1 | AB36: NULL | AC36: NULL | AG36: 0 | AL36: 0 | AM36: NULL | AN36: NULL | AO36: NULL | AP36: 0 | AQ36: 1 | AR36: NULL | AS36: 1 | AT36: 1
A37: 2110646D | B37: 36 | C37: IVOIR QUALITE ET SERVICES | D37: NULL | E37: NULL | F37: NULL | G37: DCK-036 | H37: DCK-CGA-2021-Q172 | I37: NULL | J37: SARL | K37: RME | L37: NULL | M37: NULL | N37: NULL | O37: II Plateaux I | P37: NULL | Q37: NULL | R37: NULL | S37: 2722427504 | T37: 54 | U37: Abidjan | V37: NULL | W37: NULL | X37: COCODY-ANGRÃ‰-CITÃ‰ BEL HORIZON | Y37: NULL | Z37: 44264 | AA37: 1 | AB37: NULL | AC37: NULL | AD37: NULL | AE37: NULL | AF37: NULL | AG37: NULL | AH37: NULL | AI37: NULL | AJ37: NULL | AK37: NULL | AL37: NULL | AM37: NULL | AN37: NULL | AO37: NULL | AP37: 3 | AQ37: 1 | AR37: NULL | AS37: 1 | AT37: 1
A38: 2196217J | B38: 37 | C38: SANTE & SECURITE AU TRAVAIL | D38: NULL | E38: NULL | F38: NULL | G38: DCK-037 | H38: DCK-CGA-2022-J002 | I38: NULL | J38: SARL | K38: TEE | L38: NULL | M38: NULL | N38: NULL | O38: Riviera I | P38: NULL | Q38: NULL | R38: NULL | S38: 566284952 | T38: 54 | U38: Abidjan | V38: NULL | W38: NULL | X38: COCODY RIVIERA GOLF ANONO | Y38: NULL | Z38: 44564 | AA38: 1 | AB38: NULL | AC38: NULL | AD38: NULL | AE38: NULL | AF38: NULL | AG38: NULL | AH38: NULL | AI38: NULL | AJ38: NULL | AK38: NULL | AL38: NULL | AM38: NULL | AN38: NULL | AO38: NULL | AP38: 3 | AQ38: 1 | AR38: NULL | AS38: 1 | AT38: 1
A39: 1865233X | B39: 38 | C39: YAPO YAPO GHISLAIN CYRILLE | D39: NULL | E39: NULL | F39: NULL | G39: DCK-038 | H39: DCK-CGA-2022-J004 | I39: NULL | J39: ENTREPRISE INDIVIDUELLE | K39: TEE | L39: NULL | M39: NULL | N39: NULL | O39: Riviera I | P39: NULL | Q39: NULL | R39: NULL | S39: 778120796 | T39: 54 | U39: Abidjan | V39: NULL | W39: NULL | X39: COCODY RIVIERA II | Y39: NULL | Z39: 44574 | AA39: 1 | AB39: NULL | AC39: NULL | AD39: NULL | AE39: NULL | AF39: NULL | AG39: NULL | AH39: NULL | AI39: NULL | AJ39: NULL | AK39: NULL | AL39: NULL | AM39: NULL | AN39: NULL | AO39: NULL | AP39: 3 | AQ39: 1 | AR39: NULL | AS39: 1 | AT39: 1
A40: 2114065J | B40: 39 | C40: POSY SECURITY AND SERVICES | D40: NULL | E40: NULL | F40: NULL | G40: DCK-039 | H40: DCK-CGA-2022-J011 | I40: NULL | J40: SARL | K40: TEE | L40: NULL | M40: NULL | N40: NULL | O40: II Plateaux I | P40: NULL | Q40: NULL | R40: NULL | S40: 103041792 | T40: 54 | U40: Abidjan | V40: NULL | W40: NULL | X40: COCODY ANGRE | Y40: NULL | Z40: 44588 | AA40: 1 | AB40: NULL | AC40: NULL | AD40: NULL | AE40: NULL | AF40: NULL | AG40: NULL | AH40: NULL | AI40: NULL | AJ40: NULL | AK40: NULL | AL40: NULL | AM40: NULL | AN40: NULL | AO40: NULL | AP40: 3 | AQ40: 1 | AR40: NULL | AS40: 1 | AT40: 1
A41: 2224403Z | B41: 40 | C41: MIGHTY SPIRIT GROUP | D41: NULL | E41: NULL | F41: NULL | G41: DCK-040 | H41: DCK-CGA-2022-J055 | I41: NULL | J41: SARL | K41: TEE | L41: NULL | M41: NULL | N41: NULL | O41: Riviera II | P41: NULL | Q41: NULL | R41: NULL | S41: 707102042 | T41: 54 | U41: Abidjan | V41: NULL | W41: NULL | X41: COCODY RIVERA FAYA | Y41: NULL | Z41: 44628 | AA41: 1 | AB41: NULL | AC41: NULL | AD41: NULL | AE41: NULL | AF41: NULL | AG41: NULL | AH41: NULL | AI41: NULL | AJ41: NULL | AK41: NULL | AL41: NULL | AM41: NULL | AN41: NULL | AO41: NULL | AP41: 3 | AQ41: 1 | AR41: NULL | AS41: 1 | AT41: 1
A42: 1643628L | B42: 41 | C42: GAYE ABO ALBARETTE JOSEE | D42: NULL | E42: NULL | F42: NULL | G42: DCK-041 | H42: DCK-CGA-2022-J063 | I42: NULL | J42: ENTREPRISE INDIVIDUELLE | K42: TEE | L42: NULL | M42: NULL | N42: NULL | O42: II Plateaux I | P42: NULL | Q42: NULL | R42: NULL | S42: 757284028 | T42: 54 | U42: Abidjan | V42: NULL | W42: NULL | X42: COCODY II PLATEAUX 8E TRANCHE | Y42: NULL | Z42: 44680 | AA42: 1 | AB42: NULL | AC42: NULL | AD42: NULL | AE42: NULL | AF42: NULL | AG42: NULL | AH42: NULL | AI42: NULL | AJ42: NULL | AK42: NULL | AL42: NULL | AM42: NULL | AN42: NULL | AO42: NULL | AP42: 3 | AQ42: 1 | AR42: NULL | AS42: 1 | AT42: 1
A43: 2227520U | B43: 42 | C43: CKK SERVICES & LOGISTICS | D43: NULL | E43: NULL | F43: NULL | G43: DCK-042 | H43: DCK-CGA-2022-J065 | I43: NULL | J43: SARL | K43: TEE | L43: NULL | M43: NULL | N43: NULL | O43: II Plateaux I | P43: NULL | Q43: NULL | R43: NULL | S43: 707578383 | T43: 54 | U43: Abidjan | V43: NULL | W43: NULL | X43: COCODY ANGRE 8E TRANCHE | Y43: NULL | Z43: 44680 | AA43: 1 | AB43: NULL | AC43: NULL | AD43: NULL | AE43: NULL | AF43: NULL | AG43: NULL | AH43: NULL | AI43: NULL | AJ43: NULL | AK43: NULL | AL43: NULL | AM43: NULL | AN43: NULL | AO43: NULL | AP43: 3 | AQ43: 1 | AR43: NULL | AS43: 1 | AT43: 1
A44: 1728145D | B44: 43 | C44: KHORA SARL | D44: NULL | E44: NULL | F44: NULL | G44: DCK-043 | H44: DCK-CGA-2023-J003 | I44: NULL | J44: SARL | K44: TEE | L44: NULL | M44: NULL | N44: NULL | O44: II Plateaux II | P44: NULL | Q44: NULL | R44: NULL | S44: 707262649 | T44: 54 | U44: Abidjan | V44: NULL | W44: NULL | X44: COCODY II PLATEAUX | Y44: NULL | Z44: 44939 | AA44: 1 | AB44: NULL | AC44: NULL | AD44: NULL | AE44: NULL | AF44: NULL | AG44: NULL | AH44: NULL | AI44: NULL | AJ44: NULL | AK44: NULL | AL44: NULL | AM44: NULL | AN44: NULL | AO44: NULL | AP44: 3 | AQ44: 1 | AR44: NULL | AS44: 1 | AT44: 1
A45: 2164509F | B45: 44 | C45: LEADER WORLD PERFECT | D45: 122 | E45: Mme SANFO | F45: GÃ©rante | G45: DCK-044 | H45: DCK-CGA-2022-J012 | I45: CI-ABJ-2021-03729 | J45: SARL | K45: TEE | L45: COMMERCE GENERALE-INFORMATIQUE | M45: SZ | N45: 71 | O45: II Plateaux III | P45: CCE1402 | Q45: 1000000 | R45: N/D | S45: 747994794 | T45: 54 | U45: Abidjan | V45: 06 BP 2346 ABID | W45: LWP | X45: COCODY ATTOBAN | Y45: N/D | Z45: 44952 | AA45: 1 | AB45: NULL | AC45: NULL | AG45: 0 | AL45: 0 | AM45: NULL | AN45: NULL | AO45: NULL | AP45: 0 | AQ45: 1 | AR45: NULL | AS45: 1 | AT45: 1
A46: 1821484C | B46: 45 | C46: COM & CONFORT SARL | D46: 127 | E46: GOSSE ANGE SAINT CLAIR | F46: GÃ©rant | G46: DCK-045 | H46: DCK-CGA-2022-J013 | I46: CI-ABJ-2018-B-10503 | J46: SARL | K46: TEE | L46: CABINET CONSEIL EN COMMUNICATION-IMPRESSION-PUBLICITE | M46: AO | N46: 527 | O46: II Plateaux III | P46: IND1504 | Q46: 1000000 | R46: N/D | S46: 709310771 | T46: 54 | U46: Abidjan | V46: BP 330 BINGERVI | W46: N/D | X46: COCODY RIVIERA | Y46: N/D | Z46: 44952 | AA46: 1 | AB46: NULL | AC46: NULL | AG46: 0 | AL46: 0 | AM46: NULL | AN46: NULL | AO46: NULL | AP46: 0 | AQ46: 1 | AR46: NULL | AS46: 1 | AT46: 1
A47: 2244195W | B47: 46 | C47: PRESTIGE INNOV SARLU | D47: 114 | E47: BARRY FACINET | F47: GERANT | G47: DCK-046 | H47: DCK-CGA-2023-J019 | I47: CI-ABJ-03-2022-B13-09162 | J47: SARL | K47: TEE | L47: SOLUTION-INFORMATIQUE-CONSULTING | M47: ES | N47: 73 | O47: II Plateaux III | P47: SCE0801 | Q47: 1000000 | R47: N/D | S47: 709310771 | T47: 54 | U47: Abidjan | V47: 12 BP 1661 ABID | W47: N/D | X47: COCODY RIVIERA 3 | Y47: N/D | Z47: 44953 | AA47: 1 | AB47: NULL | AC47: NULL | AG47: 0 | AL47: 0 | AM47: NULL | AN47: NULL | AO47: NULL | AP47: 0 | AQ47: 1 | AR47: NULL | AS47: 1 | AT47: 1
A48: 2136391L | B48: 47 | C48: PERFORM WAVE CONSULTING | D48: 70 | E48: FONTAINE JULIEN | F48: GÃ©rant | G48: DCK-047 | H48: DCK-CGA-2023-J021 | I48: CI-ABJ-03-2021-B12-02105 | J48: SARL | K48: TEE | L48: TIC, DEVELOPPEMENT INFORMATIQUE | M48: OZ | N48: N/D | O48: II Plateaux III | P48: SCE0804 | Q48: 700000 | R48: N/D | S48: 797923730 | T48: 54 | U48: Abidjan | V48: 28 BP 1676 ABID | W48: N/D | X48: COCODY II PLATEAUX 7E TRANCHE | Y48: N/D | Z48: 44953 | AA48: 1 | AB48: NULL | AC48: NULL | AG48: 0 | AL48: 0 | AM48: NULL | AN48: NULL | AO48: NULL | AP48: 0 | AQ48: 1 | AR48: NULL | AS48: 1 | AT48: 1
A49: 2241768C | B49: 48 | C49: J&K CONSULTING SARLU | D49: 113 | E49: DJOGBENOU JEAN NOEL | F49: GÃ©rant | G49: DCK-048 | H49: DCK-CGA-2022-J030 | I49: CI-ABJ-03-2022-B12-02388 | J49: SARL | K49: TEE | L49: FORAMATION-CONSEIL-ETUDE | M49: AO | N49: 527 | O49: II Plateaux III | P49: SCE0802 | Q49: 10000000 | R49: N/D | S49: 708414136 | T49: 54 | U49: Abidjan | V49: 09 BP 290 ABIDJ | W49: N/D | X49: COCODY RIVIERA 3 BONOUMIN | Y49: N/D | Z49: 44956 | AA49: 1 | AB49: NULL | AC49: NULL | AG49: 0 | AL49: 0 | AM49: NULL | AN49: NULL | AO49: NULL | AP49: 0 | AQ49: 1 | AR49: NULL | AS49: 1 | AT49: 1
A50: 2243769Z | B50: 49 | C50: VIDAS GROUP HOLDING | D50: NULL | E50: DJOGBENOU | F50: JEAN NOEL | G50: DCK-049 | H50: DCK-CGA-2022-J031 | I50: CI-ABJ-03-B17-00080 | J50: SARL | K50: TEE | L50: FORMATION-CONSEIL-ETUDE-VENTE | M50: AO | N50: 13 | O50: II Plateaux III | P50: SCE1504 | Q50: 10000000 | R50: N/D | S50: 708414136 | T50: 54 | U50: Abidjan | V50: 09 BP 290 ABIDJ | W50: N/D | X50: COCODY BONOUMIN | Y50: N/D | Z50: 44956 | AA50: 1 | AB50: NULL | AC50: NULL | AG50: 0 | AL50: 0 | AM50: NULL | AN50: NULL | AO50: NULL | AP50: 0 | AQ50: 1 | AR50: NULL | AS50: 1 | AT50: 1
A51: 2243064N | B51: 50 | C51: BIOFOSSE GROUP SARL | D51: NULL | E51: NULL | F51: NULL | G51: DCK-050 | H51: DCK-CGA2023-J032 | I51: NULL | J51: SARL | K51: TEE | L51: NULL | M51: NULL | N51: NULL | O51: Cocody | P51: NULL | Q51: NULL | R51: NULL | S51: 767787637 | T51: 54 | U51: Abidjan | V51: NULL | W51: NULL | X51: COCODY MERMOZ | Y51: NULL | Z51: 44957 | AA51: 1 | AB51: NULL | AC51: NULL | AD51: NULL | AE51: NULL | AF51: NULL | AG51: NULL | AH51: NULL | AI51: NULL | AJ51: NULL | AK51: NULL | AL51: NULL | AM51: NULL | AN51: NULL | AO51: NULL | AP51: 3 | AQ51: 1 | AR51: NULL | AS51: 1 | AT51: 1
A52: 2023515A | B52: 51 | C52: MULSERVICES SA | D52: NULL | E52: NULL | F52: NULL | G52: DCK-051 | I52: NULL | J52: SA | K52: RME | L52: NULL | M52: NULL | N52: NULL | O52: II Plateaux II | P52: NULL | Q52: NULL | R52: NULL | S52: 757315050 | T52: 54 | U52: Abidjan | V52: NULL | W52: NULL | X52: COCODY II PLATEAUX VALLON | Y52: NULL | Z52: 0000-00-00 | AA52: 1 | AB52: NULL | AC52: NULL | AD52: NULL | AE52: NULL | AF52: NULL | AG52: NULL | AH52: NULL | AI52: NULL | AJ52: NULL | AK52: NULL | AL52: NULL | AM52: NULL | AN52: NULL | AO52: NULL | AP52: 3 | AQ52: 1 | AR52: NULL | AS52: 1 | AT52: 1
A53: 1809549M | B53: 52 | C53: MABARA SERVICES | D53: NULL | E53: DOUMBIA MASSANKE | F53: GÃ©rante | G53: DCK-052 | H53: DCK-CGA2019-A008 | I53: CI-ABJ-2018-B-04500 | J53: SARL | K53: TEE | L53: Alimentation, fournitures techniques | M53: MN | N53: 300 | O53: II Plateaux Djibi | P53: CCE0101 | Q53: 1000000 | R53: N/D | S53: 708762020 | T53: 54 | U53: Abidjan | V53: 11 BP 2710 ABID | W53: N/D | X53: ANGRE BESSIKOI | Y53: N/D | Z53: 43479 | AA53: 1 | AB53: NULL | AC53: NULL | AG53: 0 | AL53: 0 | AM53: NULL | AN53: NULL | AO53: NULL | AP53: 0 | AQ53: 1 | AR53: NULL | AS53: 1 | AT53: 1
A54: 1342660S | B54: 53 | C54: HAMDOUN HASSAN | D54: NULL | E54: HAMDOUN HASSAN | F54: Exploitant individuel | G54: DCK-053 | H54: DCK-CGA2021-Q182 | I54: CI-ABJ-2015-A-8889 | J54: ENTREPRISE INDIVIDUELLE | K54: TEE | L54: LABO PHOTO | M54: HL | N54: 850 | O54: II Plateaux Djibi | P54: ART0403 | R54: N/D | S54: 565009518 | T54: 54 | U54: Abidjan | V54: N/D | W54: N/D | X54: ANGRE 8E TRANCHE MANDELA | Z54: 44224 | AA54: 1 | AB54: NULL | AC54: NULL | AG54: 0 | AL54: 0 | AM54: NULL | AN54: NULL | AO54: NULL | AP54: 0 | AQ54: 1 | AR54: NULL | AS54: 1 | AT54: 1
A55: 9207146M | B55: 54 | C55: DOCTEUR DIOULO MATHURIN | D55: NULL | E55: DOCTEUR DIOULO MATHURIN | F55: Exploitant individuel | G55: DCK-054 | H55: DCK-CGA2021-Q173 | I55: CI-ABJ-1992-A-165699 | J55: ENTREPRISE INDIVIDUELLE | K55: TEE | L55: CABINET MEDICAL | M55: N/D | N55: N/D | O55: II Plateaux III | P55: N/D | R55: N/D | S55: 2722430459 | T55: 54 | U55: Abidjan | V55: 08 BP 27 ABIDJA | W55: N/D | X55: COCODY | Z55: 44224 | AA55: 1 | AB55: NULL | AC55: NULL | AG55: 0 | AL55: 0 | AM55: NULL | AN55: NULL | AO55: NULL | AP55: 0 | AQ55: 1 | AR55: NULL | AS55: 1 | AT55: 1
A56: 2213255G | B56: 55 | C56: MOVATEC | D56: NULL | E56: NULL | F56: NULL | G56: DCK-055 | H56: DCK-CGA2023-J001 | I56: NULL | J56: SARL | K56: TEE | L56: NULL | M56: NULL | N56: NULL | O56: Bingerville | P56: NULL | Q56: NULL | R56: NULL | S56: 759166503 | T56: 54 | U56: Abidjan | V56: NULL | W56: NULL | X56: BINGERVILLE | Y56: NULL | Z56: 44935 | AA56: 1 | AB56: NULL | AC56: NULL | AD56: NULL | AE56: NULL | AF56: NULL | AG56: NULL | AH56: NULL | AI56: NULL | AJ56: NULL | AK56: NULL | AL56: NULL | AM56: NULL | AN56: NULL | AO56: NULL | AP56: 3 | AQ56: 1 | AR56: NULL | AS56: 1 | AT56: 1
A57: 2244612N | B57: 56 | C57: SOCIETE DE MAINTENANCE ET D'INGENIERIE | D57: NULL | E57: NULL | F57: NULL | G57: DCK-056 | H57: DCK-CGA2023-J002 | I57: NULL | J57: SARL | K57: TEE | L57: NULL | M57: NULL | N57: NULL | O57: Bingerville | P57: NULL | Q57: NULL | R57: NULL | S57: 584483480 | T57: 54 | U57: Abidjan | V57: NULL | W57: NULL | X57: BINGERVILLE | Y57: NULL | Z57: 44935 | AA57: 1 | AB57: NULL | AC57: NULL | AD57: NULL | AE57: NULL | AF57: NULL | AG57: NULL | AH57: NULL | AI57: NULL | AJ57: NULL | AK57: NULL | AL57: NULL | AM57: NULL | AN57: NULL | AO57: NULL | AP57: 3 | AQ57: 1 | AR57: NULL | AS57: 1 | AT57: 1
A58: 2164416N | B58: 57 | C58: MIWA ENTREPRISE | D58: NULL | E58: NULL | F58: NULL | G58: DCK-057 | H58: DCK-CGA2023-J005 | I58: NULL | J58: SARL | K58: TEE | L58: NULL | M58: NULL | N58: NULL | O58: Bingerville | P58: NULL | Q58: NULL | R58: NULL | S58: 777478849 | T58: 54 | U58: Abidjan | V58: NULL | W58: NULL | X58: BINGERVILLE RESIDENTIEL | Y58: NULL | Z58: 44939 | AA58: 1 | AB58: NULL | AC58: NULL | AD58: NULL | AE58: NULL | AF58: NULL | AG58: NULL | AH58: NULL | AI58: NULL | AJ58: NULL | AK58: NULL | AL58: NULL | AM58: NULL | AN58: NULL | AO58: NULL | AP58: 3 | AQ58: 1 | AR58: NULL | AS58: 1 | AT58: 1
A59: 2243334B | B59: 58 | C59: GROUP INNOV SERVICE | D59: NULL | E59: NULL | F59: NULL | G59: DCK-058 | H59: DCK-CGA2023-J006 | I59: NULL | J59: SARL | K59: TEE | L59: NULL | M59: NULL | N59: NULL | O59: Bingerville | P59: NULL | Q59: NULL | R59: NULL | S59: 759484148 | T59: 54 | U59: Abidjan | V59: NULL | W59: NULL | X59: BINGERVILLE | Y59: NULL | Z59: 44939 | AA59: 1 | AB59: NULL | AC59: NULL | AD59: NULL | AE59: NULL | AF59: NULL | AG59: NULL | AH59: NULL | AI59: NULL | AJ59: NULL | AK59: NULL | AL59: NULL | AM59: NULL | AN59: NULL | AO59: NULL | AP59: 3 | AQ59: 1 | AR59: NULL | AS59: 1 | AT59: 1
A60: 2244355H | B60: 59 | C60: AHETOU BIJOUX SARL | D60: NULL | E60: NULL | F60: NULL | G60: DCK-059 | H60: DCK-CGA2023-J009 | I60: NULL | J60: SARL | K60: TEE | L60: NULL | M60: NULL | N60: NULL | O60: Bingerville | P60: NULL | Q60: NULL | R60: NULL | S60: 707719065 | T60: 54 | U60: Abidjan | V60: NULL | W60: NULL | X60: RIVIERA 4 M'POUTO | Y60: NULL | Z60: 44942 | AA60: 1 | AB60: NULL | AC60: NULL | AD60: NULL | AE60: NULL | AF60: NULL | AG60: NULL | AH60: NULL | AI60: NULL | AJ60: NULL | AK60: NULL | AL60: NULL | AM60: NULL | AN60: NULL | AO60: NULL | AP60: 3 | AQ60: 1 | AR60: NULL | AS60: 1 | AT60: 1
A61: 1825074K | B61: 60 | C61: AFRICAN LEADERS CONSULTING GROUP | D61: NULL | E61: NULL | F61: NULL | G61: DCK-060 | H61: DCK-CGA2023-J015 | I61: NULL | J61: SARL | K61: TEE | L61: NULL | M61: NULL | N61: NULL | O61: Bingerville | P61: NULL | Q61: NULL | R61: NULL | S61: 789901646 | T61: 54 | U61: Abidjan | V61: NULL | W61: NULL | X61: BINGERVILLE | Y61: NULL | Z61: 44952 | AA61: 1 | AB61: NULL | AC61: NULL | AD61: NULL | AE61: NULL | AF61: NULL | AG61: NULL | AH61: NULL | AI61: NULL | AJ61: NULL | AK61: NULL | AL61: NULL | AM61: NULL | AN61: NULL | AO61: NULL | AP61: 3 | AQ61: 1 | AR61: NULL | AS61: 1 | AT61: 1
A62: 1985323J | B62: 61 | C62: AS SAMAD-CMS | D62: 76 | E62: ASSANVO DJEDJOU FRANCK | F62: GERANT | G62: DCK-061 | H62: DCK-CGA2023-J016 | J62: SARL | K62: TEE | S62: 707719624 | T62: 54 | U62: Abidjan | X62: BINGERVILLE | Z62: 44952 | AA62: 1 | AB62: NULL | AG62: 0 | AL62: 0 | AM62: NULL | AN62: NULL | AO62: NULL | AP62: 0 | AQ62: 1 | AR62: NULL | AS62: 1 | AT62: 1
A63: 2230526V | B63: 62 | C63: ARIELLE CONSTRUCTION | D63: NULL | E63: NULL | F63: NULL | G63: DCK-062 | H63: DCK-CGA2023-J022 | I63: NULL | J63: SARL | K63: TEE | L63: NULL | M63: NULL | N63: NULL | O63: Bingerville | P63: NULL | Q63: NULL | R63: NULL | S63: 708410032 | T63: 54 | U63: Abidjan | V63: NULL | W63: NULL | X63: BINGERVILLE | Y63: NULL | Z63: 44953 | AA63: 1 | AB63: NULL | AC63: NULL | AD63: NULL | AE63: NULL | AF63: NULL | AG63: NULL | AH63: NULL | AI63: NULL | AJ63: NULL | AK63: NULL | AL63: NULL | AM63: NULL | AN63: NULL | AO63: NULL | AP63: 3 | AQ63: 1 | AR63: NULL | AS63: 1 | AT63: 1
A64: 2242794R | B64: 63 | C64: BODI NEGOCE TRANSPORT ET BATIMENT SARL | D64: NULL | E64: NULL | F64: NULL | G64: DCK-063 | H64: DCK-CGA2023-J023 | I64: NULL | J64: SARL | K64: TEE | L64: NULL | M64: NULL | N64: NULL | O64: Riviera II | P64: NULL | Q64: NULL | R64: NULL | S64: 709340500 | T64: 54 | U64: Abidjan | V64: NULL | W64: NULL | X64: COCODY FAYA AKOUEDO | Y64: NULL | Z64: 44953 | AA64: 1 | AB64: NULL | AC64: NULL | AD64: NULL | AE64: NULL | AF64: NULL | AG64: NULL | AH64: NULL | AI64: NULL | AJ64: NULL | AK64: NULL | AL64: NULL | AM64: NULL | AN64: NULL | AO64: NULL | AP64: 3 | AQ64: 1 | AR64: NULL | AS64: 1 | AT64: 1
A65: 2244592K | B65: 64 | C65: DIVERS TRAVAUX ET MAINTENANCE | D65: NULL | E65: NULL | F65: NULL | G65: DCK-064 | H65: DCK-CGA2023-J024 | I65: NULL | J65: SARL | K65: TEE | L65: NULL | M65: NULL | N65: NULL | O65: Bingerville | P65: NULL | Q65: NULL | R65: NULL | S65: 759484148 | T65: 54 | U65: Abidjan | V65: NULL | W65: NULL | X65: BINGERVILLE | Y65: NULL | Z65: 44953 | AA65: 1 | AB65: NULL | AC65: NULL | AD65: NULL | AE65: NULL | AF65: NULL | AG65: NULL | AH65: NULL | AI65: NULL | AJ65: NULL | AK65: NULL | AL65: NULL | AM65: NULL | AN65: NULL | AO65: NULL | AP65: 3 | AQ65: 1 | AR65: NULL | AS65: 1 | AT65: 1
A66: 2243163E | B66: 65 | C66: KARMEL'S | D66: NULL | E66: NULL | F66: NULL | G66: DCK-065 | H66: DCK-CGA2023-J025 | I66: NULL | J66: SARL | K66: TEE | L66: NULL | M66: NULL | N66: NULL | O66: Bingerville | P66: NULL | Q66: NULL | R66: NULL | S66: 505095033 | T66: 54 | U66: Abidjan | V66: NULL | W66: NULL | X66: BINGERVILLE | Y66: NULL | Z66: 44953 | AA66: 1 | AB66: NULL | AC66: NULL | AD66: NULL | AE66: NULL | AF66: NULL | AG66: NULL | AH66: NULL | AI66: NULL | AJ66: NULL | AK66: NULL | AL66: NULL | AM66: NULL | AN66: NULL | AO66: NULL | AP66: 3 | AQ66: 1 | AR66: NULL | AS66: 1 | AT66: 1
A67: 2188428W | B67: 66 | C67: TETIALI ALICE | D67: NULL | E67: NULL | F67: NULL | G67: DCK-066 | H67: DCK-CGA2023-J026 | I67: NULL | J67: ENTREPRISE INDIVIDUELLE | K67: TEE | L67: NULL | M67: NULL | N67: NULL | O67: Riviera II | P67: NULL | Q67: NULL | R67: NULL | S67: 102942319 | T67: 54 | U67: Abidjan | V67: NULL | W67: NULL | X67: COCODY AKOUEDO | Y67: NULL | Z67: 44953 | AA67: 1 | AB67: NULL | AC67: NULL | AD67: NULL | AE67: NULL | AF67: NULL | AG67: NULL | AH67: NULL | AI67: NULL | AJ67: NULL | AK67: NULL | AL67: NULL | AM67: NULL | AN67: NULL | AO67: NULL | AP67: 3 | AQ67: 1 | AR67: NULL | AS67: 1 | AT67: 1
A68: 2207048P | B68: 67 | C68: GROUPE RADIUS AFRIQUE | D68: NULL | E68: NULL | F68: NULL | G68: DCK-067 | H68: DCK-CGA2023-J027 | I68: NULL | J68: SARL | K68: TEE | L68: NULL | M68: NULL | N68: NULL | O68: Bingerville | P68: NULL | Q68: NULL | R68: NULL | S68: 565117105 | T68: 54 | U68: Abidjan | V68: NULL | W68: NULL | X68: BINGERVILLE FEKESSE | Y68: NULL | Z68: 44953 | AA68: 1 | AB68: NULL | AC68: NULL | AD68: NULL | AE68: NULL | AF68: NULL | AG68: NULL | AH68: NULL | AI68: NULL | AJ68: NULL | AK68: NULL | AL68: NULL | AM68: NULL | AN68: NULL | AO68: NULL | AP68: 3 | AQ68: 1 | AR68: NULL | AS68: 1 | AT68: 1
A69: 1832429K | B69: 68 | C69: ETS SUCCES | D69: NULL | E69: NULL | F69: NULL | G69: DCK-068 | H69: DCK-CGA2023-J028 | I69: NULL | J69: SARL | K69: TEE | L69: NULL | M69: NULL | N69: NULL | O69: Bingerville | P69: NULL | Q69: NULL | R69: NULL | S69: 153207528 | T69: 54 | U69: Abidjan | V69: NULL | W69: NULL | X69: COCODY ABATTA | Y69: NULL | Z69: 44953 | AA69: 1 | AB69: NULL | AC69: NULL | AD69: NULL | AE69: NULL | AF69: NULL | AG69: NULL | AH69: NULL | AI69: NULL | AJ69: NULL | AK69: NULL | AL69: NULL | AM69: NULL | AN69: NULL | AO69: NULL | AP69: 3 | AQ69: 1 | AR69: NULL | AS69: 1 | AT69: 1
A70: 1907515M | B70: 69 | C70: CANAAN GROUP INDUSTRIE | D70: NULL | E70: NULL | F70: NULL | G70: DCK-069 | H70: DCK-CGA2023-J029 | I70: NULL | J70: SARL | K70: TEE | L70: NULL | M70: NULL | N70: NULL | O70: Riviera I | P70: NULL | Q70: NULL | R70: NULL | S70: 708757335 | T70: 54 | U70: Abidjan | V70: NULL | W70: NULL | X70: COCODY RIVIERA | Y70: NULL | Z70: 44953 | AA70: 1 | AB70: NULL | AC70: NULL | AD70: NULL | AE70: NULL | AF70: NULL | AG70: NULL | AH70: NULL | AI70: NULL | AJ70: NULL | AK70: NULL | AL70: NULL | AM70: NULL | AN70: NULL | AO70: NULL | AP70: 3 | AQ70: 1 | AR70: NULL | AS70: 1 | AT70: 1
A71: 2228002E | B71: 70 | C71: COULIBALY YACOUBA | D71: NULL | E71: NULL | F71: NULL | G71: DCK-070 | H71: DCK-CGA2022-J036 | I71: NULL | J71: ENTREPRISE INDIVIDUELLE | K71: TEE | L71: NULL | M71: NULL | N71: NULL | O71: Bingerville | P71: NULL | Q71: NULL | R71: NULL | S71: 707582582 | T71: 54 | U71: Abidjan | V71: NULL | W71: NULL | X71: ABATTA | Y71: NULL | Z71: 44957 | AA71: 1 | AB71: NULL | AC71: NULL | AD71: NULL | AE71: NULL | AF71: NULL | AG71: NULL | AH71: NULL | AI71: NULL | AJ71: NULL | AK71: NULL | AL71: NULL | AM71: NULL | AN71: NULL | AO71: NULL | AP71: 3 | AQ71: 1 | AR71: NULL | AS71: 1 | AT71: 1
A72: 2242412G | B72: 71 | C72: LOTUS PHARMA SARL | D72: NULL | E72: NULL | F72: NULL | G72: DCK-071 | H72: DCK-CGA2023-J043 | I72: NULL | J72: SARL | K72: TEE | L72: NULL | M72: NULL | N72: NULL | O72: Riviera I | P72: NULL | Q72: NULL | R72: NULL | S72: 757404308 | T72: 54 | U72: Abidjan | V72: NULL | W72: NULL | X72: COCODY RIVERA PALMERAIE | Y72: NULL | Z72: 44957 | AA72: 1 | AB72: NULL | AC72: NULL | AD72: NULL | AE72: NULL | AF72: NULL | AG72: NULL | AH72: NULL | AI72: NULL | AJ72: NULL | AK72: NULL | AL72: NULL | AM72: NULL | AN72: NULL | AO72: NULL | AP72: 3 | AQ72: 1 | AR72: NULL | AS72: 1 | AT72: 1
A73: 2301391H | B73: 72 | C73: DID AFRICA | D73: NULL | E73: NULL | F73: NULL | G73: DCK-072 | H73: DCK-CGA2023-J053 | I73: NULL | J73: SARL | K73: TEE | L73: NULL | M73: NULL | N73: NULL | O73: Bingerville | P73: NULL | Q73: NULL | R73: NULL | S73: 506497308 | T73: 54 | U73: Abidjan | V73: NULL | W73: NULL | X73: BINGERVILLE CITE DES GRACES II | Y73: NULL | Z73: 45099 | AA73: 1 | AB73: NULL | AC73: NULL | AD73: NULL | AE73: NULL | AF73: NULL | AG73: NULL | AH73: NULL | AI73: NULL | AJ73: NULL | AK73: NULL | AL73: NULL | AM73: NULL | AN73: NULL | AO73: NULL | AP73: 3 | AQ73: 1 | AR73: NULL | AS73: 1 | AT73: 1
A74: 1938295X | B74: 73 | C74: ETS ISAHORA | D74: NULL | E74: NULL | F74: NULL | G74: DCK-073 | H74: DCK-CGA2022-J016 | I74: NULL | J74: SARL | K74: TEE | L74: NULL | M74: NULL | N74: NULL | O74: Bingerville | P74: NULL | Q74: NULL | R74: NULL | S74: 708529890 | T74: 54 | U74: Abidjan | V74: NULL | W74: NULL | X74: BINGERVILLE CITE FEKRESSE | Y74: NULL | Z74: 44589 | AA74: 1 | AB74: NULL | AC74: NULL | AD74: NULL | AE74: NULL | AF74: NULL | AG74: NULL | AH74: NULL | AI74: NULL | AJ74: NULL | AK74: NULL | AL74: NULL | AM74: NULL | AN74: NULL | AO74: NULL | AP74: 3 | AQ74: 1 | AR74: NULL | AS74: 1 | AT74: 1
... A81: 1802101W | B81: 80 | C81: FIXWALL BUILDING | D81: NULL | E81: NULL | F81: NULL | G81: DCK-080 | H81: DCK-CGA2022-J009 | I81: NULL | J81: SARL | K81: TEE | L81: NULL | M81: NULL | N81: NULL | O81: Bingerville | P81: NULL | Q81: NULL | R81: NULL | S81: 505040051 | T81: 54 | U81: Abidjan | V81: NULL | W81: NULL | X81: COCODY ABATTA | Y81: NULL | Z81: 44588 | AA81: 1 | AB81: NULL | AC81: NULL | AD81: NULL | AE81: NULL | AF81: NULL | AG81: NULL | AH81: NULL | AI81: NULL | AJ81: NULL | AK81: NULL | AL81: NULL | AM81: NULL | AN81: NULL | AO81: NULL | AP81: 3 | AQ81: 1 | AR81: NULL | AS81: 1 | AT81: 1
A82: 2150505H | B82: 81 | C82: CENTRE OPTIQUE LORIAL | D82: NULL | G82: DCK-081 | H82: DCK-CGA2022-J010 | J82: SARL | K82: TEE | O82: II Plateaux Djibi | S82: 768713339 | T82: 54 | U82: Abidjan | X82: COCODY | Z82: 44588 | AA82: 1 | AB82: NULL | AG82: 0 | AL82: 0 | AM82: NULL | AN82: NULL | AO82: NULL | AP82: 0 | AQ82: 1 | AR82: NULL | AS82: 1 | AT82: 1
A83: 2173312Z | B83: 82 | C83: BODI BONDAH NEGOCE TRAVAUX PUBLIC | D83: NULL | E83: NULL | F83: NULL | G83: DCK-082 | H83: DCK-CGA2022-J017 | I83: NULL | J83: SARL | K83: TEE | L83: NULL | M83: NULL | N83: NULL | O83: Bingerville | P83: NULL | Q83: NULL | R83: NULL | S83: 777237255 | T83: 54 | U83: Abidjan | V83: NULL | W83: NULL | X83: BINGERVILLE ELOITE | Y83: NULL | Z83: 44589 | AA83: 1 | AB83: NULL | AC83: NULL | AD83: NULL | AE83: NULL | AF83: NULL | AG83: NULL | AH83: NULL | AI83: NULL | AJ83: NULL | AK83: NULL | AL83: NULL | AM83: NULL | AN83: NULL | AO83: NULL | AP83: 3 | AQ83: 1 | AR83: NULL | AS83: 1 | AT83: 1
A84: 1602307K | B84: 83 | C84: KOFFI GABOUET BEHIBRO ALFRED | D84: NULL | E84: NULL | F84: NULL | G84: DCK-083 | H84: DCK-CGA2022-J018 | I84: NULL | J84: ENTREPRISE INDIVIDUELLE | K84: TEE | L84: NULL | M84: NULL | N84: NULL | O84: Bingerville | P84: NULL | Q84: NULL | R84: NULL | S84: 708247146 | T84: 54 | U84: Abidjan | V84: NULL | W84: NULL | X84: BINGERVILLE | Y84: NULL | Z84: 44589 | AA84: 1 | AB84: NULL | AC84: NULL | AD84: NULL | AE84: NULL | AF84: NULL | AG84: NULL | AH84: NULL | AI84: NULL | AJ84: NULL | AK84: NULL | AL84: NULL | AM84: NULL | AN84: NULL | AO84: NULL | AP84: 3 | AQ84: 1 | AR84: NULL | AS84: 1 | AT84: 1
A85: 2179332B | B85: 84 | C85: IMAN TRANSIT ET LOGISTIQUES | D85: NULL | G85: DCK-084 | H85: DCK-CGA2022-J020 | J85: SARL | K85: TEE | O85: Bingerville | S85: 789549220 | T85: 54 | U85: Abidjan | X85: COCODY RIVIERA | Z85: 44589 | AA85: 1 | AB85: NULL | AG85: 0 | AL85: 0 | AM85: NULL | AN85: NULL | AO85: NULL | AP85: 0 | AQ85: 1 | AR85: NULL | AS85: 1 | AT85: 1
A86: 2127301Z | B86: 85 | C86: ETS GREEN GARDEN SARL | D86: NULL | E86: NULL | F86: NULL | G86: DCK-085 | H86: DCK-CGA2022-J022 | I86: NULL | J86: SARL | K86: TEE | L86: NULL | M86: NULL | N86: NULL | O86: Bingerville | P86: NULL | Q86: NULL | R86: NULL | S86: 777328417 | T86: 54 | U86: Abidjan | V86: NULL | W86: NULL | X86: BINGERVILLE | Y86: NULL | Z86: 44589 | AA86: 1 | AB86: NULL | AC86: NULL | AD86: NULL | AE86: NULL | AF86: NULL | AG86: NULL | AH86: NULL | AI86: NULL | AJ86: NULL | AK86: NULL | AL86: NULL | AM86: NULL | AN86: NULL | AO86: NULL | AP86: 3 | AQ86: 1 | AR86: NULL | AS86: 1 | AT86: 1
A87: 2045884K | B87: 86 | C87: BRIN 2 DOUCEUR EVENT SARL | D87: NULL | E87: NULL | F87: NULL | G87: DCK-086 | H87: DCK-CGA2022-J023 | I87: NULL | J87: SARL | K87: TEE | L87: NULL | M87: NULL | N87: NULL | O87: Bingerville | P87: NULL | Q87: NULL | R87: NULL | S87: 777973637 | T87: 54 | U87: Abidjan | V87: NULL | W87: NULL | X87: BINGERVILLE SCI CARRIERE | Y87: NULL | Z87: 44589 | AA87: 1 | AB87: NULL | AC87: NULL | AD87: NULL | AE87: NULL | AF87: NULL | AG87: NULL | AH87: NULL | AI87: NULL | AJ87: NULL | AK87: NULL | AL87: NULL | AM87: NULL | AN87: NULL | AO87: NULL | AP87: 3 | AQ87: 1 | AR87: NULL | AS87: 1 | AT87: 1
A88: 2151700M | B88: 87 | C88: NJIR INVEST SARL | D88: NULL | E88: NULL | F88: NULL | G88: DCK-087 | H88: DCK-CGA2022-J025 | I88: NULL | J88: SARL | K88: TEE | L88: NULL | M88: NULL | N88: NULL | O88: Bingerville | P88: NULL | Q88: NULL | R88: NULL | S88: 505199503 | T88: 54 | U88: Abidjan | V88: NULL | W88: NULL | X88: ABATTA | Y88: NULL | Z88: 44589 | AA88: 1 | AB88: NULL | AC88: NULL | AD88: NULL | AE88: NULL | AF88: NULL | AG88: NULL | AH88: NULL | AI88: NULL | AJ88: NULL | AK88: NULL | AL88: NULL | AM88: NULL | AN88: NULL | AO88: NULL | AP88: 3 | AQ88: 1 | AR88: NULL | AS88: 1 | AT88: 1
A89: 2025933F | B89: 89 | C89: E 2 K CONSTRUCTION | D89: 18 | G89: DCK-089 | H89: DCK-CGA2022-J069 | J89: SARL | K89: TEE | O89: Bingerville | S89: 707243416 | T89: 54 | U89: Abidjan | X89: BINGERVILLE | Z89: 44589 | AA89: 1 | AB89: NULL | AG89: 0 | AL89: 0 | AM89: NULL | AN89: NULL | AO89: NULL | AP89: 0 | AQ89: 1 | AR89: NULL | AS89: 1 | AT89: 1
A90: 2190423P | B90: 90 | C90: STENO GROUP | D90: NULL | E90: NULL | F90: NULL | G90: DCK-090 | H90: DCK-CGA2022-J070 | I90: NULL | J90: SARL | K90: TEE | L90: NULL | M90: NULL | N90: NULL | O90: Bingerville | P90: NULL | Q90: NULL | R90: NULL | T90: 54 | U90: Abidjan | V90: NULL | W90: NULL | X90: BINGERVILLE AKANDJE | Y90: NULL | Z90: 44589 | AA90: 1 | AB90: NULL | AC90: NULL | AD90: NULL | AE90: NULL | AF90: NULL | AG90: NULL | AH90: NULL | AI90: NULL | AJ90: NULL | AK90: NULL | AL90: NULL | AM90: NULL | AN90: NULL | AO90: NULL | AP90: 3 | AQ90: 1 | AR90: NULL | AS90: 1 | AT90: 1
A91: 2241802W | B91: 91 | C91: GLORY TEAM INTERNATIONAL | D91: NULL | E91: NULL | F91: NULL | G91: DCK-091 | H91: DCK-CGA2022-J074 | I91: NULL | J91: SARL | K91: TEE | L91: NULL | M91: NULL | N91: NULL | O91: Bingerville | P91: NULL | Q91: NULL | R91: NULL | S91: 777328417 | T91: 54 | U91: Abidjan | V91: NULL | W91: NULL | Y91: NULL | Z91: 44760 | AA91: 1 | AB91: NULL | AC91: NULL | AD91: NULL | AE91: NULL | AF91: NULL | AG91: NULL | AH91: NULL | AI91: NULL | AJ91: NULL | AK91: NULL | AL91: NULL | AM91: NULL | AN91: NULL | AO91: NULL | AP91: 3 | AQ91: 1 | AR91: NULL | AS91: 1 | AT91: 1
A92: 2124572M | B92: 92 | C92: KOUAME KOUAKOU MAXIME | D92: NULL | E92: NULL | F92: NULL | G92: DCK-092 | H92: DCK-CGA2023-J017 | I92: NULL | J92: ENTREPRISE INDIVIDUELLE | K92: TEE | L92: NULL | M92: NULL | N92: NULL | O92: II Plateaux II | P92: NULL | Q92: NULL | R92: NULL | T92: 54 | U92: Abidjan | V92: NULL | W92: NULL | Y92: NULL | Z92: 44951 | AA92: 1 | AB92: NULL | AC92: NULL | AD92: NULL | AE92: NULL | AF92: NULL | AG92: NULL | AH92: NULL | AI92: NULL | AJ92: NULL | AK92: NULL | AL92: NULL | AM92: NULL | AN92: NULL | AO92: NULL | AP92: 3 | AQ92: 1 | AR92: NULL | AS92: 1 | AT92: 1
A93: 2242835K | B93: 93 | C93: YANKAN-MO SARLU | D93: NULL | E93: NULL | F93: NULL | G93: DCK-093 | H93: DCK-CGA2023-J018 | I93: NULL | J93: SARL | K93: TEE | L93: NULL | M93: NULL | N93: NULL | O93: II Plateaux I | P93: NULL | Q93: NULL | R93: NULL | S93: 757118226 | T93: 54 | U93: Abidjan | V93: NULL | W93: NULL | X93: COCODY ANGRE 7E TRANCHE OSCARS | Y93: NULL | Z93: 44951 | AA93: 1 | AB93: NULL | AC93: NULL | AD93: NULL | AE93: NULL | AF93: NULL | AG93: NULL | AH93: NULL | AI93: NULL | AJ93: NULL | AK93: NULL | AL93: NULL | AM93: NULL | AN93: NULL | AO93: NULL | AP93: 3 | AQ93: 1 | AR93: NULL | AS93: 1 | AT93: 1
A94: 2217860F | B94: 94 | C94: KOUMA MAMANI PRESTIGE | D94: NULL | E94: NULL | F94: NULL | G94: DCK-094 | H94: DCK-CGA2023-J032 | I94: NULL | J94: ENTREPRISE INDIVIDUELLE | K94: TEE | L94: NULL | M94: NULL | N94: NULL | O94: II Plateaux I | P94: NULL | Q94: NULL | R94: NULL | T94: 54 | U94: Abidjan | V94: NULL | W94: NULL | Y94: NULL | Z94: 44956 | AA94: 1 | AB94: NULL | AC94: NULL | AD94: NULL | AE94: NULL | AF94: NULL | AG94: NULL | AH94: NULL | AI94: NULL | AJ94: NULL | AK94: NULL | AL94: NULL | AM94: NULL | AN94: NULL | AO94: NULL | AP94: 3 | AQ94: 1 | AR94: NULL | AS94: 1 | AT94: 1
A95: 2245374G | B95: 95 | C95: SAYNI ET SON | D95: NULL | E95: NULL | F95: NULL | G95: DCK-095 | H95: DCK-CGA2023-J035 | I95: NULL | J95: SARL | K95: TEE | L95: NULL | M95: NULL | N95: NULL | O95: Riviera II | P95: NULL | Q95: NULL | R95: NULL | S95: 708824664 | T95: 54 | U95: Abidjan | V95: NULL | W95: NULL | X95: COCODY RIVIERA BONOUMIN | Y95: NULL | Z95: 44956 | AA95: 1 | AB95: NULL | AC95: NULL | AD95: NULL | AE95: NULL | AF95: NULL | AG95: NULL | AH95: NULL | AI95: NULL | AJ95: NULL | AK95: NULL | AL95: NULL | AM95: NULL | AN95: NULL | AO95: NULL | AP95: 3 | AQ95: 1 | AR95: NULL | AS95: 1 | AT95: 1
A96: 2124572M | B96: 96 | C96: GOHI INDUSTRIES GROUP | D96: NULL | E96: NULL | F96: NULL | G96: DCK-096 | H96: DCK-CGA2022-J012 | I96: NULL | J96: SARL | K96: TEE | L96: NULL | M96: NULL | N96: NULL | O96: II Plateaux I | P96: NULL | Q96: NULL | R96: NULL | S96: 709767690 | T96: 54 | U96: Abidjan | V96: NULL | W96: NULL | X96: COCODY ANGRE 7E TRANCHE | Y96: NULL | Z96: 44589 | AA96: 1 | AB96: NULL | AC96: NULL | AD96: NULL | AE96: NULL | AF96: NULL | AG96: NULL | AH96: NULL | AI96: NULL | AJ96: NULL | AK96: NULL | AL96: NULL | AM96: NULL | AN96: NULL | AO96: NULL | AP96: 3 | AQ96: 1 | AR96: NULL | AS96: 1 | AT96: 1
A97: 2186865J | B97: 97 | C97: ASSISTANCE INTERMEDIATE LEADERS ET PARTNERS | D97: NULL | E97: NULL | F97: NULL | G97: DCK-097 | H97: DCK-CGA2022-J015 | I97: NULL | J97: SARL | K97: TEE | L97: NULL | M97: NULL | N97: NULL | O97: II Plateaux I | P97: NULL | Q97: NULL | R97: NULL | S97: 709767690 | T97: 54 | U97: Abidjan | V97: NULL | W97: NULL | X97: COCODY ANGRE 7E TRANCHE | Y97: NULL | Z97: 44589 | AA97: 1 | AB97: NULL | AC97: NULL | AD97: NULL | AE97: NULL | AF97: NULL | AG97: NULL | AH97: NULL | AI97: NULL | AJ97: NULL | AK97: NULL | AL97: NULL | AM97: NULL | AN97: NULL | AO97: NULL | AP97: 3 | AQ97: 1 | AR97: NULL | AS97: 1 | AT97: 1
A98: 2013593F | B98: 98 | C98: GROUPE ZOUHOU ET FILS SARL | D98: NULL | E98: NULL | F98: NULL | G98: DCK-098 | H98: DCK-CGA2022-J034 | I98: NULL | J98: SARL | K98: TEE | L98: NULL | M98: NULL | N98: NULL | O98: Riviera I | P98: NULL | Q98: NULL | R98: NULL | S98: 707278352 | T98: 54 | U98: Abidjan | V98: NULL | W98: NULL | X98: COCODY RIVIERA M'POUTO CITE CAD | Y98: NULL | Z98: 44589 | AA98: 1 | AB98: NULL | AC98: NULL | AD98: NULL | AE98: NULL | AF98: NULL | AG98: NULL | AH98: NULL | AI98: NULL | AJ98: NULL | AK98: NULL | AL98: NULL | AM98: NULL | AN98: NULL | AO98: NULL | AP98: 3 | AQ98: 1 | AR98: NULL | AS98: 1 | AT98: 1
A99: 2166687T | B99: 99 | C99: ENTREPRISE FADIKA IMANE HASSANE HASSANE | D99: 76 | G99: DCK-099 | H99: DCK-CGA2021-Q185 | J99: SARL | K99: TEE | O99: II Pateaux II | S99: 505596296 | T99: 54 | U99: Abidjan | X99: COCODY | Z99: 44490 | AA99: 1 | AB99: NULL | AC99: NULL | AG99: 0 | AL99: 0 | AM99: NULL | AN99: NULL | AO99: NULL | AP99: 0 | AQ99: 1 | AR99: NULL | AS99: 1 | AT99: 1
A100: 2033895A | B100: 100 | C100: N3H IMMOBILIER CÃ”TE D'IVOIRE | D100: NULL | E100: NULL | F100: NULL | G100: DCK-100 | H100: DCK-CGA2022-J046 | I100: NULL | J100: SAS | K100: TEE | L100: NULL | M100: NULL | N100: NULL | O100: Cocody | P100: NULL | Q100: NULL | R100: NULL | T100: 54 | U100: Abidjan | V100: NULL | W100: NULL | X100: COCODY BLAUCKAUSS | Y100: NULL | Z100: 44592 | AA100: 1 | AB100: NULL | AC100: NULL | AD100: NULL | AE100: NULL | AF100: NULL | AG100: NULL | AH100: NULL | AI100: NULL | AJ100: NULL | AK100: NULL | AL100: NULL | AM100: NULL | AN100: NULL | AO100: NULL | AP100: 3 | AQ100: 1 | AR100: NULL | AS100: 1 | AT100: 1
A101: 1814915G | B101: 101 | C101: ELECTRICITE-ELECTRONIQUE-PLURIEL ET ASSISTANCE | D101: NULL | E101: NULL | F101: NULL | G101: DCK-101 | H101: DCK-CGA2022-J013 | I101: NULL | J101: SARL | K101: TEE | L101: NULL | M101: NULL | N101: NULL | O101: II Plateaux I | P101: NULL | Q101: NULL | R101: NULL | S101: 708247146 | T101: 54 | U101: Abidjan | V101: NULL | W101: NULL | X101: COCODY PLATEAU DOKUI | Y101: NULL | Z101: 44589 | AA101: 1 | AB101: NULL | AC101: NULL | AD101: NULL | AE101: NULL | AF101: NULL | AG101: NULL | AH101: NULL | AI101: NULL | AJ101: NULL | AK101: NULL | AL101: NULL | AM101: NULL | AN101: NULL | AO101: NULL | AP101: 3 | AQ101: 1 | AR101: NULL | AS101: 1 | AT101: 1
A102: 2052608M | B102: 102 | C102: CITY ADS | D102: NULL | E102: NULL | F102: NULL | G102: DCK-102 | H102: DCK-CGA2022-J014 | I102: NULL | J102: SARL | K102: TEE | L102: NULL | M102: NULL | N102: NULL | O102: Cocody | P102: NULL | Q102: NULL | R102: NULL | S102: 555800500 | T102: 54 | U102: Abidjan | V102: NULL | W102: NULL | X102: COCODY BLAUCKAUSS | Y102: NULL | Z102: 44589 | AA102: 1 | AB102: NULL | AC102: NULL | AD102: NULL | AE102: NULL | AF102: NULL | AG102: NULL | AH102: NULL | AI102: NULL | AJ102: NULL | AK102: NULL | AL102: NULL | AM102: NULL | AN102: NULL | AO102: NULL | AP102: 3 | AQ102: 1 | AR102: NULL | AS102: 1 | AT102: 1
A103: 2165858D | B103: 103 | C103: SOCIETE DE TRANSPORT MAMADOU ET FRERES | D103: NULL | E103: NULL | F103: NULL | G103: DCK-103 | H103: DCK-CGA2021-Q184 | I103: NULL | J103: SARL | K103: TEE | L103: NULL | M103: NULL | N103: NULL | O103: II Plateaux II | P103: NULL | Q103: NULL | R103: NULL | S103: 757921316 | T103: 54 | U103: Abidjan | V103: NULL | W103: NULL | X103: COCODY II PLATEAUX | Y103: NULL | Z103: 44472 | AA103: 1 | AB103: NULL | AC103: NULL | AD103: NULL | AE103: NULL | AF103: NULL | AG103: NULL | AH103: NULL | AI103: NULL | AJ103: NULL | AK103: NULL | AL103: NULL | AM103: NULL | AN103: NULL | AO103: NULL | AP103: 3 | AQ103: 1 | AR103: NULL | AS103: 1 | AT103: 1
A104: 2037325R | B104: 104 | C104: 2N IMMOBILIER | D104: NULL | E104: NULL | F104: NULL | G104: DCK-104 | H104: DCK-CGA2019-A006 | I104: NULL | J104: SARL | K104: TEE | L104: NULL | M104: NULL | N104: NULL | O104: II Plateaux I | P104: NULL | Q104: NULL | R104: NULL | S104: 708514241 | T104: 54 | U104: Abidjan | V104: NULL | W104: NULL | X104: DEUX PLATEAUX SICOGI | Y104: NULL | Z104: 43479 | AA104: 1 | AB104: NULL | AC104: NULL | AD104: NULL | AE104: NULL | AF104: NULL | AG104: NULL | AH104: NULL | AI104: NULL | AJ104: NULL | AK104: NULL | AL104: NULL | AM104: NULL | AN104: NULL | AO104: NULL | AP104: 3 | AQ104: 1 | AR104: NULL | AS104: 1 | AT104: 1
A105: 1850348X | B105: 105 | C105: 5 PAINS 2 POISSONS | D105: NULL | E105: NULL | F105: NULL | G105: DCK-105 | H105: DCK-CGA2021-Q165 | I105: NULL | J105: SARL | K105: TEE | L105: NULL | M105: NULL | N105: NULL | O105: Cocody | P105: NULL | Q105: NULL | R105: NULL | S105: 708047428 | T105: 54 | U105: Abidjan | V105: NULL | W105: NULL | X105: COCODY CENTRE FACE INADES | Y105: NULL | Z105: 44224 | AA105: 1 | AB105: NULL | AC105: NULL | AD105: NULL | AE105: NULL | AF105: NULL | AG105: NULL | AH105: NULL | AI105: NULL | AJ105: NULL | AK105: NULL | AL105: NULL | AM105: NULL | AN105: NULL | AO105: NULL | AP105: 3 | AQ105: 1 | AR105: NULL | AS105: 1 | AT105: 1
A106: 0309226W | B106: 106 | C106: ABOA DETCHO JEAN PIERRE | D106: NULL | E106: NULL | F106: NULL | G106: DCK-106 | H106: DCK-CGA2021-Q125 | I106: NULL | J106: ENTREPRISE INDIVIDUELLE | K106: TEE | L106: NULL | M106: NULL | N106: NULL | O106: Cocody | P106: NULL | Q106: NULL | R106: NULL | S106: 505074836 | T106: 54 | U106: Abidjan | V106: NULL | W106: NULL | X106: LYCEE TECHNIQUE | Y106: NULL | Z106: 0000-00-00 | AA106: 1 | AB106: NULL | AC106: NULL | AD106: NULL | AE106: NULL | AF106: NULL | AG106: NULL | AH106: NULL | AI106: NULL | AJ106: NULL | AK106: NULL | AL106: NULL | AM106: NULL | AN106: NULL | AO106: NULL | AP106: 3 | AQ106: 1 | AR106: NULL | AS106: 1 | AT106: 1
...
